Workbook

Sheet OCT-19
B2: N° doc | C2: Fecha | D2: Monto Bruto | E2: Forma Pago | F2: 43753 | G2: 43754 | H2: 43755 | I2: 43756 | J2: 43757 | K2: 43758 | L2: 43759 | M2: 43760 | N2: 43761 | O2: 43762 | P2: 43763 | Q2: 43764 | R2: 43765 | S2: 43766 | T2: 43767 | U2: 43768 | V2: 43769
A3: SALDO INICIAL | F3: 0 | G3: =+F17 -> 250000 | H3: =+G17 -> 4335009.4 | I3: =+H17 -> 2818480.3 | J3: =+I17 -> 2818480.3 | K3: =+J17 -> 2818480.3 | L3: =+K17 -> 2818480.3 | M3: =+L17 -> 2818480.3 | N3: =+M17 -> 2818480.3 | ... V3: =+U17 -> 2818480.3
A4: INGRESOS
A5: Aporte LV | D5: 3000000 | F5: 250000 | G5: 2750000
A6: Aporte ML | D6: 3000000 | G6: 3000000
A8: TOTAL INGRESOS | F8: =SUM(F5:F7) -> 250000 | G8: =SUM(G5:G7) -> 5750000 | H8: =SUM(H5:H7) -> 0 | I8: =SUM(I5:I7) -> 0 | J8: =SUM(J5:J7) -> 0 | K8: =SUM(K5:K7) -> 0 | L8: =SUM(L5:L7) -> 0 | M8: =SUM(M5:M7) -> 0 | ... V8: =SUM(V5:V7) -> 0
A10: EGRESOS
A11: GECORP compra 2 equipos | B11: F22584 | C11: 43754 | D11: 1600990 | E11: TC EMS | G11: 1600990
A12: Boleta N°115 EMS Remun. Julio | B12: B115 | D12: 1500000 | E12: transferencia | H12: 1500000
A13: Anticipo Oficina Virtual Pro | B13: F3087 | D13: 64000 | E13: transferencia | G13: =48740*1.19+6000 -> 64000.6
A14: Certificado Electronico Simple | B14: F267835 | C14: 43755 | D14: 16529 | E14: TC EMS | H14: =13890*1.19 -> 16529.1
A16: TOTAL EGRESOS | F16: =SUM(F11:F15) -> 0 | G16: =SUM(G11:G15) -> 1664990.6 | H16: =SUM(H11:H15) -> 1516529.1 | I16: =SUM(I11:I15) -> 0 | J16: =SUM(J11:J15) -> 0 | K16: =SUM(K11:K15) -> 0 | L16: =SUM(L11:L15) -> 0 | M16: =SUM(M11:M15) -> 0 | ... V16: =SUM(V11:V15) -> 0
A17: SALDO FINAL | F17: =+F8+F3-F16 -> 250000 | G17: =+G3+G8-G16 -> 4335009.4 | H17: =+H3+H8-H16 -> 2818480.3 | I17: =+I3+I8-I16 -> 2818480.3 | J17: =+J3+J8-J16 -> 2818480.3 | K17: =+K3+K8-K16 -> 2818480.3 | L17: =+L3+L8-L16 -> 2818480.3 | M17: =+M3+M8-M16 -> 2818480.3 | N17: =+N3+N8-N16 -> 2818480.3 | ... V17: =+V3+V8-V16 -> 2818480.3

Sheet NOV-19
B2: N° doc | C2: Fecha | D2: Monto Bruto | E2: Forma Pago | F2: 43770 | G2: 43771 | H2: 43772 | I2: 43773 | J2: 43774 | K2: 43775 | L2: 43776 | M2: 43777 | N2: 43778 | O2: 43779 | P2: 43780 | Q2: 43781 | R2: 43782 | S2: 43783 | T2: 43784 | U2: 43785 | V2: 43786 | W2: 43787 | X2: 43788 | Y2: 43789 | Z2: 43790 | AA2: 43791 | AB2: 43792 | AC2: 43793 | AD2: 43794 | AE2: 43795 | AF2: 43796 | AG2: 43797 | AH2: 43798 | AI2: 43799
A3: SALDO INICIAL | F3: =+'OCT-19'!V17 -> 2818480.3 | G3: =+F27 -> 2818480.3 | H3: =+G27 -> 2818480.3 | I3: =+H27 -> 2818480.3 | J3: =+I27 -> 2818480.3 | K3: =+J27 -> 2318480.3 | L3: =+K27 -> 2318480.3 | M3: =+L27 -> 2318480.3 | N3: =+M27 -> 2296480.3 | ... AI3: =+AH27 -> 1470292.3
A4: INGRESOS
A6: Factura N° 2 Sofía Jottar | B6: F2 | C6: 43790 | D6: 160200
A7: Factura N° 3 Sofía Jottar | B7: F3 | C7: 43799 | D7: 267000
A8: Aporte LV | F8: 0 | G8: 0
A9: Aporte ML | G9: 0
A11: TOTAL INGRESOS | F11: =SUM(F8:F10) -> 0 | G11: =SUM(G8:G10) -> 0 | H11: =SUM(H8:H10) -> 0 | I11: =SUM(I8:I10) -> 0 | J11: =SUM(J8:J10) -> 0 | K11: =SUM(K8:K10) -> 0 | L11: =SUM(L8:L10) -> 0 | M11: =SUM(M8:M10) -> 0 | ... AI11: =SUM(AI8:AI10) -> 0
A13: EGRESOS
A15: Boleta N° 116 EMS Remun. Oct | B15: B116 | D15: 500000 | E15: transferencia | J15: 500000
A16: Harry Plotter sticker equipos | B16: F32253 | C16: 43777 | D16: 22000 | E16: TC | M16: 22000
A17: SIDTECH OC 100001 2 muebles | B17: F7 | C17: 43780 | D17: =559300 -> 559300 | E17: transferencias | X17: 200000 | Z17: 79650 | AF17: =559300/2 -> 279650
A18: SIDTECH OC 100002 | B18: F8 | C18: 43789 | D18: 125000 | E18: transferencias
A19: LIDER 3 camisas | B19: F 69885019 | C19: 43790 | D19: 12582 | E19: TC | Z19: 12582
A20: Bordado 3 camisas | B20: F 374 | C20: 43789 | D20: 11305 | E20: Transferencia | Z20: 11305
A21: Cilindro 9Kg CO2 | B21: F2485 | C21: 43791 | D21: 138000 | E21: TC | AA21: 138000
A22: Clean Ice Carga 2Kg CO2 | B22: F22146 | C22: 43796 | D22: 4760 | E22: transferencia | AF22: 4760
A23: SIDTECH OC 100003 | B23: F9 | C23: 43798 | D23: =179210*1.395 -> 249997.95 | E23: transferencia | AH23: 0
A24: Anticipo Oficina Virtual Pro | B24: F3087 | C24: 43799 | D24: 64000 | E24: transferencia
A25: RENDICION GASTOS | D25: =100241+56578 -> 156819 | AF25: =+[1]Nov!$B$13 -> 100241 | AI25: =+[1]Nov!$B$27 -> 56578
A26: TOTAL EGRESOS | F26: =SUM(F14:F25) -> 0 | G26: =SUM(G14:G25) -> 0 | H26: =SUM(H14:H25) -> 0 | I26: =SUM(I14:I25) -> 0 | J26: =SUM(J14:J25) -> 500000 | K26: =SUM(K14:K25) -> 0 | L26: =SUM(L14:L25) -> 0 | M26: =SUM(M14:M25) -> 22000 | ... AI26: =SUM(AI14:AI25) -> 56578
A27: SALDO FINAL | F27: =+F11+F3-F26 -> 2818480.3 | G27: =+G3+G11-G26 -> 2818480.3 | H27: =+H3+H11-H26 -> 2818480.3 | I27: =+I3+I11-I26 -> 2818480.3 | J27: =+J3+J11-J26 -> 2318480.3 | K27: =+K3+K11-K26 -> 2318480.3 | L27: =+L3+L11-L26 -> 2318480.3 | M27: =+M3+M11-M26 -> 2296480.3 | N27: =+N3+N11-N26 -> 2296480.3 | ... AI27: =+AI3+AI11-AI26 -> 1413714.3
D28: =+D16+D17+D18+D19+D20+D21+D22 -> 872947
D29: =+D28/1.19 -> 733568.91 | R29: =2296481+3508 -> 2299989
D30: =+D28-D29 -> 139378.09 | R30: =+R29-R27 -> 3508.7
R31: =+M16+'OCT-19'!D14+'OCT-19'!D13 -> 102529

Sheet DIC-19
B2: N° doc | C2: Fecha | D2: Monto Bruto | E2: Forma Pago | F2: 43800 | G2: 43801 | H2: 43802 | I2: 43803 | J2: 43804 | K2: 43805 | L2: 43806 | M2: 43807 | N2: 43808 | O2: 43809 | P2: 43810 | Q2: 43811 | R2: 43812 | S2: 43813 | T2: 43814 | U2: 43815 | V2: 43816 | W2: 43817 | X2: 43818 | Y2: 43819 | Z2: 43820 | AA2: 43821 | AB2: 43822 | AC2: 43823 | AD2: 43824 | AE2: 43825 | AF2: 43826 | AG2: 43827 | AH2: 43828 | AI2: 43829 | AJ2: 43830
A3: SALDO INICIAL | F3: =+'NOV-19'!AI27 -> 1413714.3 | G3: =+F32 -> 1413714.3 | H3: =+G32 -> 1413714.3 | I3: =+H32 -> 1413714.3 | J3: =+I32 -> 1413714.3 | K3: =+J32 -> 913714.3 | L3: =+K32 -> 747047.3 | M3: =+L32 -> 739067.3 | N3: =+M32 -> 739067.3 | ... AJ3: =+AI32 -> 2356809.4
A4: INGRESOS
A5: Factura N° 2 Sofía Jottar | B5: F2 | C5: 43790 | D5: 160200 | E5: cheque | W5: 160200
A6: Factura N° 3 Sofía Jottar | B6: F3 | C6: 43799 | D6: 267000 | E6: cheque
A7: Factura N° 4 Sofía Jottar | B7: F4 | C7: 43805 | D7: 267000 | E7: cheque
A8: Factura N° 5 Sofía Jottar | B8: F5 | C8: 43817 | D8: 267000 | E8: cheque
A9: Factura N° 6 Sofía Jottar | B9: F6 | C9: 43820 | D9: 267000 | E9: cheque
A11: Aporte LV
A12: Aporte ML | AI12: 2500000
A14: TOTAL INGRESOS | F14: =SUM(F5:F13) -> 0 | G14: =SUM(G5:G13) -> 0 | H14: =SUM(H5:H13) -> 0 | I14: =SUM(I5:I13) -> 0 | J14: =SUM(J5:J13) -> 0 | K14: =SUM(K5:K13) -> 0 | L14: =SUM(L5:L13) -> 0 | M14: =SUM(M5:M13) -> 0 | ... AJ14: =SUM(AJ5:AJ13) -> 0
A16: EGRESOS
A17: SIDTECH OC 100002 | B17: F8 | C17: 43789 | D17: 125000 | E17: transferencia | U17: 125000
A18: SIDTECH OC 100003 | B18: F9 | C18: 43798 | D18: =179210*1.395 -> 249997.95 | E18: transferencia | U18: =+D18 -> 249997.95
A19: SIDTECH arr reactor Entregas 19 y 21 de Nov | B19: F10 | C19: 43801 | D19: =162426*1.19 -> 193286.94 | E19: transferencia | AI19: =162426*1.19 -> 193286.94
A20: Boleta N° 117 EMS Remun Nov | B20: B117 | C20: 43804 | D20: 500000 | E20: transferencia | J20: 500000
A21: F29 OCT | C21: 43805 | D21: 166667 | E21: TC | K21: 166667
A22: F29 NOV | C22: 43811 | D22: 59146 | E22: TC | Q22: 59146
A23: Clean Ice Carga 2x 9Kg CO2 | B23: F22462 | C23: 43811 | D23: 32130 | E23: transferencia | Q23: =+D23 -> 32130
A24: SIDTECH OC 100004 200 lt | B24: F20 | C24: 43812 | D24: 250000 | E24: transferencia | L24: =3990*2 -> 7980 | AI24: 250000
A25: SIDTECH OC 100006 2 muebles | B25: F21 | C25: 43812 | D25: 559300
A26: Clean Ice Carga 2Kg CO2 | B26: F22540 | C26: 43815 | D26: 4760 | E26: transferencia | U26: =+D26 -> 4760
A27: INDURA REGULADOR PRESION | B27: F12404 | C27: 43822 | D27: 128137 | E27: TC | AB27: 128137
A28: Boleta N° 119 EMS Remun Agosto | B28: B119 | C28: 44196 | D28: 1500000 | E28: transferencia | AJ28: 1500000
A31: TOTAL EGRESOS | F31: =SUM(F17:F30) -> 0 | G31: =SUM(G17:G30) -> 0 | H31: =SUM(H17:H30) -> 0 | I31: =SUM(I17:I30) -> 0 | J31: =SUM(J17:J30) -> 500000 | K31: =SUM(K17:K30) -> 166667 | L31: =SUM(L17:L30) -> 7980 | M31: =SUM(M17:M30) -> 0 | ... AJ31: =SUM(AJ17:AJ30) -> 1500000
A32: SALDO FINAL | F32: =+F14+F3-F31 -> 1413714.3 | G32: =+G3+G14-G31 -> 1413714.3 | H32: =+H3+H14-H31 -> 1413714.3 | I32: =+I3+I14-I31 -> 1413714.3 | J32: =+J3+J14-J31 -> 913714.3 | K32: =+K3+K14-K31 -> 747047.3 | L32: =+L3+L14-L31 -> 739067.3 | M32: =+M3+M14-M31 -> 739067.3 | N32: =+N3+N14-N31 -> 739067.3 | ... AJ32: =+AJ3+AJ14-AJ31 -> 856809.41
K34: 1074022
K35: =+K32-K34 -> -326974.7
K36: =+'NOV-19'!D16+'NOV-19'!D19+'NOV-19'!D20+'NOV-19'!D21+'NOV-19'!D22+'NOV-19'!D25 -> 345466
K37: =+K36+K35 -> 18491.3
A39: Gastos con Boleta

Sheet ENE-20
B2: N° doc | C2: Fecha | D2: Monto Bruto | E2: Forma Pago | F2: 43831 | G2: 43832 | H2: 43833 | I2: 43834 | J2: 43835 | K2: 43836 | L2: 43837 | M2: 43838 | N2: 43839 | O2: 43840 | P2: 43841 | Q2: 43842 | R2: 43843 | S2: 43844 | T2: 43845 | U2: 43846 | V2: 43847 | W2: 43848 | X2: 43849 | Y2: 43850 | Z2: 43851 | AA2: 43852 | AB2: 43853 | AC2: 43854 | AD2: 43855 | AE2: 43856 | AF2: 43857 | AG2: 43858 | AH2: 43859 | AI2: 43860 | AJ2: 43861
A3: SALDO INICIAL | F3: =+'DIC-19'!AJ32 -> 856809.41 | G3: =+F41 -> 856809.41 | H3: =+G41 -> 856809.41 | I3: =+H41 -> -88840.59 | J3: =+I41 -> -88840.59 | K3: =+J41 -> -88840.59 | L3: =+K41 -> 2389889.4 | M3: =+L41 -> 2092813.4 | N3: =+M41 -> 1792813.4 | ... AJ3: =+AI41 -> 823697.41
A4: INGRESOS
A5: Factura N° 3 Sofía Jottar | B5: F3 | C5: 43799 | D5: 267000 | R5: =+D5 -> 267000
A6: Factura N° 4 Sofía Jottar | B6: F4 | C6: 43805 | D6: 267000 | E6: cheque | R6: =+D6 -> 267000
A7: Factura N° 5 Sofía Jottar | B7: F5 | C7: 43817 | D7: 267000 | E7: cheque
A8: Factura N° 6 Sofía Jottar | B8: F6 | C8: 43820 | D8: 267000 | E8: cheque
A9: Factura N° 7 Sofía Jottar | B9: F7 | C9: 43836 | D9: 267000 | E9: cheque
A10: Factura N° 8 Sofía Jottar | B10: F8 | C10: 43848 | D10: 160200 | E10: cheque
A11: Aporte LV | F11: 0 | G11: 0 | K11: 2500000
A12: Aporte ML | G12: 0
A16: TOTAL INGRESOS | F16: =SUM(F5:F15) -> 0 | G16: =SUM(G5:G15) -> 0 | H16: =SUM(H5:H15) -> 0 | I16: =SUM(I5:I15) -> 0 | J16: =SUM(J5:J15) -> 0 | K16: =SUM(K5:K15) -> 2500000 | L16: =SUM(L5:L15) -> 0 | M16: =SUM(M5:M15) -> 0 | ... AJ16: =SUM(AJ5:AJ15) -> 0
A18: EGRESOS
A19: SIDTECH OC 100007 | B19: F22 | C19: 43819 | D19: 250000 | E19: transferencia | O19: =+D19 -> 250000
A20: SIDTECH arr 2 reactor Entregas 19 y 21 de Nov | B20: F24 | C20: 43832 | D20: 177220 | E20: transferencia | AA20: =+D20 -> 177220
A21: GECORP compra 1 equipo 100 lt/min pinchadores devueltos | B21: F23501 | C21: 43833 | D21: 930125 | E21: TC EMS | H21: 930125
A22: GECORP compra accesorio equipo | B22: F23502 | C22: 43833 | D22: 3145 | E22: TC EMS | H22: 3145
A23: EASY PINTURA BLANCA MUEBLE | B23: F21509946 | C23: 43833 | D23: 12380 | E23: TC EMS | H23: 12380
A24: EASY PINTURA BLANCA MUEBLE BROCHA | B24: F21519808 | C24: 43836 | D24: 17580 | E24: TC EMS | K24: =+D24 -> 17580
A25: HOMECENTER arriendo caladora | B25: F102451374 | C25: 43836 | D25: 3690 | E25: TC EMS | K25: =+D25 -> 3690
A26: SIDTECH OC 100008 | B26: F25 | C26: 43836 | D26: 250000 | E26: transferencia | AH26: =+D26 -> 250000
A27: LANCER 2 regul, cil CO2 2.3Kg, mang | B27: F1065034 | C27: 43837 | D27: 297076 | E27: TC EMS | L27: =+D27 -> 297076
A28: Boleta N° 1 Brand Book | B28: B1 | C28: 43838 | D28: 440735 | E28: transferencia | M28: 300000 | R28: 140735
A29: ESMAX flete Casa Liberona a Huidobro a SIDTECH a Casa Mardones | B29: B168270027 | C29: 43840 | D29: 15024 | E29: TC EMS | O29: =+D29 -> 15024
A30: Boleta N° 120 EMS Remun Dic | B30: B120 | C30: 43841 | D30: 500000 | E30: transferencia | P30: =+D30 -> 500000
A31: F29 DIC | B31: 6895175876 | C31: 43843 | D31: =+R31 -> 228954 | E31: TC EMS | R31: 228954
A32: GECORP compra 1 equipo 100 lt/min pinchadores devueltos | B32: NC1990 | C32: 43843 | D32: -97968 | R32: =+D32 -> -97968
A33: Clean Ice Carga 2Kg CO2 | B33: F23187 | C33: 43844 | D33: 3570 | E33: transferencia | S33: =+D33 -> 3570
A34: COPEC flete a SIDTECH a JOTTAR a HUIDOBRO | B34: B856145 | C34: 43845 | D34: 17000 | E34: TC EMS | T34: =+D34 -> 17000
A35: UBER flete Cilindro CO2 SIDTECH a JOTTAR | C35: 43848 | D35: =+W35 -> 15011 | E35: TC EMS | W35: 15011
A36: Clean Ice Carga 2Kg CO2 | B36: F23402 | C36: 43853 | D36: 3570 | E36: transferencia | AB36: =+D36 -> 3570
A37: Flete Vitacura-Sofia Jottar | B37: B249931041 | C37: 43861 | D37: 7000 | E37: TC EMS | AJ37: =+D37 -> 7000
A40: TOTAL EGRESOS | F40: =SUM(F19:F39) -> 0 | G40: =SUM(G19:G39) -> 0 | H40: =SUM(H19:H39) -> 945650 | I40: =SUM(I19:I39) -> 0 | J40: =SUM(J19:J39) -> 0 | K40: =SUM(K19:K39) -> 21270 | L40: =SUM(L19:L39) -> 297076 | M40: =SUM(M19:M39) -> 300000 | ... AJ40: =SUM(AJ19:AJ39) -> 7000
A41: SALDO FINAL | F41: =+F16+F3-F40 -> 856809.41 | G41: =+G3+G16-G40 -> 856809.41 | H41: =+H3+H16-H40 -> -88840.59 | I41: =+I3+I16-I40 -> -88840.59 | J41: =+J3+J16-J40 -> -88840.59 | K41: =+K3+K16-K40 -> 2389889.4 | L41: =+L3+L16-L40 -> 2092813.4 | M41: =+M3+M16-M40 -> 1792813.4 | N41: =+N3+N16-N40 -> 1792813.4 | ... AJ41: =+AJ3+AJ16-AJ40 -> 816697.41

Sheet FEB-20
B2: N° doc | C2: Fecha | D2: Monto Bruto | E2: Forma Pago | F2: 43862 | G2: 43863 | H2: 43864 | I2: 43865 | J2: 43866 | K2: 43867 | L2: 43868 | M2: 43869 | N2: 43870 | O2: 43871 | P2: 43872 | Q2: 43873 | R2: 43874 | S2: 43875 | T2: 43876 | U2: 43877 | V2: 43878 | W2: 43879 | X2: 43880 | Y2: 43881 | Z2: 43882 | AA2: 43883 | AB2: 43884 | AC2: 43885 | AD2: 43886 | AE2: 43887 | AF2: 43888 | AG2: 43889 | AH2: 43890
A3: SALDO INICIAL | F3: =+'ENE-20'!AJ41 -> 816697.41 | G3: =+F42 -> 816697.41 | H3: =+G42 -> 816697.41 | I3: =+H42 -> 786632.41 | J3: =+I42 -> 786632.41 | K3: =+J42 -> 786632.41 | L3: =+K42 -> 774632.41 | M3: =+L42 -> 774632.41 | N3: =+M42 -> 774632.41 | ... AH3: =+AG42 -> -85085.59
A4: INGRESOS
A5: Factura N° 5 Sofía Jottar | B5: F5 | C5: 43817 | D5: 267000 | E5: cheque
A6: Factura N° 6 Sofía Jottar | B6: F6 | C6: 43820 | D6: 267000 | E6: cheque
A7: Factura N° 7 Sofía Jottar | B7: F7 | C7: 43836 | D7: 267000 | E7: cheque
A8: Factura N° 8 Sofía Jottar | B8: F8 | C8: 43848 | D8: 160200 | E8: cheque
A9: Factura N° 9 Sofía Jottar | B9: F9 | C9: 43865 | D9: 160200 | E9: cheque
A10: Factura N° 10 Sofía Jottar | B10: F10 | C10: 43866 | D10: 33728 | E10: cheque
A11: Factura N° 11 Sofía Jottar | B11: F11 | C11: 43876 | D11: 160200 | E11: cheque
A12: Factura N° 12 Sofía Jottar | B12: F12 | C12: 43882 | D12: 160200 | E12: cheque
A14: Aporte LV | F14: 0 | G14: 0
A15: Aporte ML | G15: 0
A18: TOTAL INGRESOS | F18: =SUM(F5:F17) -> 0 | G18: =SUM(G5:G17) -> 0 | H18: =SUM(H5:H17) -> 0 | I18: =SUM(I5:I17) -> 0 | J18: =SUM(J5:J17) -> 0 | K18: =SUM(K5:K17) -> 0 | L18: =SUM(L5:L17) -> 0 | M18: =SUM(M5:M17) -> 0 | ... AH18: =SUM(AH5:AH17) -> 0
A20: EGRESOS
A21: Clean Ice Carga 9Kg CO2 | B21: F23682 | C21: 43864 | D21: 16065 | E21: transferencia | H21: =+D21 -> 16065
A22: Flete Vitacura-CleanIce-Mercatelli-C.Huid-Gecorp-Vitacura | B22: B11294 | C22: 43864 | D22: 14000 | E22: TC EMS | H22: =+D22 -> 14000
A23: Boleta N° 121 EMS Remun Enero 2020 | B23: B121 | C23: 43867 | D23: 500000 | E23: transferencia | R23: =+D23 -> 500000
A24: Boleta N°122 Remun Variable Gerente | B24: B122 | C24: 43867 | D24: 118014 | R24: =('DIC-19'!W5+'ENE-20'!R5+'ENE-20'!R6)*0.17 -> 118014
A25: F29 Enero | C25: 43871 | D25: =+R25 -> 116900 | O25: =+'DIC-19'!J18*(1/0.9-1) -> 0 | R25: 116900
A26: Flete Vitacura-Gecorp-C.Huid-Mercatelli-Vitacura | B26: B255234562 | C26: 43867 | D26: 12000 | E26: TC EMS | K26: =+D26 -> 12000
A27: Flete Vitacura-S.Jottar-Vitacura | B27: B255856778 | C27: 43875 | D27: 7070 | E27: TC EMS | S27: 7070
A28: Flete Vitacura-S.Jottar-Vitacura | B28: B255857604 | C28: 43876 | D28: 7500 | E28: TC EMS | T28: 7500
A29: Flete Vitacura-El Establo-Cleanice-El Establo-S.Jottar-Vitacura | B29: B256141175 | C29: 43879 | D29: 13000 | E29: TC EMS | W29: 13000
A30: 10 botellas Sauvignon Blanc para test LANCER | B30: F31263917 | C30: 43879 | D30: 15959 | E30: TC EMS | W30: 15959
A31: Clean Ice Carga 9Kg+9Kg+2Kg CO2 | B31: F23989 | C31: 43879 | D31: 35700 | E31: transferencia | W31: 35700
A32: Flete Vitacura-CasaGH-S.Jottar-Vitacura | B32: B256243695 | C32: 43881 | D32: 8017 | E32: TC EMS | Y32: 8017
A33: Flete Vitacura-SIDTECH-CasaGH-S.Jottar-Vitacura | B33: B256329633 | C33: 43882 | D33: 14639 | E33: TC EMS | Z33: 14639
A34: UBER flete 60lt SIDTECH a JOTTAR | C34: 43882 | D34: 18185 | E34: TC EMS
A35: CALENDULA 1 lt alcohol de cereal | B35: F3136 | C35: 43885 | D35: 3325 | E35: TC EMS | AC35: 3325
A36: UBER flete 60lt SIDTECH a JOTTAR | C36: 43889 | D36: 19594 | E36: TC EMS | AG36: 19594
A41: TOTAL EGRESOS | F41: =SUM(F21:F37) -> 0 | G41: =SUM(G21:G37) -> 0 | H41: =SUM(H21:H37) -> 30065 | I41: =SUM(I21:I37) -> 0 | J41: =SUM(J21:J37) -> 0 | K41: =SUM(K21:K37) -> 12000 | L41: =SUM(L21:L37) -> 0 | M41: =SUM(M21:M37) -> 0 | ... AH41: =SUM(AH21:AH37) -> 0
A42: SALDO FINAL | F42: =+F18+F3-F41 -> 816697.41 | G42: =+G3+G18-G41 -> 816697.41 | H42: =+H3+H18-H41 -> 786632.41 | I42: =+I3+I18-I41 -> 786632.41 | J42: =+J3+J18-J41 -> 786632.41 | K42: =+K3+K18-K41 -> 774632.41 | L42: =+L3+L18-L41 -> 774632.41 | M42: =+M3+M18-M41 -> 774632.41 | N42: =+N3+N18-N41 -> 774632.41 | ... AH42: =+AH3+AH18-AH41 -> -85085.59

Sheet MAR-20
B2: N° doc | C2: Fecha | D2: Monto Bruto | E2: Forma Pago | F2: 43891 | G2: 43892 | H2: 43893 | I2: 43894 | J2: 43895 | K2: 43896 | L2: 43897 | M2: 43898 | N2: 43899 | O2: 43900 | P2: 43901 | Q2: 43902 | R2: 43903 | S2: 43904 | T2: 43905 | U2: 43906 | V2: 43907 | W2: 43908 | X2: 43909 | Y2: 43910 | Z2: 43911 | AA2: 43912 | AB2: 43913 | AC2: 43914 | AD2: 43915 | AE2: 43916 | AF2: 43917 | AG2: 43918 | AH2: 43919 | AI2: 43920 | AJ2: 43921
A3: SALDO INICIAL | F3: =+'FEB-20'!AH42 -> -85085.59 | G3: =+F58 -> -85085.59 | H3: =+G58 -> -85085.59 | I3: =+H58 -> -85085.59 | J3: =+I58 -> -85085.59 | K3: =+J58 -> -85085.59 | L3: =+K58 -> -85085.59 | M3: =+L58 -> -85085.59 | N3: =+M58 -> -85085.59 | ... AJ3: =+AI58 -> 1026449.7
A4: INGRESOS
A5: Factura N° 5 Sofía Jottar | B5: F5 | C5: 43817 | D5: 267000 | E5: cheque | AJ5: 0
A6: Factura N° 9 Sofía Jottar | B6: F9 | C6: 43865 | D6: 160200 | E6: cheque
A7: Factura N° 10 Sofía Jottar | B7: F10 | C7: 43866 | D7: 33728 | E7: cheque
A8: Factura N° 11 Sofía Jottar | B8: F11 | C8: 43876 | D8: 160200 | E8: cheque
A9: Factura N° 12 Sofía Jottar | B9: F12 | C9: 43882 | D9: 160200 | E9: cheque
D10: =SUM(D6:D9)*1.19 -> 612050.32
A11: Aporte LV | F11: 0 | G11: 0
A12: Aporte ML | D12: 2500000 | G12: 0 | W12: 2500000
A13: Remanente IVA
A16: TOTAL INGRESOS | F16: =SUM(F5:F15) -> 0 | G16: =SUM(G5:G15) -> 0 | H16: =SUM(H5:H15) -> 0 | I16: =SUM(I5:I15) -> 0 | J16: =SUM(J5:J15) -> 0 | K16: =SUM(K5:K15) -> 0 | L16: =SUM(L5:L15) -> 0 | M16: =SUM(M5:M15) -> 0 | ... AJ16: =SUM(AJ5:AJ15) -> 0
A18: EGRESOS
A19: Flete Vitacura-SJottar-Vitacura | B19: B258439138 | C19: 43906 | D19: 4278 | E19: TC EMS | U19: 4278
A20: SIDTECH arr 3 reactor Entregas 19 y 21 de Nov y 15 de Enero | B20: F26 | C20: 43864 | D20: 285243 | E20: =+D20/3 -> 95081 | AJ20: 0
A21: SIDTECH mueble+vino | B21: F27 | C21: 43884 | D21: 253499 | W21: 253499
A22: SIDTECH arr 3 reactor Entregas 19 y 21 de Nov y 15 de Enero+vino | B22: F28 | C22: 43890 | D22: 220655 | E22: =+(81600+3*21008)*1.19 -> 172102.56
A23: ANALAB preparación mezcla Aperol | B23: F194283 | C23: 43892 | D23: =45500*1.19 -> 54145 | G23: 0
A24: Boleta N° 123 EMS Remun Febrero 2020 | B24: B123 | C24: 43896 | D24: 500000 | E24: transferencia | W24: =+D24 -> 500000
A25: Flete Vitacura-SIDTECH-Vitacura | B25: B2237829 | C25: 43900 | D25: 8500 | E25: TC EMS | O25: 8500
A26: F29 Febrero | C26: 43902 | D26: 75855.737 | X26: =+(('FEB-20'!D23+'FEB-20'!D24)/0.8925)*0.1075+0.0025*SUM('ABR-20'!D9:D13)/1.19 -> 75855.737
A27: Clean Ice Carga 9Kg+2Kg CO2 | B27: F24588 | C27: 43902 | D27: 19635 | E27: transferencia | Q27: 19635
A28: FERSOL tambor 60 lt una boca | B28: F3861 | C28: 43902 | D28: 11662 | E28: transferencia | Q28: 11662
A29: CALENDULA 4 lt alcohol de cereal | B29: F3265 | C29: 43902 | D29: 14000 | E29: TC EMS | Q29: 14000
A30: Flete Vitacura-Cleanice-Wenco-Fersol-Sjottar-Vitacura | B30: B258222749 | C30: 43902 | D30: 15903 | E30: TC EMS | Q30: 15903
A31: UNIMARC 8X6 LT agua+5 kg azucar | B31: F31511712 | C31: 43902 | D31: 14490 | E31: TC EMS | Q31: 14490
A32: SABORES Ltda. Ingredientes Aperol | B32: F84289 | C32: 43902 | D32: 116875 | E32: transferencia | Q32: 116875
A33: FERNAPET Balanza 500 +/- 1 gramo | B33: F58956 | C33: 43902 | D33: 4990 | E33: TC EMS | Q33: 4990
A34: Flete Vitacura-SIDTECH-S.Jottar-Vitacura | B34: B258279430 | C34: 43903 | D34: 15000 | E34: TC EMS | R34: 15000
A35: Flete Vitacura-SJottar-Vitacura | B35: B258333151 | C35: 43904 | D35: 7037 | E35: TC EMS | S35: 7037
A36: SIDTECH vino | B36: F29 | C36: 43905 | D36: 125998
A37: TOTTUS alargador electrico | B37: B484741684 | C37: 43906 | D37: 3990 | E37: TC EMS | U37: 3990
A38: SIDTECH vino+mezcla+llenado Spritz | B38: F30 | C38: 43906 | D38: 24395
A39: SIDTECH OC 100010 1000 lt vino abono 20% | B39: F32 | C39: 43909 | D39: 250007 | E39: transferencia | W39: 250000
A40: Flete Vitacura-Chicureo-Vitacura 18 y 20 Marzo | B40: B258613719 | C40: 43910 | D40: 14750 | E40: TC EMS | Y40: 14750
A41: Oficina Virtual | B41: F36 | C41: 43916 | D41: =58000 -> 58000 | E41: transferencia | W41: 58000
A42: SIDTECH arr 3 reactor Entregas 19 y 21 de Nov y 15 de Enero | B42: F33 | C42: 43920 | D42: 149048 | E42: =83500*1.19*14/30 -> 46370.333
C44: AF | D44: =+D21+D28+D33+D37 -> 274141
A48: Insumos 500 lt Laura Seyler Spritz | B48: xxxx | C48: xxx | D48: 370000
A49: LANCER carbonatador | D49: =431000*1.19 -> 512890
A50: 100 Bolsas 10 lt | D50: =2150*100*1.19 -> 255850
A51: 2 Cilindro CO2 9Kg | D51: =138000*2 -> 276000
A52: cilindro CO2 2 Kg | D52: =65000*1.19 -> 77350
A53: Equipo llenado de bolsas artesanal | D53: 200000
A54: Equipo llenado de bolsas mecanizado | D54: 800000
A57: TOTAL EGRESOS | F57: =SUM(F19:F56) -> 0 | G57: =SUM(G19:G56) -> 0 | H57: =SUM(H19:H56) -> 0 | I57: =SUM(I19:I56) -> 0 | J57: =SUM(J19:J56) -> 0 | K57: =SUM(K19:K56) -> 0 | L57: =SUM(L19:L56) -> 0 | M57: =SUM(M19:M56) -> 0 | ... AJ57: =SUM(AJ19:AJ56) -> 0
A58: SALDO FINAL | F58: =+F16+F3-F57 -> -85085.59 | G58: =+G3+G16-G57 -> -85085.59 | H58: =+H3+H16-H57 -> -85085.59 | I58: =+I3+I16-I57 -> -85085.59 | J58: =+J3+J16-J57 -> -85085.59 | K58: =+K3+K16-K57 -> -85085.59 | L58: =+L3+L16-L57 -> -85085.59 | M58: =+M3+M16-M57 -> -85085.59 | N58: =+N3+N16-N57 -> -85085.59 | ... AJ58: =+AJ3+AJ16-AJ57 -> 1026449.7

Sheet ABR-20
B2: N° doc | C2: Fecha | D2: Monto Bruto | E2: Forma Pago | F2: 43922 | G2: 43923 | H2: 43924 | I2: 43925 | J2: 43926 | K2: 43927 | L2: 43928 | M2: 43929 | N2: 43930 | O2: 43931 | P2: 43932 | Q2: 43933 | R2: 43934 | S2: 43935 | T2: 43936 | U2: 43937 | V2: 43938 | W2: 43939 | X2: 43940 | Y2: 43941 | Z2: 43942 | AA2: 43943 | AB2: 43944 | AC2: 43945 | AD2: 43946 | AE2: 43947 | AF2: 43948 | AG2: 43949 | AH2: 43950 | AI2: 43951
A3: SALDO INICIAL | F3: =+'MAR-20'!AJ58 -> 1026449.7 | G3: =+F34 -> 1026449.7 | H3: =+G34 -> 1026449.7 | I3: =+H34 -> 1026449.7 | J3: =+I34 -> 1026449.7 | K3: =+J34 -> 1026449.7 | L3: =+K34 -> 1026449.7 | M3: =+L34 -> 1026449.7 | N3: =+M34 -> 1293449.7 | ... AI3: =+AH34 -> 97707.584
A4: INGRESOS
A5: Factura N° 5 Sofía Jottar | B5: F5 | C5: 43817 | D5: 267000 | E5: transferencia | M5: 267000
A6: Factura N° 6 Sofía Jottar | B6: F6 | C6: 43820 | D6: 267000 | E6: cheque
A7: Factura N° 7 Sofía Jottar | B7: F7 | C7: 43836 | D7: 267000 | E7: cheque
A8: Factura N° 8 Sofía Jottar | B8: F8 | C8: 43848 | D8: 160200 | E8: cheque
A9: Factura N° 9 Sofía Jottar | B9: F9 | C9: 43865 | D9: 160200 | E9: cheque
A10: Factura N° 10 Sofía Jottar | B10: F10 | C10: 43866 | D10: 33728 | E10: cheque
A11: Factura N° 11 Sofía Jottar | B11: F11 | C11: 43876 | D11: 160200 | E11: cheque
A12: Factura N° 12 Sofía Jottar | B12: F12 | C12: 43882 | D12: 160200 | E12: cheque
A13: Factura N° 13 Sofía Jottar | B13: F13 | C13: 43889 | D13: 160200 | E13: cheque
A14: Factura N° 14 Sofía Jottar | B14: F14 | C14: 43892 | D14: =28475.41*1.19 -> 33885.738 | E14: cheque
A15: Factura N° 15 Sofía Jottar | B15: F15 | C15: 43904 | D15: 160200 | E15: cheque
A16: Factura N° XX Sofía Jottar SPRITZ | B16: FXX | D16: =4500*60 -> 270000
A18: Aporte LV | F18: 0 | G18: 0
A19: Aporte ML | G19: 0
A20: Remanente IVA | D20: 2001574
A23: TOTAL INGRESOS | F23: =SUM(F6:F22) -> 0 | G23: =SUM(G6:G22) -> 0 | H23: =SUM(H6:H22) -> 0 | I23: =SUM(I6:I22) -> 0 | J23: =SUM(J6:J22) -> 0 | K23: =SUM(K6:K22) -> 0 | L23: =SUM(L6:L22) -> 0 | M23: =SUM(M5:M22) -> 267000 | N23: =SUM(N6:N22) -> 0 | O23: =SUM(O6:O22) -> 0 | P23: =SUM(P6:P22) -> 0 | Q23: =SUM(Q6:Q22) -> 0 | R23: =SUM(R6:R22) -> 0 | S23: =SUM(S6:S22) -> 0 | T23: =SUM(T6:T22) -> 0 | U23: =SUM(U6:U22) -> 0 | ... AI23: =SUM(AI6:AI22) -> 0
A25: EGRESOS
A26: SIDTECH vino+mezcla+llenado Spritz | B26: F30 | C26: 43906 | D26: 24395 | E26: transferencia | S26: 24395
A27: SIDTECH vino | B27: F29 | C27: 43905 | D27: 124998 | AF27: 124998
A28: Boleta N° 124 EMS Remun Marzo 2020 | B28: B124 | C28: 43926 | D28: 500000 | O28: 500000
A29: F29 Marzo | O29: =+'MAR-20'!W24*0.1075/0.8925+('ABR-20'!D14+'ABR-20'!D15)*0.0025*0 -> 60224.09
A30: Boleta N° 2 saldo Brand Book | B30: B2 | D30: 440735 | N30: 440735
A31: Boleta N°125 Remun Variable Gerente | B31: B125 | D31: 45390 | O31: =+M5*0.17 -> 45390
A33: TOTAL EGRESOS | F33: =SUM(F26:F32) -> 0 | G33: =SUM(G26:G32) -> 0 | H33: =SUM(H26:H32) -> 0 | I33: =SUM(I26:I32) -> 0 | J33: =SUM(J26:J32) -> 0 | K33: =SUM(K26:K32) -> 0 | L33: =SUM(L26:L32) -> 0 | M33: =SUM(M26:M32) -> 0 | ... AI33: =SUM(AI26:AI32) -> 0
A34: SALDO FINAL | F34: =+F23+F3-F33 -> 1026449.7 | G34: =+G3+G23-G33 -> 1026449.7 | H34: =+H3+H23-H33 -> 1026449.7 | I34: =+I3+I23-I33 -> 1026449.7 | J34: =+J3+J23-J33 -> 1026449.7 | K34: =+K3+K23-K33 -> 1026449.7 | L34: =+L3+L23-L33 -> 1026449.7 | M34: =+M3+M23-M33 -> 1293449.7 | N34: =+N3+N23-N33 -> 852714.67 | ... AI34: =+AI3+AI23-AI33 -> 97707.584

Sheet MAY-20
B2: N° doc | C2: Fecha | D2: Monto Bruto | E2: Forma Pago | F2: 43952 | G2: 43953 | H2: 43954 | I2: 43955 | J2: 43956 | K2: 43957 | L2: 43958 | M2: 43959 | N2: 43960 | O2: 43961 | P2: 43962 | Q2: 43963 | R2: 43964 | S2: 43965 | T2: 43966 | U2: 43967 | V2: 43968 | W2: 43969 | X2: 43970 | Y2: 43971 | Z2: 43972 | AA2: 43973 | AB2: 43974 | AC2: 43975 | AD2: 43976 | AE2: 43977 | AF2: 43978 | AG2: 43979 | AH2: 43980 | AI2: 43981 | AJ2: 43982
A3: SALDO INICIAL | F3: =+'ABR-20'!AI34 -> 97707.584 | G3: =+F33 -> 97707.584 | H3: =+G33 -> 97707.584 | I3: =+H33 -> 97707.584 | J3: =+I33 -> 97707.584 | K3: =+J33 -> -2292.4163 | L3: =+K33 -> -2292.4163 | M3: =+L33 -> -2292.4163 | N3: =+M33 -> -2292.4163 | ... AJ3: =+AI33 -> -2292.4163
A4: INGRESOS
A5: Factura N° 6 Sofía Jottar | B5: F6 | C5: 43820 | D5: 267000
A6: Factura N° 7 Sofía Jottar | B6: F7 | C6: 43836 | D6: 267000
A7: Factura N° 8 Sofía Jottar | B7: F8 | C7: 43848 | D7: 160200
A8: Factura N° 9 Sofía Jottar | B8: F9 | C8: 43865 | D8: 160200
A9: Factura N° 10 Sofía Jottar | B9: F10 | C9: 43866 | D9: 33728
A10: Factura N° 11 Sofía Jottar | B10: F11 | C10: 43876 | D10: 160200
A11: Factura N° 12 Sofía Jottar | B11: F12 | C11: 43882 | D11: 160200
A12: Factura N° 13 Sofía Jottar | B12: F13 | C12: 43889 | D12: 160200
A13: Factura N° 14 Sofía Jottar | B13: F14 | C13: 43892 | D13: =28475.41*1.19 -> 33885.738
A14: Factura N° 15 Sofía Jottar | B14: F15 | C14: 43904 | D14: 160200
A15: Factura N° XX Sofía Jottar SPRITZ | B15: FXX | D15: =4500*60 -> 270000 | E15: por facturar
A17: Aporte LV | F17: 0 | G17: 0
A18: Aporte ML | G18: 0
A19: Remanente IVA | D19: 2001574
A22: TOTAL INGRESOS | F22: =SUM(F5:F21) -> 0 | G22: =SUM(G5:G21) -> 0 | H22: =SUM(H5:H21) -> 0 | I22: =SUM(I5:I21) -> 0 | J22: =SUM(J5:J21) -> 0 | K22: =SUM(K5:K21) -> 0 | L22: =SUM(L5:L21) -> 0 | M22: =SUM(M5:M21) -> 0 | ... AJ22: =SUM(AJ5:AJ21) -> 0
A24: EGRESOS
A25: SIDTECH OC 100006 2 muebles | B25: F21 | C25: 43812 | D25: 559300
A26: Boleta N° xxx EMS Remun Abril 2020 | B26: Bxxx | D26: 500000
A27: Boleta N°xxx Remun Variable Gerente | B27: Bxxx | D27: =+(D5+D6+D7)*0.17 -> 118014
A28: SIDTECH OC 100010 1000 lt vino saldo 80% | B28: FXX | D28: =1250000-250000- 2150*1.19*100 -> 744150
A29: SIDTECH arr 3 reactor Entregas 19 y 21 de Nov y 15 de Enero | B29: F26 | C29: 43864 | D29: 285243
A30: Pyme Asesores Declaracion Renta | B30: F Ex 493 | D30: 100000 | J30: 100000
A32: TOTAL EGRESOS | F32: =SUM(F25:F31) -> 0 | G32: =SUM(G25:G31) -> 0 | H32: =SUM(H25:H31) -> 0 | I32: =SUM(I25:I31) -> 0 | J32: =SUM(J25:J31) -> 100000 | K32: =SUM(K25:K31) -> 0 | L32: =SUM(L25:L31) -> 0 | M32: =SUM(M25:M31) -> 0 | ... AJ32: =SUM(AJ25:AJ31) -> 0
A33: SALDO FINAL | F33: =+F22+F3-F32 -> 97707.584 | G33: =+G3+G22-G32 -> 97707.584 | H33: =+H3+H22-H32 -> 97707.584 | I33: =+I3+I22-I32 -> 97707.584 | J33: =+J3+J22-J32 -> -2292.4163 | K33: =+K3+K22-K32 -> -2292.4163 | L33: =+L3+L22-L32 -> -2292.4163 | M33: =+M3+M22-M32 -> -2292.4163 | N33: =+N3+N22-N32 -> -2292.4163 | ... AJ33: =+AJ3+AJ22-AJ32 -> -2292.4163

Sheet JUN-20
B2: N° doc | C2: Fecha | D2: Monto Bruto | E2: Forma Pago | F2: 43983 | G2: 43984 | H2: 43985 | I2: 43986 | J2: 43987 | K2: 43988 | L2: 43989 | M2: 43990 | N2: 43991 | O2: 43992 | P2: 43993 | Q2: 43994 | R2: 43995 | S2: 43996 | T2: 43997 | U2: 43998 | V2: 43999 | W2: 44000 | X2: 44001 | Y2: 44002 | Z2: 44003 | AA2: 44004 | AB2: 44005 | AC2: 44006 | AD2: 44007 | AE2: 44008 | AF2: 44009 | AG2: 44010 | AH2: 44011 | AI2: 44012
A3: SALDO INICIAL | F3: =+'MAY-20'!AJ33 -> -2292.4163 | G3: =+F35 -> -2292.4163 | H3: =+G35 -> -2292.4163 | I3: =+H35 -> -2292.4163 | J3: =+I35 -> -2292.4163 | K3: =+J35 -> -2292.4163 | L3: =+K35 -> -2292.4163 | M3: =+L35 -> -2292.4163 | N3: =+M35 -> -2292.4163 | ... AI3: =+AH35 -> -2292.4163
A4: INGRESOS
A5: Factura N° 6 Sofía Jottar | B5: F6 | C5: 43820 | D5: 267000
A6: Factura N° 7 Sofía Jottar | B6: F7 | C6: 43836 | D6: 267000
A7: Factura N° 8 Sofía Jottar | B7: F8 | C7: 43848 | D7: 160200
A8: Factura N° 9 Sofía Jottar | B8: F9 | C8: 43865 | D8: 160200
A9: Factura N° 10 Sofía Jottar | B9: F10 | C9: 43866 | D9: 33728
A10: Factura N° 11 Sofía Jottar | B10: F11 | C10: 43876 | D10: 160200
A11: Factura N° 12 Sofía Jottar | B11: F12 | C11: 43882 | D11: 160200
A12: Factura N° 13 Sofía Jottar | B12: F13 | C12: 43889 | D12: 160200
A13: Factura N° 14 Sofía Jottar | B13: F14 | C13: 43892 | D13: =28475.41*1.19 -> 33885.738
A14: Factura N° 15 Sofía Jottar | B14: F15 | C14: 43904 | D14: 160200
A15: Factura N° XX Sofía Jottar SPRITZ | B15: FXX | D15: =4500*60 -> 270000 | E15: por facturar
A16: GECORP N/C 1990 | B16: NC 1990 | C16: 43843 | D16: 97968 | AI16: =+D16 -> 97968
A17: SII DEVOLUCION PPM 2019
A19: Aporte LV | F19: 0 | G19: 0
A20: Aporte ML | G20: 0
A21: Remanente IVA | D21: 2001574
A24: TOTAL INGRESOS | F24: =SUM(F5:F23) -> 0 | G24: =SUM(G5:G23) -> 0 | H24: =SUM(H5:H23) -> 0 | I24: =SUM(I5:I23) -> 0 | J24: =SUM(J5:J23) -> 0 | K24: =SUM(K5:K23) -> 0 | L24: =SUM(L5:L23) -> 0 | M24: =SUM(M5:M23) -> 0 | ... AI24: =SUM(AI5:AI23) -> 97968
A26: EGRESOS
A27: SIDTECH OC 100006 2 muebles | B27: F21 | C27: 43812 | D27: 559300
A28: Boleta N° xxx EMS Remun Abril 2020 | B28: Bxxx | D28: 500000
A29: Boleta N° xxx EMS Remun Mayo 2020 | B29: Bxxx | D29: 500000
A30: Boleta N°xxx Remun Variable Gerente | B30: Bxxx | D30: =+(D5+D6+D7)*0.17 -> 118014
A31: SIDTECH OC 100010 1000 lt vino saldo 80% | B31: FXX | D31: =1250000-250000- 2150*1.19*100 -> 744150
A32: SIDTECH arr 3 reactor Entregas 19 y 21 de Nov y 15 de Enero | B32: F26 | C32: 43864 | D32: 285243
A34: TOTAL EGRESOS | F34: =SUM(F27:F33) -> 0 | G34: =SUM(G27:G33) -> 0 | H34: =SUM(H27:H33) -> 0 | I34: =SUM(I27:I33) -> 0 | J34: =SUM(J27:J33) -> 0 | K34: =SUM(K27:K33) -> 0 | L34: =SUM(L27:L33) -> 0 | M34: =SUM(M27:M33) -> 0 | ... AI34: =SUM(AI27:AI33) -> 0
A35: SALDO FINAL | F35: =+F24+F3-F34 -> -2292.4163 | G35: =+G3+G24-G34 -> -2292.4163 | H35: =+H3+H24-H34 -> -2292.4163 | I35: =+I3+I24-I34 -> -2292.4163 | J35: =+J3+J24-J34 -> -2292.4163 | K35: =+K3+K24-K34 -> -2292.4163 | L35: =+L3+L24-L34 -> -2292.4163 | M35: =+M3+M24-M34 -> -2292.4163 | N35: =+N3+N24-N34 -> -2292.4163 | ... AI35: =+AI3+AI24-AI34 -> 95675.584

Sheet JUL-20
B2: N° doc | C2: Fecha | D2: Monto Bruto | E2: Forma Pago | F2: 44013 | G2: 44014 | H2: 44015 | I2: 44016 | J2: 44017 | K2: 44018 | L2: 44019 | M2: 44020 | N2: 44021 | O2: 44022 | P2: 44023 | Q2: 44024 | R2: 44025 | S2: 44026 | T2: 44027 | U2: 44028 | V2: 44029 | W2: 44030 | X2: 44031 | Y2: 44032 | Z2: 44033 | AA2: 44034 | AB2: 44035 | AC2: 44036 | AD2: 44037 | AE2: 44038 | AF2: 44039 | AG2: 44040 | AH2: 44041 | AI2: 44042 | AJ2: 44043
A3: SALDO INICIAL | F3: =+'JUN-20'!AI35 -> 95675.584 | G3: =+F38 -> 95675.584 | H3: =+G38 -> 95675.584 | I3: =+H38 -> 95675.584 | J3: =+I38 -> 95675.584 | K3: =+J38 -> 95675.584 | L3: =+K38 -> 95675.584 | M3: =+L38 -> 95675.584 | N3: =+M38 -> 95675.584 | ... AJ3: =+AI38 -> 62605.584
A4: INGRESOS
A5: Factura N° 6 Sofía Jottar | B5: F6 | C5: 43820 | D5: 267000
A6: Factura N° 7 Sofía Jottar | B6: F7 | C6: 43836 | D6: 267000
A7: Factura N° 8 Sofía Jottar | B7: F8 | C7: 43848 | D7: 160200
A8: Factura N° 9 Sofía Jottar | B8: F9 | C8: 43865 | D8: 160200
A9: Factura N° 10 Sofía Jottar | B9: F10 | C9: 43866 | D9: 33728
A10: Factura N° 11 Sofía Jottar | B10: F11 | C10: 43876 | D10: 160200
A11: Factura N° 12 Sofía Jottar | B11: F12 | C11: 43882 | D11: 160200
A12: Factura N° 13 Sofía Jottar | B12: F13 | C12: 43889 | D12: 160200
A13: Factura N° 14 Sofía Jottar | B13: F14 | C13: 43892 | D13: =28475.41*1.19 -> 33885.738
A14: Factura N° 15 Sofía Jottar | B14: F15 | C14: 43904 | D14: 160200
A15: Factura N° XX Sofía Jottar SPRITZ | B15: FXX | D15: =4500*60 -> 270000 | E15: por facturar
A16: SII DEVOLUCION PPM 2019 | C16: 43980 | D16: 10465 | V16: 0
A18: Aporte LV | F18: 0 | G18: 0
A19: Aporte ML | G19: 0
A20: Remanente IVA | D20: 2001574
A23: TOTAL INGRESOS | F23: =SUM(F5:F22) -> 0 | G23: =SUM(G5:G22) -> 0 | H23: =SUM(H5:H22) -> 0 | I23: =SUM(I5:I22) -> 0 | J23: =SUM(J5:J22) -> 0 | K23: =SUM(K5:K22) -> 0 | L23: =SUM(L5:L22) -> 0 | M23: =SUM(M5:M22) -> 0 | ... AJ23: =SUM(AJ5:AJ22) -> 0
A25: EGRESOS
A26: SIDTECH OC 100006 2 muebles | B26: F21 | C26: 43812 | D26: 559300
A27: Boleta N° xxx EMS Remun Abril 2020 | B27: Bxxx | D27: 500000
A28: Boleta N° xxx EMS Remun Mayo 2020 | B28: Bxxx | D28: 500000
A29: Boleta N° xxx EMS Remun Junio 2020 | B29: Bxxx | D29: =500000/2 -> 250000
A30: Boleta N°xxx Remun Variable Gerente | B30: Bxxx | D30: =+(D5+D6+D7)*0.17 -> 118014
A31: SIDTECH OC 100010 1000 lt vino saldo 80% | B31: FXX | D31: =1250000-250000- 2150*1.19*100 -> 744150
A32: SIDTECH arr 3 reactor Entregas 19 y 21 de Nov y 15 de Enero | B32: F26 | C32: 43864 | D32: 285243
A33: Corretajes Torres | B33: F1130 | C33: 44004 | D33: =7500*1.19 -> 8925 | O33: =7500*1.19 -> 8925
A34: ANALAB preparación mezcla Aperol | B34: F194283 | C34: 43892 | D34: =45500*1.19 -> 54145 | O34: =54145-30000 -> 24145
A37: TOTAL EGRESOS | F37: =SUM(F26:F34) -> 0 | G37: =SUM(G26:G34) -> 0 | H37: =SUM(H26:H34) -> 0 | I37: =SUM(I26:I34) -> 0 | J37: =SUM(J26:J34) -> 0 | K37: =SUM(K26:K34) -> 0 | L37: =SUM(L26:L34) -> 0 | M37: =SUM(M26:M34) -> 0 | ... AJ37: =SUM(AJ26:AJ34) -> 0
A38: SALDO FINAL | F38: =+F23+F3-F37 -> 95675.584 | G38: =+G3+G23-G37 -> 95675.584 | H38: =+H3+H23-H37 -> 95675.584 | I38: =+I3+I23-I37 -> 95675.584 | J38: =+J3+J23-J37 -> 95675.584 | K38: =+K3+K23-K37 -> 95675.584 | L38: =+L3+L23-L37 -> 95675.584 | M38: =+M3+M23-M37 -> 95675.584 | N38: =+N3+N23-N37 -> 95675.584 | ... AJ38: =+AJ3+AJ23-AJ37 -> 62605.584

Sheet AGO-20
B2: N° doc | C2: Fecha | D2: Monto Bruto | E2: Forma Pago | F2: 44044 | G2: 44045 | H2: 44046 | I2: 44047 | J2: 44048 | K2: 44049 | L2: 44050 | M2: 44051 | N2: 44052 | O2: 44053 | P2: 44054 | Q2: 44055 | R2: 44056 | S2: 44057 | T2: 44058 | U2: 44059 | V2: 44060 | W2: 44061 | X2: 44062 | Y2: 44063 | Z2: 44064 | AA2: 44065 | AB2: 44066 | AC2: 44067 | AD2: 44068 | AE2: 44069 | AF2: 44070 | AG2: 44071 | AH2: 44072 | AI2: 44073 | AJ2: 44074
A3: SALDO INICIAL | F3: =+'JUL-20'!AJ38 -> 62605.584 | G3: =+F44 -> 62605.584 | H3: =+G44 -> 62605.584 | I3: =+H44 -> 62605.584 | J3: =+I44 -> 62605.584 | K3: =+J44 -> 62605.584 | L3: =+K44 -> -2145.4163 | M3: =+L44 -> -2145.4163 | N3: =+M44 -> -2145.4163 | ... AJ3: =+AI44 -> -18210.416
A4: INGRESOS
A5: Factura N° 6 Sofía Jottar | B5: F6 | C5: 43820 | D5: 267000
A6: Factura N° 7 Sofía Jottar | B6: F7 | C6: 43836 | D6: 267000
A7: Factura N° 8 Sofía Jottar | B7: F8 | C7: 43848 | D7: 160200
A8: Factura N° 9 Sofía Jottar | B8: F9 | C8: 43865 | D8: 160200
A9: Factura N° 10 Sofía Jottar | B9: F10 | C9: 43866 | D9: 33728
A10: Factura N° 11 Sofía Jottar | B10: F11 | C10: 43876 | D10: 160200
A11: Factura N° 12 Sofía Jottar | B11: F12 | C11: 43882 | D11: 160200
A12: Factura N° 13 Sofía Jottar | B12: F13 | C12: 43889 | D12: 160200
A13: Factura N° 14 Sofía Jottar | B13: F14 | C13: 43892 | D13: =28475.41*1.19 -> 33885.738
A14: Factura N° 15 Sofía Jottar | B14: F15 | C14: 43904 | D14: 160200
A15: Factura N° XX Sofía Jottar SPRITZ | B15: FXX | D15: =4500*60 -> 270000 | E15: por facturar
A16: SII DEVOLUCION PPM 2019 | C16: 43980 | D16: 10465
A18: Aporte LV | F18: 0 | G18: 0
A19: Aporte ML | G19: 0
A20: Remanente IVA | D20: 2001574
A23: TOTAL INGRESOS | F23: =SUM(F5:F22) -> 0 | G23: =SUM(G5:G22) -> 0 | H23: =SUM(H5:H22) -> 0 | I23: =SUM(I5:I22) -> 0 | J23: =SUM(J5:J22) -> 0 | K23: =SUM(K5:K22) -> 0 | L23: =SUM(L5:L22) -> 0 | M23: =SUM(M5:M22) -> 0 | ... AJ23: =SUM(AJ5:AJ22) -> 0
A25: EGRESOS
A26: SIDTECH OC 100006 2 muebles | B26: F21 | C26: 43812 | D26: 559300
A27: Boleta N° xxx EMS Remun Abril 2020 | B27: Bxxx | D27: 500000
A28: Boleta N° xxx EMS Remun Mayo 2020 | B28: Bxxx | D28: 500000
A29: Boleta N° xxx EMS Remun Junio 2020 | B29: Bxxx | D29: =500000/2 -> 250000
A30: Boleta N° xxx EMS Remun Julio 2020 | B30: Bxxx | D30: =500000/2 -> 250000
A31: Boleta N°xxx Remun Variable Gerente | B31: Bxxx | D31: =+(D5+D6+D7)*0.17 -> 118014
A32: SIDTECH OC 100010 1000 lt vino saldo 80% | B32: FXX | D32: =1250000-250000- 2150*1.19*100 -> 744150
A33: SIDTECH arr 3 reactor Entregas 19 y 21 de Nov y 15 de Enero | B33: F26 | C33: 43864 | D33: 285243
A34: ANALAB preparación mezcla Aperol | B34: F194283 | C34: 43892 | D34: =45500*1.19 -> 54145 | E34: Transfer
A35: VIÑA STA. CAROLINA 1.5X9X12 lt Chardonnay | B35: Boleta N°xxx7282 | C35: 44049 | D35: 48000 | E35: TC | K35: 48000
A36: Av. Ricardo Mahn 2 bidones 30 lt | B36: sin boleta | C36: 44049 | D36: =2500*2 -> 5000 | E36: Transfer | K36: 5000
A37: Flete Vitacura-Viña Sta Carolina-Vitacura | B37: B181419 | C37: 44049 | D37: =(18.6*703/9+1265)*2 -> 5435.7333 | E37: TC EMS | K37: 5436
A38: UNIMARC AGUA AZUCAR | B38: F31909557 | C38: 44053 | D38: 6315 | E38: TC | K38: 6315
A39: CLEAN ICE recarga 9 Kg CO2 | B39: F26833 | C39: 44068 | D39: 16065 | E39: Transfer | AD39: 16065
A43: TOTAL EGRESOS | F43: =SUM(F26:F42) -> 0 | G43: =SUM(G26:G42) -> 0 | H43: =SUM(H26:H42) -> 0 | I43: =SUM(I26:I42) -> 0 | J43: =SUM(J26:J42) -> 0 | K43: =SUM(K26:K42) -> 64751 | L43: =SUM(L26:L42) -> 0 | M43: =SUM(M26:M42) -> 0 | ... AJ43: =SUM(AJ26:AJ42) -> 0
A44: SALDO FINAL | F44: =+F23+F3-F43 -> 62605.584 | G44: =+G3+G23-G43 -> 62605.584 | H44: =+H3+H23-H43 -> 62605.584 | I44: =+I3+I23-I43 -> 62605.584 | J44: =+J3+J23-J43 -> 62605.584 | K44: =+K3+K23-K43 -> -2145.4163 | L44: =+L3+L23-L43 -> -2145.4163 | M44: =+M3+M23-M43 -> -2145.4163 | N44: =+N3+N23-N43 -> -2145.4163 | ... AJ44: =+AJ3+AJ23-AJ43 -> -18210.416

Sheet SEPT-20
B2: N° doc | C2: Fecha | D2: Monto Bruto | E2: Forma Pago | F2: 44075 | G2: 44076 | H2: 44077 | I2: 44078 | J2: 44079 | K2: 44080 | L2: 44081 | M2: 44082 | N2: 44083 | O2: 44084 | P2: 44085 | Q2: 44086 | R2: 44087 | S2: 44088 | T2: 44089 | U2: 44090 | V2: 44091 | W2: 44092 | X2: 44093 | Y2: 44094 | Z2: 44095 | AA2: 44096 | AB2: 44097 | AC2: 44098 | AD2: 44099 | AE2: 44100 | AF2: 44101 | AG2: 44102 | AH2: 44103 | AI2: 44104 | AJ2: TOTAL
A3: SALDO INICIAL | F3: =+'AGO-20'!AJ44 -> -18210.416 | G3: =+F39 -> -18210.416 | H3: =+G39 -> -18210.416 | I3: =+H39 -> -18210.416 | J3: =+I39 -> -18210.416 | K3: =+J39 -> -18210.416 | L3: =+K39 -> -18210.416 | M3: =+L39 -> -18210.416 | N3: =+M39 -> -18210.416 | ... AI3: =+AH39 -> -18210.416
A4: INGRESOS
A5: Factura N° 6 Sofía Jottar | B5: F6 | C5: 43820 | D5: 267000 | AJ5: =SUM(E5:AI5) -> 0
A6: Factura N° 7 Sofía Jottar | B6: F7 | C6: 43836 | D6: 267000 | AJ6: =SUM(E6:AI6) -> 0
A7: Factura N° 8 Sofía Jottar | B7: F8 | C7: 43848 | D7: 160200 | AJ7: =SUM(E7:AI7) -> 0
A8: Factura N° 9 Sofía Jottar | B8: F9 | C8: 43865 | D8: 160200 | AJ8: =SUM(E8:AI8) -> 0
A9: Factura N° 10 Sofía Jottar | B9: F10 | C9: 43866 | D9: 33728 | AJ9: =SUM(E9:AI9) -> 0
A10: Factura N° 11 Sofía Jottar | B10: F11 | C10: 43876 | D10: 160200 | AJ10: =SUM(E10:AI10) -> 0
A11: Factura N° 12 Sofía Jottar | B11: F12 | C11: 43882 | D11: 160200 | AJ11: =SUM(E11:AI11) -> 0
A12: Factura N° 13 Sofía Jottar | B12: F13 | C12: 43889 | D12: 160200 | AJ12: =SUM(E12:AI12) -> 0
A13: Factura N° 14 Sofía Jottar | B13: F14 | C13: 43892 | D13: =28475.41*1.19 -> 33885.738 | AJ13: =SUM(E13:AI13) -> 0
A14: Factura N° 15 Sofía Jottar | B14: F15 | C14: 43904 | D14: 160200 | AJ14: =SUM(E14:AI14) -> 0
A15: Factura N° XX Sofía Jottar SPRITZ | B15: FXX | D15: =4500*60 -> 270000 | E15: por facturar | AJ15: =SUM(E15:AI15) -> 0
A16: SII DEVOLUCION PPM 2019 | C16: 43980 | D16: 10465 | AJ16: =SUM(E16:AI16) -> 0
A17: SUBTOTAL VENTAS | AJ17: =SUM(AJ5:AJ16) -> 0
A18: Aporte LV | F18: 0 | G18: 0
A19: Aporte ML | G19: 0
A20: Remanente IVA | D20: 2001574
A23: TOTAL INGRESOS | F23: =SUM(F5:F22) -> 0 | G23: =SUM(G5:G22) -> 0 | H23: =SUM(H5:H22) -> 0 | I23: =SUM(I5:I22) -> 0 | J23: =SUM(J5:J22) -> 0 | K23: =SUM(K5:K22) -> 0 | L23: =SUM(L5:L22) -> 0 | M23: =SUM(M5:M22) -> 0 | ... AI23: =SUM(AI5:AI22) -> 0
A25: EGRESOS
A26: SIDTECH OC 100006 2 muebles | B26: F21 | C26: 43812 | D26: 559300
A27: Boleta N° xxx EMS Remun Abril 2020 | B27: Bxxx | D27: 500000
A28: Boleta N° xxx EMS Remun Mayo 2020 | B28: Bxxx | D28: 500000
A29: Boleta N° xxx EMS Remun Junio 2020 | B29: Bxxx | D29: =500000/2 -> 250000
A30: Boleta N° xxx EMS Remun Julio 2020 | B30: Bxxx | D30: =500000/2 -> 250000
A31: Boleta N° xxx EMS Remun Agosto 2020 | B31: Bxxx | D31: =500000/2 -> 250000
A32: Boleta N°xxx Remun Variable Gerente | B32: Bxxx | D32: =+(D5+D6+D7)*0.17 -> 118014
A33: SIDTECH OC 100010 1000 lt vino saldo 80% | B33: FXX | D33: =1250000-250000- 2150*1.19*100 -> 744150
A34: SIDTECH arr 3 reactor Entregas 19 y 21 de Nov y 15 de Enero | B34: F26 | C34: 43864 | D34: 285243
A35: ANALAB preparación mezcla Aperol | B35: F194283 | C35: 43892 | D35: =45500*1.19 -> 54145 | E35: Transfer
A36: Oficina Virtual al 16 de Octubre | D36: 109000
A38: TOTAL EGRESOS | F38: =SUM(F26:F37) -> 0 | G38: =SUM(G26:G37) -> 0 | H38: =SUM(H26:H37) -> 0 | I38: =SUM(I26:I37) -> 0 | J38: =SUM(J26:J37) -> 0 | K38: =SUM(K26:K37) -> 0 | L38: =SUM(L26:L37) -> 0 | M38: =SUM(M26:M37) -> 0 | ... AI38: =SUM(AI26:AI37) -> 0
A39: SALDO FINAL | F39: =+F23+F3-F38 -> -18210.416 | G39: =+G3+G23-G38 -> -18210.416 | H39: =+H3+H23-H38 -> -18210.416 | I39: =+I3+I23-I38 -> -18210.416 | J39: =+J3+J23-J38 -> -18210.416 | K39: =+K3+K23-K38 -> -18210.416 | L39: =+L3+L23-L38 -> -18210.416 | M39: =+M3+M23-M38 -> -18210.416 | N39: =+N3+N23-N38 -> -18210.416 | ... AI39: =+AI3+AI23-AI38 -> -18210.416

Sheet OCT-20
B2: N° doc | C2: Fecha | D2: Monto Bruto | E2: Forma Pago | F2: 44105 | G2: 44106 | H2: 44107 | I2: 44108 | J2: 44109 | K2: 44110 | L2: 44111 | M2: 44112 | N2: 44113 | O2: 44114 | P2: 44115 | Q2: 44116 | R2: 44117 | S2: 44118 | T2: 44119 | U2: 44120 | V2: 44121 | W2: 44122 | X2: 44123 | Y2: 44124 | Z2: 44125 | AA2: 44126 | AB2: 44127 | AC2: 44128 | AD2: 44129 | AE2: 44130 | AF2: 44131 | AG2: 44132 | AH2: 44133 | AI2: 44134 | AJ2: 44135 | AK2: TOTAL
A3: SALDO INICIAL | F3: =+'SEPT-20'!AI39 -> -18210.416 | G3: =+F51 -> -18210.416 | H3: =+G51 -> -18210.416 | I3: =+H51 -> -18210.416 | J3: =+I51 -> -18210.416 | K3: =+J51 -> -18210.416 | L3: =+K51 -> -18210.416 | M3: =+L51 -> -18210.416 | N3: =+M51 -> -18210.416 | ... AJ3: =+AI51 -> 164750.04
A4: INGRESOS
A5: Factura N° 6 Sofía Jottar | B5: F6 | C5: 43820 | D5: 267000 | AK5: =SUM(F5:AJ5) -> 0
A6: Factura N° 7 Sofía Jottar | B6: F7 | C6: 43836 | D6: 267000 | AK6: =SUM(F6:AJ6) -> 0
A7: Factura N° 8 Sofía Jottar | B7: F8 | C7: 43848 | D7: 160200 | AK7: =SUM(F7:AJ7) -> 0
A8: Factura N° 9 Sofía Jottar | B8: F9 | C8: 43865 | D8: 160200 | AK8: =SUM(F8:AJ8) -> 0
A9: Factura N° 10 Sofía Jottar | B9: F10 | C9: 43866 | D9: 33728 | AK9: =SUM(F9:AJ9) -> 0
A10: Factura N° 11 Sofía Jottar | B10: F11 | C10: 43876 | D10: 160200 | AK10: =SUM(F10:AJ10) -> 0
A11: Factura N° 12 Sofía Jottar | B11: F12 | C11: 43882 | D11: 160200 | AK11: =SUM(F11:AJ11) -> 0
A12: Factura N° 13 Sofía Jottar | B12: F13 | C12: 43889 | D12: 160200 | AK12: =SUM(F12:AJ12) -> 0
A13: Factura N° 14 Sofía Jottar | B13: F14 | C13: 43892 | D13: =28475.41*1.19 -> 33885.738 | AK13: =SUM(F13:AJ13) -> 0
A14: Factura N° 15 Sofía Jottar | B14: F15 | C14: 43904 | D14: 160200 | AK14: =SUM(F14:AJ14) -> 0
A15: Factura N° XX Sofía Jottar SPRITZ | B15: FXX | D15: =4500*60 -> 270000 | E15: por facturar | AK15: =SUM(F15:AJ15) -> 0
A16: Factura N° 25 Marina | B16: F25 | C16: 44127 | D16: 62665 | AI16: 62665 | AK16: =SUM(F16:AJ16) -> 62665
A17: SUBTOTAL VENTAS | AK17: =SUM(AK5:AK16) -> 62665
A18: CREDITO BANCO ESTADO | T18: 500000
A19: Gastos no reembolsado EMS acumuldo al 14 Oct | S19: 18210
A20: Aporte LV | F20: 0 | G20: 0
A21: Aporte ML | G21: 0
A24: TOTAL INGRESOS | F24: =SUM(F5:F23) -> 0 | G24: =SUM(G5:G23) -> 0 | H24: =SUM(H5:H23) -> 0 | I24: =SUM(I5:I23) -> 0 | J24: =SUM(J5:J23) -> 0 | K24: =SUM(K5:K23) -> 0 | L24: =SUM(L5:L23) -> 0 | M24: =SUM(M5:M23) -> 0 | ... AJ24: =SUM(AJ5:AJ23) -> 0
A26: EGRESOS
A27: SIDTECH OC 100006 2 muebles | B27: F21 | C27: 43812 | D27: =559300*0 -> 0
A28: Boleta N° xxx EMS Remun Abril 2020 | B28: Bxxx | D28: 500000
A29: Boleta N° xxx EMS Remun Mayo 2020 | B29: Bxxx | D29: 500000
A30: Boleta N° xxx EMS Remun Junio 2020 | B30: Bxxx | D30: =500000/2 -> 250000
A31: Boleta N° xxx EMS Remun Julio 2020 | B31: Bxxx | D31: =500000/2 -> 250000
A32: Boleta N° xxx EMS Remun Agosto 2020 | B32: Bxxx | D32: =500000/2 -> 250000
A33: Boleta N°xxx Remun Variable Gerente | B33: Bxxx | D33: =+(D5+D6+D7)*0.17 -> 118014 | AI33: =+(AJ5+AJ6+AJ7)*0.17 -> 0 | AJ33: =SUM(AJ8:AJ15)*0.17 -> 0
A34: SIDTECH OC 100010 1000 lt vino saldo 80% | B34: FXX | D34: =(1250000-250000- 2150*1.19*100)*0 -> 0 | AJ34: =(1250000-250000- 2150*1.19*100)*0 -> 0
A35: SIDTECH arr 3 reactor Entregas 19 y 21 de Nov y 15 de Enero | B35: F26 | C35: 43864 | D35: =285243*0 -> 0 | AJ35: =100*850*1.19*0 -> 0
A36: Oficina Virtual al 16 de Octubre | D36: 171000 | E36: Transfer Estado | U36: 171000
A37: Flete Vitacura-Emb.La Colonia Peñaflor-Vitacura | C37: 44104 | D37: =1509.36+2936.91+601+41+525+259+57.4*2*822/9 -> 16357.337 | E37: Transfer Estado | Z37: =1509.36+2936.91+601+41+525+259+57.4*2*822/9 -> 16357.337
A38: LANCER arriendo 1 equipo | B38: F1069066 | C38: 44112 | D38: =60000*1.19 -> 71400 | E38: Transfer Estado | V38: =60000*1.19 -> 71400
A39: Flete Vitacura-SIDTECH San Joaquin-Vitacura | C39: 44125 | D39: =1509.36+2936.91+601+41+525+259+39.2*822/9 -> 9452.5367 | E39: Transfer Estado | Z39: =1509.36+2936.91+601+41+525+259+39.2*822/9 -> 9452.5367
A40: Flete Vitacura-Renca-Requinoa-Recoleta-Vitacura | C40: 44126 | D40: =2615+1313+389+788+407+560+644+377+337+614+285+1237+3800+2700*2+283*780/9 -> 43292.667 | E40: Transfer Estado | AA40: =2615+1313+389+788+407+560+644+377+337+614+285+1237+3800+2700*2+283*780/9 -> 43292.667
A41: LANCER embolsado+ caja 40 lt | B41: F1069201 | C41: 44126 | D41: =12800*1.19 -> 15232 | E41: Transfer Estado | AB41: =12800*1.19 -> 15232
A42: TAGLER | B42: F11147260 | C42: 44126 | D42: =11500*1.19 -> 13685 | E42: Transfer Estado | AA42: =11500*1.19 -> 13685
A43: firma.cl | B43: F34231 | C43: 44127 | D43: 14161 | E43: TC | AB43: 14161
A44: HOMECENTER Pintura | B44: F107907716 | C44: 44127 | D44: 5489 | E44: TC | AB44: 5489
A45: Reembolso a EMS gastos no reembolsados al 14Oct | C45: 23-0ct | D45: =-'SEPT-20'!Z39 -> 18210.416 | E45: Transfer Estado | AB45: 18210
A46: Clean Ice | B46: F28050 | C46: 44134 | D46: 19635 | E46: Transfer | AI46: 19635
F50: =SUM(F27:F46) -> 0 | G50: =SUM(G27:G46) -> 0 | H50: =SUM(H27:H46) -> 0 | I50: =SUM(I27:I46) -> 0 | J50: =SUM(J27:J46) -> 0 | K50: =SUM(K27:K46) -> 0 | L50: =SUM(L27:L46) -> 0 | M50: =SUM(M27:M46) -> 0 | ... AJ50: =SUM(AJ27:AJ46) -> 0
A51: TOTAL EGRESOS | F51: =+F24+F3-F50 -> -18210.416 | G51: =+G3+G24-G50 -> -18210.416 | H51: =+H3+H24-H50 -> -18210.416 | I51: =+I3+I24-I50 -> -18210.416 | J51: =+J3+J24-J50 -> -18210.416 | K51: =+K3+K24-K50 -> -18210.416 | L51: =+L3+L24-L50 -> -18210.416 | M51: =+M3+M24-M50 -> -18210.416 | N51: =+N3+N24-N50 -> -18210.416 | ... AJ51: =+AJ3+AJ24-AJ50 -> 164750.04
A52: SALDO FINAL
W55: =500000-360070 -> 139930

Sheet NOV-20
B2: N° doc | C2: Fecha | D2: Monto Bruto | E2: Forma Pago | F2: 44136 | G2: 44137 | H2: 44138 | I2: 44139 | J2: 44140 | K2: 44141 | L2: 44142 | M2: 44143 | N2: 44144 | O2: 44145 | P2: 44146 | Q2: 44147 | R2: 44148 | S2: 44149 | T2: 44150 | U2: 44151 | V2: 44152 | W2: 44153 | X2: 44154 | Y2: 44155 | Z2: 44156 | AA2: 44157 | AB2: 44158 | AC2: 44159 | AD2: 44160 | AE2: 44161 | AF2: 44162 | AG2: 44163 | AH2: 44164 | AI2: 44165 | AJ2: TOTAL
A3: SALDO INICIAL | F3: =+'OCT-20'!AJ51 -> 164750.04 | G3: =+F66 -> 164750.04 | H3: =+G66 -> 196083.04 | I3: =+H66 -> 352746.04 | J3: =+I66 -> 339117.04 | K3: =+J66 -> 339117.04 | L3: =+K66 -> 248606.04 | M3: =+L66 -> 248606.04 | N3: =+M66 -> 248606.04 | ... AI3: =+AH66 -> 2093888.1
A4: INGRESOS
A5: Factura N° 6 Sofía Jottar | B5: F6 | C5: 43820 | D5: 267000 | AC5: 267000 | AI5: 0 | AJ5: =SUM(E5:AI5) -> 267000
A6: Factura N° 7 Sofía Jottar | B6: F7 | C6: 43836 | D6: 267000 | AC6: =350000-AC5 -> 83000 | AD6: 184000 | AI6: 0 | AJ6: =SUM(E6:AI6) -> 267000
A7: Factura N° 8 Sofía Jottar | B7: F8 | C7: 43848 | D7: 160200 | AI7: 0 | AJ7: =SUM(E7:AI7) -> 0
A8: Factura N° 9 Sofía Jottar | B8: F9 | C8: 43865 | D8: 160200 | AI8: 0 | AJ8: =SUM(E8:AI8) -> 0
A9: Factura N° 10 Sofía Jottar | B9: F10 | C9: 43866 | D9: 33728 | AI9: 0 | AJ9: =SUM(E9:AI9) -> 0
A10: Factura N° 11 Sofía Jottar | B10: F11 | C10: 43876 | D10: 160200 | AI10: 0 | AJ10: =SUM(E10:AI10) -> 0
A11: Factura N° 12 Sofía Jottar | B11: F12 | C11: 43882 | D11: 160200 | AI11: 0 | AJ11: =SUM(E11:AI11) -> 0
A12: Factura N° 13 Sofía Jottar | B12: F13 | C12: 43889 | D12: 160200 | AI12: 0 | AJ12: =SUM(E12:AI12) -> 0
A13: Factura N° 14 Sofía Jottar | B13: F14 | C13: 43892 | D13: =28475.41*1.19 -> 33885.738 | AI13: 0 | AJ13: =SUM(E13:AI13) -> 0
A14: Factura N° 15 Sofía Jottar | B14: F15 | C14: 43904 | D14: 160200 | AI14: 0 | AJ14: =SUM(E14:AI14) -> 0
A15: Factura N° XX Sofía Jottar SPRITZ | B15: FXX | D15: =4500*60 -> 270000 | E15: por facturar | AI15: 0 | AJ15: =SUM(E15:AI15) -> 0
A16: Factura N° 26 Marina | B16: F26 | C16: 44128 | D16: 31333 | G16: 31333 | AI16: 0 | AJ16: =SUM(E16:AI16) -> 31333
A17: Factura N° 27 Marina | B17: F27 | C17: 44133 | D17: 31333 | H17: 31333 | AI17: 0 | AJ17: =SUM(E17:AI17) -> 31333
A18: Factura N° 28 Marina | B18: F28 | C18: 44136 | D18: 62665 | H18: 62665 | AI18: 0 | AJ18: =SUM(E18:AI18) -> 62665
A19: Factura N° 29 Marina | B19: F29 | C19: 44136 | D19: 93998 | H19: =156663-31333-62665 -> 62665 | AI19: 0 | AJ19: =SUM(E19:AI19) -> 62665
A20: Factura N° 30 Marina | B20: F30 | C20: 44148 | D20: 125331 | W20: 156664 | AI20: 0 | AJ20: =SUM(E20:AI20) -> 156664
A21: Factura N° 31 Marina | B21: F31 | C21: 44155 | D21: 62665 | AI21: 0 | AJ21: =SUM(E21:AI21) -> 0
A22: Factura N° 32 Entretoros | B22: F32 | C22: 44155 | D22: 115199 | AI22: 0 | AJ22: =SUM(E22:AI22) -> 0
A23: Factura N° 33Marina | B23: F33 | C23: 44161 | D23: =26330*4*1.19 -> 125330.8 | AI23: 0 | AJ23: =SUM(E23:AI23) -> 0
A24: SUBTOTAL VENTAS | AJ24: =SUM(AJ5:AJ23) -> 878660
A25: SII DEVOLUCION PPM 2019 | C25: 43980 | D25: 10465
A26: Aporte LV | D26: =250000+1950000 -> 2200000 | F26: 0 | G26: 0 | O26: 250000 | R26: 1950000
A27: Aporte ML | G27: 0
A28: SENCE subsidio | R28: 16666
A29: Remanente IVA | D29: 2001574
A32: TOTAL INGRESOS | F32: =SUM(F5:F31) -> 0 | G32: =SUM(G5:G31) -> 31333 | H32: =SUM(H5:H31) -> 156663 | I32: =SUM(I5:I31) -> 0 | J32: =SUM(J5:J31) -> 0 | K32: =SUM(K5:K31) -> 0 | L32: =SUM(L5:L31) -> 0 | M32: =SUM(M5:M31) -> 0 | ... AI32: =SUM(AI5:AI31) -> 0
A34: EGRESOS
A35: Boleta N° 126 EMS Remun Abril 2020 | B35: B126 | D35: 500000 | U35: 500000 | AI35: 0
A36: Boleta N° xxx EMS Remun Mayo 2020 | B36: Bxxx | D36: 500000 | AI36: 0
A37: Boleta N° xxx EMS Remun Junio 2020 | B37: Bxxx | D37: =500000/2 -> 250000 | AI37: 0
A38: Boleta N° xxx EMS Remun Julio 2020 | B38: Bxxx | D38: =500000/2 -> 250000 | AI38: 0
A39: Boleta N° xxx EMS Remun Agosto 2020 | B39: Bxxx | D39: =500000/2 -> 250000 | AI39: 0
A40: Boleta N° xxx EMS Remun Sept 2020 | B40: Bxxx | D40: 250000 | AI40: 0
A41: Boleta N° xxx EMS Remun Oct 2020 | B41: Bxxx | D41: 500000 | AI41: 0
A42: Boleta N° xxx EMS Remun Nov 2020 | B42: Bxxx | D42: 500000 | AI42: 0
A43: Boleta N°xxx Remun Variable Gerente | B43: Bxxx | D43: =+AI43 -> 0 | AI43: 0
A44: ANALAB preparación mezcla Aperol | B44: F194283 | C44: 43892 | D44: =45500*1.19 -> 54145 | E44: Transfer | U44: 30000
A45: Flete Vitacura-Chicureo-Recoleta-Vitacura | C45: 44134 | D45: =(23.8+36.4+3.5+15.4)*810/9+2287*2+1351+585 -> 13629 | E45: Transfer | I45: =(23.8+36.4+3.5+15.4)*810/9+2287*2+1351+585 -> 13629
A46: LANCER insumos | B46: F1069298 | C46: 44134 | D46: 19111 | E46: Transfer | K46: 19111
A47: LANCER arriendo equipo | B47: F1069330 | C47: 44137 | D47: 71400 | E47: Transfer | K47: 71400
A48: GoDaddy renovación anual dominio web | B48: F1774612869 | C48: 44143 | D48: =19798+3789+142 -> 23729 | R48: =19798+3789+142 -> 23729
A49: GoDaddy renovación anual casilla email | B49: F1774166231 | C49: 44142 | D49: =46548*1.19 -> 55392.12 | R49: =46548*1.19 -> 55392.12
A50: Flete Vitacura-Requinoa-Recoleta-Vitacura | C50: 44147 | D50: =2615+1313+389+788+407+560+644+377+337+614+285+1237+3800+2700*2+283*480/12 -> 30086 | R50: =2615+1313+389+788+407+560+644+377+337+614+285+1237+3800+2700*2+283*480/12 -> 30086
A51: TRANSF A B. ESTADO CTA CLIENTE | B51: 7052893 | C51: 44144 | D51: 137 | N51: 137
A52: Flete Vitacura-Recoleta-Rest.Marina -Vitacura | C52: 44148 | D52: =(15.4+5.7+14.6)*810/9 -> 3213 | U52: =(15.4+5.7+14.6)*810/9 -> 3213
A53: LANCER Servicio de embolsado u caja | B53: F1069495 | C53: 44148 | D53: =3200*10*1.19 -> 38080 | Y53: =3200*10*1.19 -> 38080
A54: SODIMAC aislante tuberias | B54: F108312903 | C54: 44152 | D54: =1647*1.19 -> 1959.93 | AG54: 1960
A55: LANCER Cilindro,recarga,regulador | B55: F1069553 | C55: 44153 | D55: =112020*1.19 -> 133303.8 | Y55: =112020*1.19 -> 133303.8
A56: Flete Vitacura-Chicureo-Vitacura | C56: 44153 | D56: =(23.4*2)*810/9 -> 4212 | Y56: =(23.4*2)*810/9 -> 4212
A57: Flete Vitacura-Chicureo-Vitacura | C57: 44154 | D57: =(23.4*2)*810/9 -> 4212 | Y57: =(23.4*2)*810/9 -> 4212
A58: SABORES escencia ginger colorante caramelo | B58: F95603 Pedido 27963 | C58: 44155 | D58: =38366*1.19 -> 45655.54 | E58: Transfer | Y58: 45656
A59: SAG SPS 534539 | C59: 44155 | D59: 7094 | Y59: 7094
A60: RENO alcohol 200 lt | B60: F388861 | C60: 44159 | D60: 174011 | AB60: 174011
A61: Flete Vitacura-Marina-Chicureo-Vitacura | C61: 44160 | D61: =+((14.1+23.4)*2)*810/9 -> 6750 | AG61: 6750
A62: Flete Vitacura-Chicureo-Vitacura | C62: 44161 | D62: =(23.4*2)*810/9 -> 4212 | AG62: 4212
A65: TOTAL EGRESOS | F65: =SUM(F35:F64) -> 0 | G65: =SUM(G35:G64) -> 0 | H65: =SUM(H35:H64) -> 0 | I65: =SUM(I35:I64) -> 13629 | J65: =SUM(J35:J64) -> 0 | K65: =SUM(K35:K64) -> 90511 | L65: =SUM(L35:L64) -> 0 | M65: =SUM(M35:M64) -> 0 | ... AI65: =SUM(AI35:AI64) -> 0
A66: SALDO FINAL | F66: =+F32+F3-F65 -> 164750.04 | G66: =+G3+G32-G65 -> 196083.04 | H66: =+H3+H32-H65 -> 352746.04 | I66: =+I3+I32-I65 -> 339117.04 | J66: =+J3+J32-J65 -> 339117.04 | K66: =+K3+K32-K65 -> 248606.04 | L66: =+L3+L32-L65 -> 248606.04 | M66: =+M3+M32-M65 -> 248606.04 | N66: =+N3+N32-N65 -> 248469.04 | ... AI66: =+AI3+AI32-AI65 -> 2093888.1
W70: =500000-360070 -> 139930

Sheet DIC-20
B2: N° doc | C2: Fecha | D2: Monto Bruto | E2: Forma Pago | F2: 44166 | G2: 44167 | H2: 44168 | I2: 44169 | J2: 44170 | K2: 44171 | L2: 44172 | M2: 44173 | N2: 44174 | O2: 44175 | P2: 44176 | Q2: 44177 | R2: 44178 | S2: 44179 | T2: 44180 | U2: 44181 | V2: 44182 | W2: 44183 | X2: 44184 | Y2: 44185 | Z2: 44186 | AA2: 44187 | AB2: 44188 | AC2: 44189 | AD2: 44190 | AE2: 44191 | AF2: 44192 | AG2: 44193 | AH2: 44194 | AI2: 44195 | AJ2: 44196 | AK2: TOTAL
A3: SALDO INICIAL | F3: =+'NOV-20'!AI66 -> 2093888.1 | G3: =+F62 -> 2048758.1 | H3: =+G62 -> 2212660.1 | I3: =+H62 -> 2212660.1 | J3: =+I62 -> 2212660.1 | K3: =+J62 -> 2212660.1 | L3: =+K62 -> 2212660.1 | M3: =+L62 -> 2212660.1 | N3: =+M62 -> 2212660.1 | ... AJ3: =+AI62 -> 1552648.3
A4: INGRESOS
A5: Factura N° 8 Sofía Jottar | B5: F8 | C5: 43848 | D5: 160200 | AJ5: 0 | AK5: =SUM(F5:AJ5) -> 0
A6: Factura N° 9 Sofía Jottar | B6: F9 | C6: 43865 | D6: 160200 | AJ6: 0 | AK6: =SUM(F6:AJ6) -> 0
A7: Factura N° 10 Sofía Jottar | B7: F10 | C7: 43866 | D7: 33728 | AJ7: 0 | AK7: =SUM(F7:AJ7) -> 0
A8: Factura N° 11 Sofía Jottar | B8: F11 | C8: 43876 | D8: 160200 | AJ8: 0 | AK8: =SUM(F8:AJ8) -> 0
A9: Factura N° 12 Sofía Jottar | B9: F12 | C9: 43882 | D9: 160200 | AJ9: 0 | AK9: =SUM(F9:AJ9) -> 0
A10: Factura N° 13 Sofía Jottar | B10: F13 | C10: 43889 | D10: 160200 | AJ10: 0 | AK10: =SUM(F10:AJ10) -> 0
A11: Factura N° 14 Sofía Jottar | B11: F14 | C11: 43892 | D11: =28475.41*1.19 -> 33885.738 | AJ11: 0 | AK11: =SUM(F11:AJ11) -> 0
A12: Factura N° 15 Sofía Jottar | B12: F15 | C12: 43904 | D12: 160200 | AJ12: 0 | AK12: =SUM(F12:AJ12) -> 0
A13: Factura N° XX Sofía Jottar SPRITZ | B13: FXX | D13: =4500*60 -> 270000 | E13: por facturar | AJ13: 0 | AK13: =SUM(F13:AJ13) -> 0
A14: Factura N° 31 Marina | B14: F31 | C14: 44155 | D14: 62665 | G14: 125331 | N14: -125331 | P14: 62665 | AK14: =SUM(F14:AJ14) -> 62665
A15: Factura N° 32 Entretoros | B15: F32 | C15: 44155 | D15: 115199 | AC15: =+D15 -> 115199 | AK15: =SUM(F15:AJ15) -> 115199
A16: Factura N° 33Marina | B16: F33 | C16: 44161 | D16: =26330*4*1.19 -> 125330.8 | G16: 125331 | AK16: =SUM(F16:AJ16) -> 125331
A17: Factura N° 34Marina | B17: F34 | C17: 44174 | D17: 62665 | P17: 62666 | AK17: =SUM(F17:AJ17) -> 62666
A18: Factura N° 35 Entretoros | B18: F35 | C18: 44175 | D18: 31333 | AC18: =+D18 -> 31333 | AK18: =SUM(F18:AJ18) -> 31333
A19: Factura N° 36Marina | B19: F36 | C19: 44180 | D19: 31333 | U19: 31333 | AK19: =SUM(F19:AJ19) -> 31333
A20: Factura N° 37Marina | B20: F37 | C20: 44186 | D20: 62666 | AB20: 62666 | AK20: =SUM(F20:AJ20) -> 62666
A21: Factura N° 38Marina | B21: F38 | C21: 44187 | D21: 34604 | AB21: 34604 | AK21: =SUM(F21:AJ21) -> 34604
A22: SUBTOTAL VENTAS | AK22: =SUM(AK5:AK21) -> 525797
A23: SII DEVOLUCION PPM 2019 | C23: 43980 | D23: 10465
A24: Aporte LV | D24: 0 | F24: 0 | G24: 0
A25: Aporte ML | G25: 0
A26: SENCE subsidio
A27: Remanente IVA | D27: 2001574 | AJ27: 0
A30: TOTAL INGRESOS | B30: 2020 | F30: =SUM(F5:F29) -> 0 | G30: =SUM(G5:G29) -> 250662 | H30: =SUM(H5:H29) -> 0 | I30: =SUM(I5:I29) -> 0 | J30: =SUM(J5:J29) -> 0 | K30: =SUM(K5:K29) -> 0 | L30: =SUM(L5:L29) -> 0 | M30: =SUM(M5:M29) -> 0 | ... AI30: =SUM(AI5:AI29) -> 0
A32: EGRESOS
A33: Boleta N° 127 EMS Remun Mayo 2020 | B33: B127 | D33: 500000 | P33: 500000
A34: Boleta N° xxx EMS Remun Junio 2020 | B34: Bxxx | D34: =500000/2 -> 250000 | AJ34: 0
A35: Boleta N° xxx EMS Remun Julio 2020 | B35: Bxxx | D35: =500000/2 -> 250000 | AJ35: 0
A36: Boleta N° xxx EMS Remun Agosto 2020 | B36: Bxxx | D36: =500000/2 -> 250000 | AJ36: 0
A37: Boleta N° xxx EMS Remun Sept 2020 | B37: Bxxx | D37: 250000 | AJ37: 0
A38: Boleta N° xxx EMS Remun Oct 2020 | B38: Bxxx | D38: 500000 | AJ38: 0
A39: Boleta N° xxx EMS Remun Nov 2020 | B39: Bxxx | D39: 500000 | AJ39: 0
A40: Boleta N°xxx Remun Variable Gerente | B40: Bxxx | D40: =+AJ40 -> 0 | AJ40: 0
A41: HARRY PLOTTER | B41: F36586 | C41: 44166 | D41: 45130 | E41: Transfer | F41: 45130
A42: Rebeca Trincado 4 ruedas 10 cm + 4 con freno | B42: F6499 | C42: 44167 | D42: 22000 | E42: transfer | G42: 22000
A43: Elias Becerra modificación mueble chico | C43: 44167 | D43: 60000 | E43: transfer | G43: 60000
A44: Flete Vitacura Chicureo Vitacura | C44: 44167 | D44: =+(25.6*2)*790/9 -> 4494.2222 | E44: transfer | P44: =+(25.6*2)*790/9 -> 4494.2222
A45: LANCER arriendo equipo N°1 y 2 | B45: F1069793 | C45: 44167 | D45: =71400*2 -> 142800 | R45: =71400*2 -> 142800
A46: SODIMAC pintura spray + barniz spray | B46: F108597127 | C46: 44168 | D46: 11180 | E46: TC ems | P46: 11180
A47: Cleanice | B47: F28793 | C47: 44168 | D47: 4760 | E47: transfer | G47: 4760
A48: Flete Vitacura Recoleta -Marina Vitacura | C48: 44168 | D48: =+(16.3+7.6+14.5)*790/9 -> 3370.6667 | E48: transfer | P48: =+(16.3+7.6+14.5)*790/9 -> 3370.6667
A49: LANCER Cilindro,recarga | B49: F1069820 | C49: 44168 | D49: =(65020+7000)*1.19 -> 85703.8 | R49: =(65020+7000)*1.19 -> 85703.8
A50: LANCER arriendo equipo N°3 | B50: F1069822 | C50: 44168 | D50: 71400 | R50: 71400
A51: Flete Vitacura Chicureo Vitacura | C51: 44174 | D51: =+(25.6*2)*790/9 -> 4494.2222 | E51: transfer | P51: =+(25.6*2)*790/9 -> 4494.2222
A52: Flete Vitacura Chicureo Vitacura | C52: 44175 | D52: =+(25.6*2)*790/9 -> 4494.2222 | E52: transfer | P52: =+(25.6*2)*790/9 -> 4494.2222
A53: Flete Vitacura Chicureo Vitacura | C53: 44176 | D53: =+(25.6*2)*790/9 -> 4494.2222 | E53: transfer | P53: =+(25.6*2)*790/9 -> 4494.2222
A54: F29 Nov | C54: 44176 | D54: 77637 | E54: transfer | P54: 77637
A55: Flete Mario Liberona Stgo Requinoa Stgo | C55: 44181 | D55: 16944 | E55: transfer | AA55: 16944
A56: Flete Vitacura Recoleta Vitacura | C56: 44182 | D56: =+(12.3*2)*790/9 -> 2159.3333 | E56: transfer | AB56: =+(12.3*2)*790/9 -> 2159.3333
A57: Flete Vitacura Recoleta Vitacura | C57: 44186 | D57: =+(13.7*2)*790/9 -> 2405.1111 | E57: transfer | AB57: =+(13.7*2)*790/9 -> 2405.1111
A58: Cleanice recarga 2Kg | B58: F29156 | C58: 44186 | D58: 3570 | E58: transfer | Z58: 3570
A61: TOTAL EGRESOS | F61: =SUM(F33:F59) -> 45130 | G61: =SUM(G33:G59) -> 86760 | H61: =SUM(H33:H59) -> 0 | I61: =SUM(I33:I59) -> 0 | J61: =SUM(J33:J59) -> 0 | K61: =SUM(K33:K59) -> 0 | L61: =SUM(L33:L59) -> 0 | M61: =SUM(M33:M59) -> 0 | ... AJ61: =SUM(AJ33:AJ59) -> 0
A62: SALDO FINAL | F62: =+F30+F3-F61 -> 2048758.1 | G62: =+G3+G30-G61 -> 2212660.1 | H62: =+H3+H30-H61 -> 2212660.1 | I62: =+I3+I30-I61 -> 2212660.1 | J62: =+J3+J30-J61 -> 2212660.1 | K62: =+K3+K30-K61 -> 2212660.1 | L62: =+L3+L30-L61 -> 2212660.1 | M62: =+M3+M30-M61 -> 2212660.1 | N62: =+N3+N30-N61 -> 2087329.1 | ... AJ62: =+AJ3+AJ30-AJ61 -> 1552648.3
P63: 1329252
P64: =+P62-P63 -> 273243.57
W66: =500000-360070 -> 139930

Sheet ENE-21
B2: N° doc | C2: Fecha | D2: Monto Bruto | E2: Forma Pago | F2: 44197 | G2: 44198 | H2: 44199 | I2: 44200 | J2: 44201 | K2: 44202 | L2: 44203 | M2: 44204 | N2: 44205 | O2: 44206 | P2: 44207 | Q2: 44208 | R2: 44209 | S2: 44210 | T2: 44211 | U2: 44212 | V2: 44213 | W2: 44214 | X2: 44215 | Y2: 44216 | Z2: 44217 | AA2: 44218 | AB2: 44219 | AC2: 44220 | AD2: 44221 | AE2: 44222 | AF2: 44223 | AG2: 44224 | AH2: 44225 | AI2: 44226 | AJ2: 44227 | AK2: TOTAL
A3: SALDO INICIAL | F3: =+'DIC-20'!AJ62 -> 1552648.3 | G3: =+F66 -> 1552648.3 | H3: =+G66 -> 1552648.3 | I3: =+H66 -> 1552648.3 | J3: =+I66 -> 1552648.3 | K3: =+J66 -> 1552648.3 | L3: =+K66 -> 1380747.3 | M3: =+L66 -> 1123477.3 | N3: =+M66 -> 1123477.3 | ... AJ3: =+AI66 -> 475165.43
A4: INGRESOS
A5: Factura N° 8 Sofía Jottar | B5: F8 | C5: 43848 | D5: 160200 | AH5: 250000 | AJ5: 0 | AK5: =SUM(F5:AJ5) -> 250000
A6: Factura N° 9 Sofía Jottar | B6: F9 | C6: 43865 | D6: 160200 | AI6: 70400 | AJ6: 0 | AK6: =SUM(F6:AJ6) -> 70400
A7: Factura N° 10 Sofía Jottar | B7: F10 | C7: 43866 | D7: 33728 | AJ7: 0 | AK7: =SUM(F7:AJ7) -> 0
A8: Factura N° 11 Sofía Jottar | B8: F11 | C8: 43876 | D8: 160200 | AJ8: 0 | AK8: =SUM(F8:AJ8) -> 0
A9: Factura N° 12 Sofía Jottar | B9: F12 | C9: 43882 | D9: 160200 | AJ9: 0 | AK9: =SUM(F9:AJ9) -> 0
A10: Factura N° 13 Sofía Jottar | B10: F13 | C10: 43889 | D10: 160200 | AJ10: 0 | AK10: =SUM(F10:AJ10) -> 0
A11: Factura N° 14 Sofía Jottar | B11: F14 | C11: 43892 | D11: =28475.41*1.19 -> 33885.738 | AJ11: 0 | AK11: =SUM(F11:AJ11) -> 0
A12: Factura N° 15 Sofía Jottar | B12: F15 | C12: 43904 | D12: 160200 | AJ12: 0 | AK12: =SUM(F12:AJ12) -> 0
A13: Factura N° XX Sofía Jottar SPRITZ | B13: FXX | D13: =4500*60 -> 270000 | E13: por facturar | AJ13: 0 | AK13: =SUM(F13:AJ13) -> 0
A14: Factura N° 39 Entretoros | B14: F39 | C14: 44194 | D14: 31333 | AF14: 31333 | AK14: =SUM(F14:AJ14) -> 31333
A15: Factura N° 40Marina | B15: F40 | C15: 44194 | D15: 62665 | Y15: 62665 | AK15: =SUM(F15:AJ15) -> 62665
A16: Factura N° 41Marina | B16: F41 | C16: 44202 | D16: 62665 | Y16: =124817-Y15 -> 62152 | AF16: 515 | AK16: =SUM(F16:AJ16) -> 62667
A17: Factura N°42Marina ARRIENDO VAR DIC2020 | B17: F42 | C17: 44207 | D17: 51885 | AF17: 51885 | AK17: =SUM(F17:AJ17) -> 51885
A18: Factura N°43Marina | B18: F43 | C18: 44207 | D18: 47600 | AF18: 47600 | AK18: =SUM(F18:AJ18) -> 47600
A19: Factura N° 44 Entretoros | B19: F44 | C19: 44209 | D19: 31333 | AK19: =SUM(F19:AJ19) -> 0
A20: Factura N°45Marina | B20: F45 | C20: 44209 | D20: 156664 | AK20: =SUM(F20:AJ20) -> 0
A21: SUBTOTAL VENTAS | AK21: =SUM(AK5:AK20) -> 576550
A22: SII DEVOLUCION PPM 2019 | C22: 43980 | D22: 10465 | AJ22: 0
A23: Aporte LV | D23: 0 | F23: 0 | G23: 0
A24: Aporte ML | G24: 0
A25: SENCE subsidio
A26: Remanente IVA | D26: 2001574 | AJ26: 0
A29: TOTAL INGRESOS | F29: =SUM(F5:F28) -> 0 | G29: =SUM(G5:G28) -> 0 | H29: =SUM(H5:H28) -> 0 | I29: =SUM(I5:I28) -> 0 | J29: =SUM(J5:J28) -> 0 | K29: =SUM(K5:K28) -> 0 | L29: =SUM(L5:L28) -> 0 | M29: =SUM(M5:M28) -> 0 | ... AJ29: =SUM(AJ5:AJ28) -> 0
A31: EGRESOS
A32: Boleta N° xxx EMS Remun Junio 2020 | B32: Bxxx | D32: =500000/2 -> 250000 | AJ32: 0
A33: Boleta N° xxx EMS Remun Julio 2020 | B33: Bxxx | D33: =500000/2 -> 250000 | AJ33: 0
A34: Boleta N° xxx EMS Remun Agosto 2020 | B34: Bxxx | D34: =500000/2 -> 250000 | AJ34: 0
A35: Boleta N° xxx EMS Remun Sept 2020 | B35: Bxxx | D35: 250000 | AJ35: 0
A36: Boleta N° xxx EMS Remun Oct 2020 | B36: Bxxx | D36: 500000 | AJ36: 0
A37: Boleta N° xxx EMS Remun Nov 2020 | B37: Bxxx | D37: 500000 | AJ37: 0
A38: Boleta N° xxx EMS Remun Dic2020 | B38: Bxxx | D38: 500000 | AJ38: 0
A39: Boleta N°xxx Remun Variable Gerente | B39: Bxxx | D39: =+AJ39 -> 0 | AJ39: 0
A40: Flete Vitacura Chicureo Vitacura | C40: 44194 | D40: =+(25.6*2)*790/9 -> 4494.2222 | P40: =+(25.6*2)*790/9 -> 4494.2222 | AJ40: 0
A41: SABORES goma Xanthan escencia ginger colorante caramelo | B41: F95603 Pedido 27963 | C41: 44155 | D41: 7270 | E41: Transfer | L41: 7270
A42: LANCER EMBOLSADO | B42: F1070013 | C42: 44182 | D42: 121856
A43: ANTAWARA | B43: F5 | C43: 44195 | D43: 240975
A44: Flete Vitacura-Chicureo-Vitacura | C44: 44201 | D44: =(23.4*2)*810/9 -> 4212 | P44: =(23.4*2)*810/9 -> 4212
A45: Flete Vitacura Chicureo Vitacura | C45: 44201 | D45: =+(25.6*2)*790/9 -> 4494.2222 | P45: =+(25.6*2)*790/9 -> 4494.2222
A46: LANCER ULTIMA CUOTA 1ER EQUIPO | B46: F1070271 | C46: 44202 | D46: 475030 | T46: 475030
A47: LANCER arriendos equipos | B47: F1070272 | C47: 44202 | D47: 142800 | T47: 142800
A48: FRIGO torre 3grifos | B48: F108 | C48: 44202 | D48: =164901+7000 -> 171901 | K48: =164901+7000 -> 171901
A49: LANCER bomba,regulador sec, varios | B49: F1070330 | C49: 44203 | D49: 283101 | T49: 283101
A50: LANCER EMBOLSADO | B50: F1070335 | C50: 44203 | D50: 34272 | T50: 34272
A51: LANCER conector abrazaderas | B51: F1070344 | C51: 44203 | D51: 28988
A52: Jorge Araya plataforma bar + arreglo mueble chico | C52: 44203 | D52: 250000 | L52: 250000
A53: Flete Vitacura Chicureo Vitacura | C53: 44203 | D53: =+(25.6*2)*790/9 -> 4494.2222 | P53: =+(25.6*2)*790/9 -> 4494.2222
A54: SANGRIALEGRIA | B54: F48 | C54: 44204 | D54: 77900 | S54: 77900
A55: Flete Vitacura Chicureo Vitacura | C55: 44204 | D55: =+(25.6*2)*790/9 -> 4494.2222 | P55: =+(25.6*2)*790/9 -> 4494.2222
A56: F29 DIC | C56: 44207 | D56: 60570 | P56: 60570
A57: Flete Vitacura Chicureo Vitacura | C57: 44207 | D57: =+(25.6*2)*790/9 -> 4494.2222
A58: Flete Vitacura Chicureo Vitacura | C58: 44208 | D58: =+(25.6*2)*790/9 -> 4494.2222
A59: Flete Vitacura Chicureo Providencia Vitacura | C59: 44209 | D59: =+(25.6*2)*790/9 -> 4494.2222
A60: UNIMARC azúcar+agua purificada | B60: F32480830 | C60: 44203 | D60: 15700 | E60: TC ems
A61: LIDER Spritz Livenza | B61: B8190758004 | C61: 44204 | D61: 5990 | E61: TC ems
A62: UNIMARC azúcar+agua purificada | B62: F32502972 | C62: 44210 | D62: 12730 | E62: TC ems
A63: Jorge Araya 50% arreglo mueble mediano | C63: 44216 | D63: 129000 | E63: Transfer | Y63: 129000
A65: TOTAL EGRESOS | F65: =SUM(F32:F63) -> 0 | G65: =SUM(G32:G63) -> 0 | H65: =SUM(H32:H63) -> 0 | I65: =SUM(I32:I63) -> 0 | J65: =SUM(J32:J63) -> 0 | K65: =SUM(K32:K63) -> 171901 | L65: =SUM(L32:L63) -> 257270 | M65: =SUM(M32:M63) -> 0 | ... AJ65: =SUM(AJ32:AJ63) -> 0
A66: SALDO FINAL | F66: =+F29+F3-F65 -> 1552648.3 | G66: =+G3+G29-G65 -> 1552648.3 | H66: =+H3+H29-H65 -> 1552648.3 | I66: =+I3+I29-I65 -> 1552648.3 | J66: =+J3+J29-J65 -> 1552648.3 | K66: =+K3+K29-K65 -> 1380747.3 | L66: =+L3+L29-L65 -> 1123477.3 | M66: =+M3+M29-M65 -> 1123477.3 | N66: =+N3+N29-N65 -> 1123477.3 | ... AJ66: =+AJ3+AJ29-AJ65 -> 475165.43
P67: 1040719
W70: =500000-360070 -> 139930

Sheet FEB-21
B2: N° doc | C2: Fecha | D2: Monto Bruto | E2: Forma Pago | F2: 44228 | G2: 44229 | H2: 44230 | I2: 44231 | J2: 44232 | K2: 44233 | L2: 44234 | M2: 44235 | N2: 44236 | O2: 44237 | P2: 44238 | Q2: 44239 | R2: 44240 | S2: 44241 | T2: 44242 | U2: 44243 | V2: 44244 | W2: 44245 | X2: 44246 | Y2: 44247 | Z2: 44248 | AA2: 44249 | AB2: 44250 | AC2: 44251 | AD2: 44252 | AE2: 44253 | AF2: 44254 | AG2: 44255 | AH2: TOTAL
A3: SALDO INICIAL | F3: =+'ENE-21'!AJ66 -> 475165.43 | G3: =+F80 -> 475165.43 | H3: =+G80 -> 427262.77 | I3: =+H80 -> 427262.77 | J3: =+I80 -> 404057.77 | K3: =+J80 -> 404057.77 | L3: =+K80 -> 404057.77 | M3: =+L80 -> 404057.77 | N3: =+M80 -> 221927.83 | ... AG3: =+AF80 -> 520473.83
A4: INGRESOS
A5: Factura N° 10 Sofía Jottar | B5: F10 | C5: 43866 | D5: 33728 | AH5: =SUM(F5:AG5) -> 0
A6: Factura N° 11 Sofía Jottar | B6: F11 | C6: 43876 | D6: 160200 | AH6: =SUM(F6:AG6) -> 0
A7: Factura N° 12 Sofía Jottar | B7: F12 | C7: 43882 | D7: 160200 | AH7: =SUM(F7:AG7) -> 0
A8: Factura N° 13 Sofía Jottar | B8: F13 | C8: 43889 | D8: 160200 | AH8: =SUM(F8:AG8) -> 0
A9: Factura N° 14 Sofía Jottar | B9: F14 | C9: 43892 | D9: =28475.41*1.19 -> 33885.738 | AH9: =SUM(F9:AG9) -> 0
A10: Factura N° 15 Sofía Jottar | B10: F15 | C10: 43904 | D10: 160200 | AH10: =SUM(F10:AG10) -> 0
A11: Factura N° XX Sofía Jottar SPRITZ | B11: FXX | D11: =4500*60 -> 270000 | E11: por facturar | AH11: =SUM(F11:AG11) -> 0
A12: Factura N° 39 Entretoros | B12: F39 | C12: 44194 | D12: 31333 | AH12: =SUM(F12:AG12) -> 0
A13: Factura N° 44 Entretoros | B13: F44 | C13: 44209 | D13: 31333 | AH13: =SUM(F13:AG13) -> 0
A14: Factura N°45Marina | B14: F45 | C14: 44209 | D14: 156664 | M14: 156664 | AH14: =SUM(F14:AG14) -> 156664
A15: Factura N° 46 Entretoros | B15: F46 | C15: 44229 | D15: =31333+3050*10/0.75 -> 71999.667 | AH15: =SUM(F15:AG15) -> 0
A16: Factura N°47 Entretoros ARRIENDO VAR ENE2021 | B16: F47 | C16: 44229 | D16: 66902 | AH16: =SUM(F16:AG16) -> 0
A17: Factura N°48 Marina | B17: F48 | C17: 44229 | D17: =2350*5/0.75 -> 15666.667 | M17: 15667 | AH17: =SUM(F17:AG17) -> 15667
A18: Factura N°50 Marina ARRIENDO VAR ENE2020 | B18: F50 | C18: 44229 | D18: 50956 | M18: =200000-M17-M14 -> 27669 | O18: =+D18-M18 -> 23287 | AH18: =SUM(F18:AG18) -> 50956
A19: Factura Gilberto | D19: 31333 | AH19: =SUM(F19:AG19) -> 0
A20: Factura N°51 Marina | B20: F51 | C20: 44231 | D20: 110265 | O20: 110265 | AH20: =SUM(F20:AG20) -> 110265
A21: Factura N°52 Marina | B21: F52 | C21: 44235 | D21: 78933 | O21: 78933 | AH21: =SUM(F21:AG21) -> 78933
A22: Factura N°53 Marina | B22: F53 | C22: 44238 | D22: 189198 | O22: =341651-O21-O20-O18 -> 129166 | U22: =+D22-O22 -> 60032 | AH22: =SUM(F22:AG22) -> 189198
A23: Factura N°54 Marina | B23: F54 | C23: 44242 | D23: 31333 | U23: =91364-U22 -> 31332 | AH23: =SUM(F23:AG23) -> 31332
A24: Factura N°55 Marina | B24: F55 | C24: 44243 | D24: 150714 | AC24: 150714 | AH24: =SUM(F24:AG24) -> 150714
A25: Factura N°56 Marina | B25: F56 | C25: 44251 | D25: 141598 | AH25: =SUM(F25:AG25) -> 0
A26: Factura N° 57 Entretoros | B26: F57 | C26: 44251 | D26: =31333 -> 31333 | AH26: =SUM(F26:AG26) -> 0
AH27: =SUM(F27:AG27) -> 0
AH28: =SUM(AH5:AH24) -> 783729
A30: SII DEVOLUCION PPM 2019 | C30: 43980 | D30: 10465
A31: Aporte LV | D31: 0 | F31: 0 | G31: 0
A32: Aporte ML | G32: 0
A33: SENCE subsidio
A34: Remanente IVA | D34: 2001574
A37: TOTAL INGRESOS | F37: =SUM(F5:F36) -> 0 | G37: =SUM(G5:G36) -> 0 | H37: =SUM(H5:H36) -> 0 | I37: =SUM(I5:I36) -> 0 | J37: =SUM(J5:J36) -> 0 | K37: =SUM(K5:K36) -> 0 | L37: =SUM(L5:L36) -> 0 | M37: =SUM(M5:M36) -> 200000 | ... AG37: =SUM(AG5:AG36) -> 0
A39: EGRESOS
A40: Boleta N° xxx EMS Remun Junio 2020 | B40: Bxxx | D40: =500000/2 -> 250000
A41: Boleta N° xxx EMS Remun Julio 2020 | B41: Bxxx | D41: =500000/2 -> 250000
A42: Boleta N° xxx EMS Remun Agosto 2020 | B42: Bxxx | D42: =500000/2 -> 250000
A43: Boleta N° xxx EMS Remun Sept 2020 | B43: Bxxx | D43: 250000
A44: Boleta N° xxx EMS Remun Oct 2020 | B44: Bxxx | D44: 500000
A45: Boleta N° xxx EMS Remun Nov 2020 | B45: Bxxx | D45: 500000
A46: Boleta N° xxx EMS Remun Dic2020 | B46: Bxxx | D46: 500000
A47: Boleta N° xxx EMS Remun Ene2021 | B47: Bxxx | D47: 500000
A48: Boleta N°129 Remun Var. Gte. a Enero | B48: B129 | D48: =+('OCT-20'!AK17+'NOV-20'!AJ24+'DIC-20'!AK22+'ENE-21'!AK21)*0.17 -> 347424.24 | M48: 347424.24
A49: LANCER EMBOLSADO | B49: F1170013 | C49: 44182 | D49: 121856
A50: ANTAWARA | B50: F5 | C50: 44195 | D50: 240975
A51: LANCER conector abrazaderas | B51: F1070344 | C51: 44203 | D51: 28988
A52: UNIMARC azúcar+agua purificada | B52: F32480830 | C52: 44203 | D52: 15700 | E52: TC ems | G52: 15700
A53: LIDER Spritz Livenza | B53: B8190758004 | C53: 44204 | D53: 5990 | E53: TC ems | G53: 5990
A54: Flete Vitacura Chicureo Vitacura | C54: 44207 | D54: =+(25.6*2)*790/9 -> 4494.2222 | G54: =+(25.6*2)*790/9 -> 4494.2222
A55: Flete Vitacura Chicureo Vitacura | C55: 44208 | D55: =+(25.6*2)*790/9 -> 4494.2222 | G55: =+(25.6*2)*790/9 -> 4494.2222
A56: Flete Vitacura Chicureo Providencia Vitacura | C56: 44209 | D56: =+(25.6*2)*790/9 -> 4494.2222 | G56: =+(25.6*2)*790/9 -> 4494.2222
A57: UNIMARC azúcar+agua purificada | B57: F32502972 | C57: 44210 | D57: 12730 | E57: TC ems | G57: 12730
A58: UBER Vitacura -Marina | C58: 44224 | D58: 6088 | M58: 6088
A59: Flete Vitacura Chicureo Vitacura | C59: 44228 | D59: =+(25.6*2)*828/9 -> 4710.4 | M59: 4710.4
A60: Flete Vitacura Chicureo Vitacura | C60: 44229 | D60: =+(25.6*2)*828/9 -> 4710.4 | M60: 4710.4
A61: LIDER alargador eléctrico | B61: B812610383 | C61: 44229 | D61: 4990 | M61: 4990
A62: LANCER arriendo equipo N°2 3a cuota | B62: F1070817 | C62: 44229 | D62: =60000*1.19 -> 71400
A63: LANCER arriendo equipo N°3 2a cuota | B63: F1070818 | C63: 44229 | D63: =60000*1.19 -> 71400
A64: Flete Vitacura Chicureo Vitacura | C64: 44230 | D64: =+(25.6*2)*828/9 -> 4710.4 | M64: =+(25.6*2)*828/9 -> 4710.4
A65: Flete Vitacura Marina Clean Ice Vitacura | C65: 44231 | D65: =+(14.4+7.6+12.8)*828/9+673.5+911 -> 4786.1 | M65: =+(14.4+7.6+12.8)*828/9+673.5+911 -> 4786.1
A66: CLEAN ICE carga 2 x2 kg 1 x 9 kg | B66: F30107 | C66: 44231 | D66: 23205 | E66: transfer | I66: 23205
A67: Flete Vitacura Chicureo Vitacura | C67: 44232 | D67: =+(25.6*2)*800/9 -> 4551.1111 | M67: =+(25.6*2)*828/9 -> 4710.4
A68: ANTAWARA 2700 lt | B68: F14 | C68: 44235 | D68: 2216970
A69: Flete Vitacura Chicureo Marina Vitacura | C69: 44238 | D69: =+(19.3+31.7+15.2)*790/9+2432+363+934 -> 9539.8889
A70: SANGRIALEGRIA | B70: F63 | C70: 44238 | D70: 77900 | P70: 77900
A71: Jorge Araya saldo 50% arreglo mueble mediano | C71: 44239 | D71: 129000 | E71: Transfer | Q71: 129000
A72: F29 ENERO | Q72: 383
A73: SANGRIALEGRIA | B73: F66 | C73: 44242 | D73: 77900 | T73: 77900
A74: Flete Vitacura Chicureo Vitacura | C74: 44242 | D74: =+(25.6*2)*800/9 -> 4551.1111
A75: Flete Vitacura Marina Vitacura | C75: 44243 | D75: =+(14.4*2)*800/9+674+935 -> 4169
A76: Flete Vitacura Marina Chicureo Vitacura | C76: 44251 | D76: =+(14.4+28.6+25.7)*800/9+1977+2432+1220 -> 11735.667
A79: TOTAL EGRESOS | F79: =SUM(F40:F78) -> 0 | G79: =SUM(G40:G78) -> 47902.667 | H79: =SUM(H40:H78) -> 0 | I79: =SUM(I40:I78) -> 23205 | J79: =SUM(J40:J78) -> 0 | K79: =SUM(K40:K78) -> 0 | L79: =SUM(L40:L78) -> 0 | M79: =SUM(M40:M78) -> 382129.94 | ... AG79: =SUM(AG40:AG78) -> 0
A80: SALDO FINAL | F80: =+F37+F3-F79 -> 475165.43 | G80: =+G3+G37-G79 -> 427262.77 | H80: =+H3+H37-H79 -> 427262.77 | I80: =+I3+I37-I79 -> 404057.77 | J80: =+J3+J37-J79 -> 404057.77 | K80: =+K3+K37-K79 -> 404057.77 | L80: =+L3+L37-L79 -> 404057.77 | M80: =+M3+M37-M79 -> 221927.83 | N80: =+N3+N37-N79 -> 221927.83 | ... AG80: =+AG3+AG37-AG79 -> 520473.83

Sheet MAR-21
B2: N° doc | C2: Fecha | D2: Monto Bruto | E2: Forma Pago | F2: 44256 | G2: 44257 | H2: 44258 | I2: 44259 | J2: 44260 | K2: 44261 | L2: 44262 | M2: 44263 | N2: 44264 | O2: 44265 | P2: 44266 | Q2: 44267 | R2: 44268 | S2: 44269 | T2: 44270 | U2: 44271 | V2: 44272 | W2: 44273 | X2: 44274 | Y2: 44275 | Z2: 44276 | AA2: 44277 | AB2: 44278 | AC2: 44279 | AD2: 44280 | AE2: 44281 | AF2: 44282 | AG2: 44283 | AH2: 44284 | AI2: 44285 | AJ2: 44286 | AK2: TOTAL
A3: SALDO INICIAL | F3: =+'FEB-21'!AG80 -> 520473.83 | G3: =+F66 -> 520473.83 | H3: =+G66 -> 442573.83 | I3: =+H66 -> 184171.83 | J3: =+I66 -> 145525.61 | K3: =+J66 -> 145525.61 | L3: =+K66 -> 145525.61 | M3: =+L66 -> 145525.61 | N3: =+M66 -> 107445.61 | ... AJ3: =+AI66 -> 113413.45
A4: INGRESOS
A5: Factura N° 10 Sofía Jottar | B5: F10 | C5: 43866 | D5: 33728 | AJ5: 0 | AK5: =SUM(F5:AJ5) -> 0
A6: Factura N° 11 Sofía Jottar | B6: F11 | C6: 43876 | D6: 160200 | AJ6: 0 | AK6: =SUM(F6:AJ6) -> 0
A7: Factura N° 12 Sofía Jottar | B7: F12 | C7: 43882 | D7: 160200 | AJ7: 0 | AK7: =SUM(F7:AJ7) -> 0
A8: Factura N° 13 Sofía Jottar | B8: F13 | C8: 43889 | D8: 160200 | AJ8: 0 | AK8: =SUM(F8:AJ8) -> 0
A9: Factura N° 14 Sofía Jottar | B9: F14 | C9: 43892 | D9: =28475.41*1.19 -> 33885.738 | AJ9: 0 | AK9: =SUM(F9:AJ9) -> 0
A10: Factura N° 15 Sofía Jottar | B10: F15 | C10: 43904 | D10: 160200 | AJ10: 0 | AK10: =SUM(F10:AJ10) -> 0
A11: Factura N° XX Sofía Jottar SPRITZ | B11: FXX | D11: =4500*60 -> 270000 | E11: por facturar | AJ11: 0 | AK11: =SUM(F11:AJ11) -> 0
A12: Factura N° 44 Entretoros | B12: F44 | C12: 44209 | D12: 31333 | O12: 31333 | AK12: =SUM(F12:AJ12) -> 31333
A13: Factura N° 46 Entretoros | B13: F46 | C13: 44229 | D13: =31333+3050*10/0.75 -> 71999.667 | O13: =31333+3050*10/0.75 -> 71999.667 | AK13: =SUM(F13:AJ13) -> 71999.667
A14: Factura Gilberto | D14: 31333 | AK14: =SUM(F14:AJ14) -> 0
A15: Factura N°56 Marina | B15: F56 | C15: 44251 | D15: 141598 | H15: 141598 | AK15: =SUM(F15:AJ15) -> 141598
A16: Factura N° 57 Entretoros | B16: F57 | C16: 44251 | D16: =31333 -> 31333 | O16: =31333 -> 31333 | AK16: =SUM(F16:AJ16) -> 31333
A17: Factura N°58 Marina | B17: F58 | C17: 44257 | D17: 251864 | O17: 251864 | AK17: =SUM(F17:AJ17) -> 251864
A18: Factura N°59 Marina ARRIENDO VAR FEB2020 | B18: F59 | C18: 44257 | D18: 23247 | O18: 23247 | AK18: =SUM(F18:AJ18) -> 23247
AK19: =SUM(AK5:AK18) -> 551374.67
A21: SII DEVOLUCION PPM 2019 | C21: 43980 | D21: 10465
A22: Aporte LV | D22: 0 | F22: 0 | G22: 0
A23: Aporte ML | G23: 0
A24: SENCE subsidio
A27: TOTAL INGRESOS | F27: =SUM(F5:F26) -> 0 | G27: =SUM(G5:G26) -> 0 | H27: =SUM(H5:H26) -> 141598 | I27: =SUM(I5:I26) -> 0 | J27: =SUM(J5:J26) -> 0 | K27: =SUM(K5:K26) -> 0 | L27: =SUM(L5:L26) -> 0 | M27: =SUM(M5:M26) -> 0 | ... AJ27: =SUM(AJ5:AJ26) -> 0
A29: EGRESOS
A30: Boleta N° xxx EMS Remun Junio 2020 | B30: Bxxx | D30: =500000/2 -> 250000
A31: Boleta N° xxx EMS Remun Julio 2020 | B31: Bxxx | D31: =500000/2 -> 250000
A32: Boleta N° xxx EMS Remun Agosto 2020 | B32: Bxxx | D32: =500000/2 -> 250000
A33: Boleta N° xxx EMS Remun Sept 2020 | B33: Bxxx | D33: 250000
A34: Boleta N° xxx EMS Remun Oct 2020 | B34: Bxxx | D34: 500000
A35: Boleta N° xxx EMS Remun Nov 2020 | B35: Bxxx | D35: 500000
A36: Boleta N° xxx EMS Remun Dic2020 | B36: Bxxx | D36: 500000
A37: Boleta N° xxx EMS Remun Ene2021 | B37: Bxxx | D37: 500000
A38: Boleta N° xxx EMS Remun Feb2021 | B38: Bxxx | D38: 500000
A39: Boleta N°130 Remun Var. Gte. Feb 2021 | B39: B130 | D39: =+('FEB-21'!AH28)*0.17 -> 133233.93 | Q39: 133233.93
A40: LANCER EMBOLSADO | B40: F1170013 | C40: 44182 | D40: 121856
A41: ANTAWARA | B41: F5 | C41: 44195 | D41: 240975
A42: LANCER conector abrazaderas | B42: F1070344 | C42: 44203 | D42: 28988 | E42: x
A43: LANCER arriendo equipo N°2 3a cuota | B43: F1070817 | C43: 44229 | D43: =60000*1.19 -> 71400 | E43: x
A44: LANCER arriendo equipo N°3 2a cuota | B44: F1070818 | C44: 44229 | D44: =60000*1.19 -> 71400 | E44: x
A45: ANTAWARA 2700 lt | B45: F14 | C45: 44235 | D45: 2216970 | H45: 400000
A46: Flete Vitacura Chicureo Marina Vitacura | C46: 44238 | D46: =+(19.3+31.7+15.2)*790/9+2432+363+934 -> 9539.8889 | I46: =+(19.3+31.7+15.2)*790/9+2432+363+934 -> 9539.8889
A47: Flete Vitacura Chicureo Vitacura | C47: 44242 | D47: =+(25.6*2)*800/9 -> 4551.1111 | I47: =+(25.6*2)*800/9 -> 4551.1111
A48: SANGRIALEGRIA | B48: F69 | C48: 44242 | D48: 77900 | G48: 77900
A49: Flete Vitacura Marina Vitacura | C49: 44243 | D49: =+(14.4*2)*800/9+674+935 -> 4169 | I49: =+(14.4*2)*800/9+674+935 -> 4169
A50: Flete Vitacura Marina Chicureo Vitacura | C50: 44251 | D50: =+(14.4+28.6+25.7)*800/9+1977+2432+1220 -> 11735.667 | I50: =+(14.4+28.6+25.7)*800/9+1977+2432+1220 -> 11735.667
A51: Flete Vitacura Mari na Vitacura | C51: 44257 | D51: =+(14.4*2)*800/9+674+935 -> 4169 | I51: =+(14.4*2)*800/9+674+935 -> 4169
A52: SANGRIALEGRIA | B52: F70 | C52: 44257 | D52: 110694 | T52: 110694
A53: Flete Vitacura Jazz Corner Recoleta Vitacura | C53: 44259 | D53: =+(15.2+5.6+15.4)*790/9+1304 -> 4481.5556 | I53: =+(15.2+5.6+15.4)*790/9+1304 -> 4481.5556
A54: LANCER embolsado 10x10 lt | B54: F1071146 | C54: 44259 | D54: 38080 | M54: 38080
A55: LANCER arriendo equipo N°2 4a cuota | B55: F1071138 | C55: 44259 | D55: 475030 | E55: x
A56: LANCER arriendo equipo N°3 3a cuota | B56: F1071139 | C56: 44259 | D56: =60000*1.19 -> 71400 | E56: x
A57: Flete Vitacura Marina Jazz Corner Entretoros Vitacura | C57: 44264 | D57: =+(19.3+31.7+15.2)*790/9+2432+363+934 -> 9539.8889 | AH57: =+(19.3+31.7+15.2)*790/9+2432+363+934 -> 9539.8889
A58: Flete Vitacura Marina Jazz Corner Vitacura | C58: 44279 | D58: =+(14.4*2)*800/9+674+935 -> 4169 | AH58: =+(14.4*2)*800/9+674+935 -> 4169
A59: Idealbridge Contabilidad Abono Decl Renta, Rectif y Deecl.Juradas | C59: 44281 | D59: 100000 | AE59: 100000
A60: F29 Feb | D60: 46172 | O60: 46172
C62: A.FIJO | D62: =+SUMIF(E40:E55,"x",D40:D55) -> 646818
A65: TOTAL EGRESOS | F65: =SUM(F30:F64) -> 0 | G65: =SUM(G30:G64) -> 77900 | H65: =SUM(H30:H64) -> 400000 | I65: =SUM(I30:I64) -> 38646.222 | J65: =SUM(J30:J64) -> 0 | K65: =SUM(K30:K64) -> 0 | L65: =SUM(L30:L64) -> 0 | M65: =SUM(M30:M64) -> 38080 | ... AJ65: =SUM(AJ30:AJ64) -> 0
A66: SALDO FINAL | F66: =+F27+F3-F65 -> 520473.83 | G66: =+G3+G27-G65 -> 442573.83 | H66: =+H3+H27-H65 -> 184171.83 | I66: =+I3+I27-I65 -> 145525.61 | J66: =+J3+J27-J65 -> 145525.61 | K66: =+K3+K27-K65 -> 145525.61 | L66: =+L3+L27-L65 -> 145525.61 | M66: =+M3+M27-M65 -> 107445.61 | N66: =+N3+N27-N65 -> 107445.61 | ... AJ66: =+AJ3+AJ27-AJ65 -> 113413.45

Sheet ABR-21
B2: N° doc | C2: Fecha | D2: Monto Bruto | E2: Forma Pago | F2: 44287 | G2: 44288 | H2: 44289 | I2: 44290 | J2: 44291 | K2: 44292 | L2: 44293 | M2: 44294 | N2: 44295 | O2: 44296 | P2: 44297 | Q2: 44298 | R2: 44299 | S2: 44300 | T2: 44301 | U2: 44302 | V2: 44303 | W2: 44304 | X2: 44305 | Y2: 44306 | Z2: 44307 | AA2: 44308 | AB2: 44309 | AC2: 44310 | AD2: 44311 | AE2: 44312 | AF2: 44313 | AG2: 44314 | AH2: 44315 | AI2: 44316 | AJ2: TOTAL
A3: SALDO INICIAL | F3: =+'MAR-21'!AJ66 -> 113413.45 | G3: =+F55 -> 113413.45 | H3: =+G55 -> 113413.45 | I3: =+H55 -> 113413.45 | J3: =+I55 -> 113413.45 | K3: =+J55 -> 13025.454 | L3: =+K55 -> 13025.454 | M3: =+L55 -> 13025.454 | N3: =+M55 -> 13025.454 | ... AI3: =+AH55 -> 274129.45
A4: INGRESOS
A5: Factura N° 10 Sofía Jottar | B5: F10 | C5: 43866 | D5: 33728 | AI5: 0 | AJ5: =SUM(E5:AI5) -> 0
A6: Factura N° 11 Sofía Jottar | B6: F11 | C6: 43876 | D6: 160200 | AI6: 0 | AJ6: =SUM(E6:AI6) -> 0
A7: Factura N° 12 Sofía Jottar | B7: F12 | C7: 43882 | D7: 160200 | AI7: 0 | AJ7: =SUM(E7:AI7) -> 0
A8: Factura N° 13 Sofía Jottar | B8: F13 | C8: 43889 | D8: 160200 | AI8: 0 | AJ8: =SUM(E8:AI8) -> 0
A9: Factura N° 14 Sofía Jottar | B9: F14 | C9: 43892 | D9: =28475.41*1.19 -> 33885.738 | AI9: 0 | AJ9: =SUM(E9:AI9) -> 0
A10: Factura N° 15 Sofía Jottar | B10: F15 | C10: 43904 | D10: 160200 | AI10: 0 | AJ10: =SUM(E10:AI10) -> 0
A11: Factura N° XX Sofía Jottar SPRITZ | B11: FXX | D11: =4500*60 -> 270000 | E11: por facturar | AI11: 0 | AJ11: =SUM(E11:AI11) -> 0
AJ18: =SUM(AJ5:AJ11) -> 0
A20: SII DEVOLUCION PPM 2019 | C20: 43980 | D20: 10465
A21: Aporte LV | D21: 300000 | Y21: 300000
A22: Aporte ML
A23: SENCE subsidio
A26: TOTAL INGRESOS | F26: =SUM(F5:F25) -> 0 | G26: =SUM(G5:G25) -> 0 | H26: =SUM(H5:H25) -> 0 | I26: =SUM(I5:I25) -> 0 | J26: =SUM(J5:J25) -> 0 | K26: =SUM(K5:K25) -> 0 | L26: =SUM(L5:L25) -> 0 | M26: =SUM(M5:M25) -> 0 | ... AJ26: =SUM(AJ5:AJ25) -> 0
A28: EGRESOS
A29: Boleta N° xxx EMS Remun Junio 2020 | B29: Bxxx | D29: =500000/2 -> 250000 | AJ29: 0
A30: Boleta N° xxx EMS Remun Julio 2020 | B30: Bxxx | D30: =500000/2 -> 250000 | AJ30: 0
A31: Boleta N° xxx EMS Remun Agosto 2020 | B31: Bxxx | D31: =500000/2 -> 250000 | AJ31: 0
A32: Boleta N° xxx EMS Remun Sept 2020 | B32: Bxxx | D32: 250000 | AJ32: 0
A33: Boleta N° xxx EMS Remun Oct 2020 | B33: Bxxx | D33: 500000 | AJ33: 0
A34: Boleta N° xxx EMS Remun Nov 2020 | B34: Bxxx | D34: 500000 | AJ34: 0
A35: Boleta N° xxx EMS Remun Dic2020 | B35: Bxxx | D35: 500000 | AJ35: 0
A36: Boleta N° xxx EMS Remun Ene2021 | B36: Bxxx | D36: 500000 | AJ36: 0
A37: Boleta N° xxx EMS Remun Feb2021 | B37: Bxxx | D37: 500000 | AJ37: 0
A38: Boleta N° xxx EMS Remun Marzo 2021 | B38: Bxxx | D38: 250000
A39: Boleta N°xxx Remun Var. Gte. Mar 2021 | B39: Bxxx | D39: =+'MAR-21'!AK19*0.17 -> 93733.693
A40: LANCER EMBOLSADO | B40: F1170013 | C40: 44182 | D40: 121856
A41: ANTAWARA | B41: F5 | C41: 44195 | D41: 240975
A42: LANCER conector abrazaderas | B42: F1070344 | C42: 44203 | D42: 28988 | E42: x | J42: 28988
A43: LANCER arriendo equipo N°2 3a cuota | B43: F1070817 | C43: 44229 | D43: =60000*1.19 -> 71400 | E43: x | J43: 71400
A44: LANCER arriendo equipo N°3 2a cuota | B44: F1070818 | C44: 44229 | D44: =60000*1.19 -> 71400 | E44: x
A45: ANTAWARA 2700 lt | B45: F14 | C45: 44235 | D45: =2216970-'MAR-21'!$H$45 -> 1816970 | AJ45: 0
A46: LANCER arriendo equipo N°2 4a cuota | B46: F1071138 | C46: 44259 | D46: 475030 | E46: x
A47: LANCER arriendo equipo N°3 3a cuota | B47: F1071139 | C47: 44259 | D47: =60000*1.19 -> 71400 | E47: x
A48: Oficina Virtual (semestre) | C48: 44269 | D48: 109000
A49: F29 Marzo | C49: 44296 | D49: 17540 | Y49: 17540
A50: LANCER arriendo equipo N°3 4a cuota | B50: F11071495 | C50: 44298 | D50: =262085*1.19 -> 311881.15 | E50: x
A51: Credito FOGAPE | B51: Cuota N° 1 de 25 | C51: 44291 | D51: 21356 | Z51: 21356
C52: A.FIJO | D52: =+SUMIF(E40:E50,"x",D40:D50) -> 1030099.1
A54: TOTAL EGRESOS | F54: =SUM(F29:F53) -> 0 | G54: =SUM(G29:G53) -> 0 | H54: =SUM(H29:H53) -> 0 | I54: =SUM(I29:I53) -> 0 | J54: =SUM(J29:J53) -> 100388 | K54: =SUM(K29:K53) -> 0 | L54: =SUM(L29:L53) -> 0 | M54: =SUM(M29:M53) -> 0 | ... AI54: =SUM(AI29:AI53) -> 0
A55: SALDO FINAL | F55: =+F26+F3-F54 -> 113413.45 | G55: =+G3+G26-G54 -> 113413.45 | H55: =+H3+H26-H54 -> 113413.45 | I55: =+I3+I26-I54 -> 113413.45 | J55: =+J3+J26-J54 -> 13025.454 | K55: =+K3+K26-K54 -> 13025.454 | L55: =+L3+L26-L54 -> 13025.454 | M55: =+M3+M26-M54 -> 13025.454 | N55: =+N3+N26-N54 -> 13025.454 | ... AI55: =+AI3+AI26-AI54 -> 274129.45
E59: Prioridad
A60: F29 Marzo | C60: 44296 | D60: 17549 | E60: 1
A61: Credito FOGAPE | B61: Cuota N° 1 de 25 | C61: 44291 | D61: 21178 | E61: 2
A62: LANCER EMBOLSADO | B62: F1170013 | C62: 44182 | D62: 121856 | E62: 3
A63: Oficina Virtual (semestre) | C63: 44269 | D63: 109000 | E63: 4
A64: LANCER arriendo equipo N°3 2a cuota | B64: F1070818 | C64: 44229 | D64: =60000*1.19 -> 71400 | E64: 5
A65: Idealbridge Contabilidad Saldo Decl Renta, Rectif y Decl.Juradas | C65: 44316 | D65: 100000 | E65: 6
A66: LANCER arriendo equipo N°2 4a cuota | B66: F1071138 | C66: 44259 | D66: 475030 | E66: 7
A67: LANCER arriendo equipo N°3 3a cuota | B67: F1071139 | C67: 44259 | D67: =60000*1.19 -> 71400 | E67: 8
A68: LANCER arriendo equipo N°2 4a cuota | B68: F11071495 | C68: 44298 | D68: =262085*1.19 -> 311881.15 | E68: 9
A69: ANTAWARA 2700 lt | B69: F14 | C69: 44235 | D69: =2216970-400000 -> 1816970 | E69: 10
A70: ANTAWARA | B70: F5 | C70: 44195 | D70: 240975 | E70: 11

Sheet MAY-21
B2: N° doc | C2: Fecha | D2: Monto Bruto | E2: Forma Pago | F2: 44317 | G2: 44318 | H2: 44319 | I2: 44320 | J2: 44321 | K2: 44322 | L2: 44323 | M2: 44324 | N2: 44325 | O2: 44326 | P2: 44327 | Q2: 44328 | R2: 44329 | S2: 44330 | T2: 44331 | U2: 44332 | V2: 44333 | W2: 44334 | X2: 44335 | Y2: 44336 | Z2: 44337 | AA2: 44338 | AB2: 44339 | AC2: 44340 | AD2: 44341 | AE2: 44342 | AF2: 44343 | AG2: 44344 | AH2: 44345 | AI2: 44346 | AJ2: 44347 | AK2: TOTAL
A3: SALDO INICIAL | F3: =+'ABR-21'!AI55 -> 274129.45 | G3: =+F51 -> 274129.45 | H3: =+G51 -> 274129.45 | I3: =+H51 -> 274129.45 | J3: =+I51 -> 274129.45 | K3: =+J51 -> 252944.45 | L3: =+K51 -> 252944.45 | M3: =+L51 -> 202944.45 | N3: =+M51 -> 202944.45 | ... AJ3: =+AI51 -> 189620.45
A4: INGRESOS
A5: Factura N° 10 Sofía Jottar | B5: F10 | C5: 43866 | D5: 33728 | AJ5: 0 | AK5: =SUM(E5:AJ5) -> 0
A6: Factura N° 11 Sofía Jottar | B6: F11 | C6: 43876 | D6: 160200 | AJ6: 0 | AK6: =SUM(E6:AJ6) -> 0
A7: Factura N° 12 Sofía Jottar | B7: F12 | C7: 43882 | D7: 160200 | AJ7: 0 | AK7: =SUM(E7:AJ7) -> 0
A8: Factura N° 13 Sofía Jottar | B8: F13 | C8: 43889 | D8: 160200 | AJ8: 0 | AK8: =SUM(E8:AJ8) -> 0
A9: Factura N° 14 Sofía Jottar | B9: F14 | C9: 43892 | D9: =28475.41*1.19 -> 33885.738 | AJ9: 0 | AK9: =SUM(E9:AJ9) -> 0
A10: Factura N° 15 Sofía Jottar | B10: F15 | C10: 43904 | D10: 160200 | AJ10: 0 | AK10: =SUM(E10:AJ10) -> 0
A11: Factura N° XX Sofía Jottar SPRITZ | B11: FXX | D11: =4500*60 -> 270000 | E11: por facturar | AJ11: 0 | AK11: =SUM(E11:AJ11) -> 0
A12: Factura N° 60 Jazz Corner | B12: F60 | C12: 44328 | D12: 138825 | AJ12: 0 | AK12: =SUM(E12:AJ12) -> 0
A13: Factura N° 61 Jazz Corner | B13: F61 | C13: 44335 | D13: 76160 | AJ13: 0 | AK13: =SUM(E13:AJ13) -> 0
AK14: =SUM(AK5:AK13) -> 0
A15: SII DEVOLUCION PPM 2019 | C15: 43980 | D15: 10465
A16: Aporte LV | D16: 0
A17: Aporte ML
A18: SENCE subsidio
A21: TOTAL INGRESOS | F21: =SUM(F5:F20) -> 0 | G21: =SUM(G5:G20) -> 0 | H21: =SUM(H5:H20) -> 0 | I21: =SUM(I5:I20) -> 0 | J21: =SUM(J5:J20) -> 0 | K21: =SUM(K5:K20) -> 0 | L21: =SUM(L5:L20) -> 0 | M21: =SUM(M5:M20) -> 0 | ... AJ21: =SUM(AJ5:AJ20) -> 0
A23: EGRESOS
A24: Boleta N° xxx EMS Remun Junio 2020 | B24: Bxxx | D24: =500000/2 -> 250000
A25: Boleta N° xxx EMS Remun Julio 2020 | B25: Bxxx | D25: =500000/2 -> 250000
A26: Boleta N° xxx EMS Remun Agosto 2020 | B26: Bxxx | D26: =500000/2 -> 250000
A27: Boleta N° xxx EMS Remun Sept 2020 | B27: Bxxx | D27: 250000
A28: Boleta N° xxx EMS Remun Oct 2020 | B28: Bxxx | D28: 500000
A29: Boleta N° xxx EMS Remun Nov 2020 | B29: Bxxx | D29: 500000
A30: Boleta N° xxx EMS Remun Dic2020 | B30: Bxxx | D30: 500000
A31: Boleta N° xxx EMS Remun Ene2021 | B31: Bxxx | D31: 500000
A32: Boleta N° xxx EMS Remun Feb2021 | B32: Bxxx | D32: 500000
A33: Boleta N° xxx EMS Remun Marzo 2021 | B33: Bxxx | D33: 250000
A34: Boleta N°xxx Remun Var. Gte. Mar 2021 | B34: Bxxx | D34: =+'MAR-21'!AK19*0.17 -> 93733.693
A35: LANCER EMBOLSADO | B35: F1170013 | C35: 44182 | D35: 121856
A36: ANTAWARA | B36: F5 | C36: 44195 | D36: 240975
A37: LANCER arriendo equipo N°3 2a cuota | B37: F1070818 | C37: 44229 | D37: =60000*1.19 -> 71400 | E37: x
A38: ANTAWARA 2700 lt | B38: F14 | C38: 44235 | D38: =2216970-'MAR-21'!$H$45 -> 1816970
A39: LANCER arriendo equipo N°2 4a cuota | B39: F1071138 | C39: 44259 | D39: 475030 | E39: x
A40: LANCER arriendo equipo N°3 3a cuota | B40: F1071139 | C40: 44259 | D40: =60000*1.19 -> 71400 | E40: x
A41: Oficina Virtual (semestre) (abono) | B41: F269 | C41: 44412 | D41: 50000 | L41: 50000
A42: LANCER arriendo equipo N°3 4a cuota | B42: F11071495 | C42: 44298 | D42: =262085*1.19 -> 311881.15 | E42: x
A43: Credito FOGAPE | B43: Cuota N° 2 de 25 | C43: 44321 | D43: 21185 | J43: 21185
A44: Flete Vitacura Marina Jazz Corner Vitacura | C44: 44328 | D44: =+(14.4*2)*880/9+1304+935 -> 5055 | AF44: =+(14.4*2)*880/9+1304+935 -> 5055
A45: Flete Vitacura LANCER Vitacura | C45: 44335 | D45: =+(15.4*2)*900/9+1304+935 -> 5319 | AF45: =+(15.4*2)*900/9+1304+935 -> 5319
A46: Mundo Cervecero Deterg.desincrustante | B46: F20833 | C46: 44343 | D46: 2950 | E46: TC ems | AF46: 2950
A47: F29 Abril | C47: 44326 | D47: 0
C49: A.FIJO | D49: =+SUMIF(E35:E42,"x",D35:D42) -> 929711.15
A50: TOTAL EGRESOS | F50: =SUM(F24:F49) -> 0 | G50: =SUM(G24:G49) -> 0 | H50: =SUM(H24:H49) -> 0 | I50: =SUM(I24:I49) -> 0 | J50: =SUM(J24:J49) -> 21185 | K50: =SUM(K24:K49) -> 0 | L50: =SUM(L24:L49) -> 50000 | M50: =SUM(M24:M49) -> 0 | ... AJ50: =SUM(AJ24:AJ49) -> 0
A51: SALDO FINAL | F51: =+F21+F3-F50 -> 274129.45 | G51: =+G3+G21-G50 -> 274129.45 | H51: =+H3+H21-H50 -> 274129.45 | I51: =+I3+I21-I50 -> 274129.45 | J51: =+J3+J21-J50 -> 252944.45 | K51: =+K3+K21-K50 -> 252944.45 | L51: =+L3+L21-L50 -> 202944.45 | M51: =+M3+M21-M50 -> 202944.45 | N51: =+N3+N21-N50 -> 202944.45 | ... AJ51: =+AJ3+AJ21-AJ50 -> 189620.45
E55: Prioridad
A56: F29 Marzo | C56: 44296 | D56: 17549 | E56: 1
A57: Credito FOGAPE | B57: Cuota N° 1 de 25 | C57: 44291 | D57: 21178 | E57: 2
A58: LANCER EMBOLSADO | B58: F1170013 | C58: 44182 | D58: 121856 | E58: 3
A59: Oficina Virtual (semestre) | C59: 44269 | D59: 109000 | E59: 4
A60: LANCER arriendo equipo N°3 2a cuota | B60: F1070818 | C60: 44229 | D60: =60000*1.19 -> 71400 | E60: 5
A61: Idealbridge Contabilidad Saldo Decl Renta, Rectif y Decl.Juradas | C61: 44316 | D61: 100000 | E61: 6
A62: LANCER arriendo equipo N°2 4a cuota | B62: F1071138 | C62: 44259 | D62: 475030 | E62: 7
A63: LANCER arriendo equipo N°3 3a cuota | B63: F1071139 | C63: 44259 | D63: =60000*1.19 -> 71400 | E63: 8
A64: LANCER arriendo equipo N°2 4a cuota | B64: F11071495 | C64: 44298 | D64: =262085*1.19 -> 311881.15 | E64: 9
A65: ANTAWARA 2700 lt | B65: F14 | C65: 44235 | D65: =2216970-400000 -> 1816970 | E65: 10
A66: ANTAWARA | B66: F5 | C66: 44195 | D66: 240975 | E66: 11

Sheet JUN-21
B2: N° doc | C2: Fecha | D2: Monto Bruto | E2: Forma Pago | F2: 44348 | G2: 44349 | H2: 44350 | I2: 44351 | J2: 44352 | K2: 44353 | L2: 44354 | M2: 44355 | N2: 44356 | O2: 44357 | P2: 44358 | Q2: 44359 | R2: 44360 | S2: 44361 | T2: 44362 | U2: 44363 | V2: 44364 | W2: 44365 | X2: 44366 | Y2: 44367 | Z2: 44368 | AA2: 44369 | AB2: 44370 | AC2: 44371 | AD2: 44372 | AE2: 44373 | AF2: 44374 | AG2: 44375 | AH2: 44376 | AI2: 44377 | AK2: TOTAL
A3: SALDO INICIAL | F3: =+'MAY-21'!AJ51 -> 189620.45 | G3: =+F49 -> 189620.45 | H3: =+G49 -> 189620.45 | I3: =+H49 -> 189620.45 | J3: =+I49 -> 189620.45 | K3: =+J49 -> 189620.45 | L3: =+K49 -> 189620.45 | M3: =+L49 -> 168435.45 | N3: =+M49 -> 168435.45 | ... AI3: =+AH49 -> 10329.454
A4: INGRESOS
A5: Factura N° 10 Sofía Jottar | B5: F10 | C5: 43866 | D5: 33728 | AI5: 0 | AK5: =SUM($E5:AI5) -> 0
A6: Factura N° 11 Sofía Jottar | B6: F11 | C6: 43876 | D6: 160200 | AI6: 0 | AK6: =SUM($E6:AI6) -> 0
A7: Factura N° 12 Sofía Jottar | B7: F12 | C7: 43882 | D7: 160200 | AI7: 0 | AK7: =SUM($E7:AI7) -> 0
A8: Factura N° 13 Sofía Jottar | B8: F13 | C8: 43889 | D8: 160200 | AI8: 0 | AK8: =SUM($E8:AI8) -> 0
A9: Factura N° 14 Sofía Jottar | B9: F14 | C9: 43892 | D9: =28475.41*1.19 -> 33885.738 | AI9: 0 | AK9: =SUM($E9:AI9) -> 0
A10: Factura N° 15 Sofía Jottar | B10: F15 | C10: 43904 | D10: 160200 | AI10: 0 | AK10: =SUM($E10:AI10) -> 0
A11: Factura N° XX Sofía Jottar SPRITZ | B11: FXX | D11: 0 | E11: por facturar | AI11: 0 | AK11: =SUM($E11:AI11) -> 0
A12: Factura N° 60 Jazz Corner | B12: F60 | C12: 44328 | D12: 138825 | AI12: 0 | AK12: =SUM($E12:AI12) -> 0
A13: Factura N° 61 Jazz Corner | B13: F61 | C13: 44335 | D13: 76160 | AI13: 0 | AK13: =SUM($E13:AI13) -> 0
AK14: =SUM(AK5:AK13) -> 0
A15: SII DEVOLUCION PPM 2019 | C15: 43980 | D15: 10465
A16: Aporte LV | D16: 0
A17: Aporte ML
A18: SENCE subsidio
A21: TOTAL INGRESOS | F21: =SUM(F5:F20) -> 0 | G21: =SUM(G5:G20) -> 0 | H21: =SUM(H5:H20) -> 0 | I21: =SUM(I5:I20) -> 0 | J21: =SUM(J5:J20) -> 0 | K21: =SUM(K5:K20) -> 0 | L21: =SUM(L5:L20) -> 0 | M21: =SUM(M5:M20) -> 0 | ... AJ21: =SUM(AJ5:AJ20) -> 0
A23: EGRESOS
A24: Boleta N° xxx EMS Remun Junio 2020 | B24: Bxxx | D24: =500000/2 -> 250000 | AJ24: 0
A25: Boleta N° xxx EMS Remun Julio 2020 | B25: Bxxx | D25: =500000/2 -> 250000 | AJ25: =SUM(F24:AI24) -> 0
A26: Boleta N° xxx EMS Remun Agosto 2020 | B26: Bxxx | D26: =500000/2 -> 250000 | AJ26: 0
A27: Boleta N° xxx EMS Remun Sept 2020 | B27: Bxxx | D27: 250000 | AJ27: 0
A28: Boleta N° xxx EMS Remun Oct 2020 | B28: Bxxx | D28: 500000 | AJ28: 0
A29: Boleta N° xxx EMS Remun Nov 2020 | B29: Bxxx | D29: 500000 | AJ29: 0
A30: Boleta N° xxx EMS Remun Dic2020 | B30: Bxxx | D30: 500000 | AJ30: 0
A31: Boleta N° xxx EMS Remun Ene2021 | B31: Bxxx | D31: 500000 | AJ31: 0
A32: Boleta N° xxx EMS Remun Feb2021 | B32: Bxxx | D32: 500000 | AJ32: 0
A33: Boleta N° xxx EMS Remun Marzo 2021 | B33: Bxxx | D33: 250000
A34: Boleta N°xxx Remun Var. Gte. Mar 2021 | B34: Bxxx | D34: =+'MAR-21'!AK19*0.17 -> 93733.693
A35: LANCER EMBOLSADO | B35: F1170013 | C35: 44182 | D35: 121856 | U35: 121856
A36: ANTAWARA | B36: F5 | C36: 44195 | D36: 240975
A37: LANCER arriendo equipo N°3 2a cuota | B37: F1070818 | C37: 44229 | D37: =60000*1.19 -> 71400 | E37: x
A38: ANTAWARA 2700 lt | B38: F14 | C38: 44235 | D38: =2216970-'MAR-21'!$H$45 -> 1816970
A39: LANCER arriendo equipo N°2 4a cuota | B39: F1071138 | C39: 44259 | D39: 475030 | E39: x
A40: LANCER arriendo equipo N°3 3a cuota | B40: F1071139 | C40: 44259 | D40: =60000*1.19 -> 71400 | E40: x
A41: LANCER arriendo equipo N°3 4a cuota | B41: F11071495 | C41: 44298 | D41: =262085*1.19 -> 311881.15 | E41: x
A42: Credito FOGAPE | B42: Cuota N° 3 de 25 | C42: 44354 | D42: 21185 | E42: cargo Cta Vista | L42: 21185
A43: F29 Mayo | C43: 44357 | D43: 226 | E43: Transf | O43: 226
A44: TCL Group capilares | B44: F4283 | C44: 44357 | D44: 6274 | E44: Transf | O44: 6274
A45: LANCER Medidor TDS | B45: F1072123 | C45: 44369 | D45: 29750 | E45: Transf | AA45: 29750
C47: A.FIJO | D47: =+SUMIF(E35:E41,"x",D35:D41) -> 929711.15
A48: TOTAL EGRESOS | F48: =SUM(F24:F47) -> 0 | G48: =SUM(G24:G47) -> 0 | H48: =SUM(H24:H47) -> 0 | I48: =SUM(I24:I47) -> 0 | J48: =SUM(J24:J47) -> 0 | K48: =SUM(K24:K47) -> 0 | L48: =SUM(L24:L47) -> 21185 | M48: =SUM(M24:M47) -> 0 | ... AI48: =SUM(AI24:AI47) -> 0
A49: SALDO FINAL | F49: =+F21+F3-F48 -> 189620.45 | G49: =+G3+G21-G48 -> 189620.45 | H49: =+H3+H21-H48 -> 189620.45 | I49: =+I3+I21-I48 -> 189620.45 | J49: =+J3+J21-J48 -> 189620.45 | K49: =+K3+K21-K48 -> 189620.45 | L49: =+L3+L21-L48 -> 168435.45 | M49: =+M3+M21-M48 -> 168435.45 | N49: =+N3+N21-N48 -> 168435.45 | ... AI49: =+AI3+AI21-AI48 -> 10329.454
E53: Prioridad
A54: F29 Marzo | C54: 44296 | D54: 17549 | E54: 1
A55: Credito FOGAPE | B55: Cuota N° 1 de 25 | C55: 44291 | D55: 21178 | E55: 2
A56: LANCER EMBOLSADO | B56: F1170013 | C56: 44182 | D56: 121856 | E56: 3
A57: Oficina Virtual (semestre) | C57: 44269 | D57: 109000 | E57: 4
A58: LANCER arriendo equipo N°3 2a cuota | B58: F1070818 | C58: 44229 | D58: =60000*1.19 -> 71400 | E58: 5
A59: Idealbridge Contabilidad Saldo Decl Renta, Rectif y Decl.Juradas | C59: 44316 | D59: 100000 | E59: 6
A60: LANCER arriendo equipo N°2 4a cuota | B60: F1071138 | C60: 44259 | D60: 475030 | E60: 7
A61: LANCER arriendo equipo N°3 3a cuota | B61: F1071139 | C61: 44259 | D61: =60000*1.19 -> 71400 | E61: 8
A62: LANCER arriendo equipo N°2 4a cuota | B62: F11071495 | C62: 44298 | D62: =262085*1.19 -> 311881.15 | E62: 9
A63: ANTAWARA 2700 lt | B63: F14 | C63: 44235 | D63: =2216970-400000 -> 1816970 | E63: 10
A64: ANTAWARA | B64: F5 | C64: 44195 | D64: 240975 | E64: 11

Sheet JUL-21
B2: N° doc | C2: Fecha | D2: Monto Bruto | E2: Forma Pago | F2: 44378 | G2: 44379 | H2: 44380 | I2: 44381 | J2: 44382 | K2: 44383 | L2: 44384 | M2: 44385 | N2: 44386 | O2: 44387 | P2: 44388 | Q2: 44389 | R2: 44390 | S2: 44391 | T2: 44392 | U2: 44393 | V2: 44394 | W2: 44395 | X2: 44396 | Y2: 44397 | Z2: 44398 | AA2: 44399 | AB2: 44400 | AC2: 44401 | AD2: 44402 | AE2: 44403 | AF2: 44404 | AG2: 44405 | AH2: 44406 | AI2: 44407 | AJ2: 44408 | AK2: TOTAL
A3: SALDO INICIAL | F3: =+'JUN-21'!AI49 -> 10329.454 | G3: =+F66 -> 10329.454 | H3: =+G66 -> 10329.454 | I3: =+H66 -> 10329.454 | J3: =+I66 -> 10329.454 | K3: =+J66 -> 10329.454 | L3: =+K66 -> 10329.454 | M3: =+L66 -> 522417.45 | N3: =+M66 -> 465290.12 | ... AJ3: =+AI66 -> 907398.12
A4: INGRESOS
A5: Factura N° 10 Sofía Jottar | B5: F10 | C5: 43866 | D5: 33728 | AK5: =SUM($E5:AJ5) -> 0
A6: Factura N° 11 Sofía Jottar | B6: F11 | C6: 43876 | D6: 160200 | AK6: =SUM($E6:AJ6) -> 0
A7: Factura N° 12 Sofía Jottar | B7: F12 | C7: 43882 | D7: 160200 | AK7: =SUM($E7:AJ7) -> 0
A8: Factura N° 13 Sofía Jottar | B8: F13 | C8: 43889 | D8: 160200 | AK8: =SUM($E8:AJ8) -> 0
A9: Factura N° 14 Sofía Jottar | B9: F14 | C9: 43892 | D9: =28475.41*1.19 -> 33885.738 | AK9: =SUM($E9:AJ9) -> 0
A10: Factura N° 15 Sofía Jottar | B10: F15 | C10: 43904 | D10: 160200 | AK10: =SUM($E10:AJ10) -> 0
A11: Factura N° XX Sofía Jottar SPRITZ | B11: FXX | D11: 0 | E11: por facturar | AK11: =SUM($E11:AJ11) -> 0
A12: Factura N° 60 Jazz Corner | B12: F60 | C12: 44328 | D12: 138825 | AK12: =SUM($E12:AJ12) -> 0
A13: Factura N° 61 Jazz Corner | B13: F61 | C13: 44335 | D13: 76160 | AK13: =SUM($E13:AJ13) -> 0
A14: Factura N° 62 Sangria Alegria | B14: F62 | C14: 44381 | D14: 19278 | L14: 19278 | AK14: =SUM($E14:AJ14) -> 19278
A15: Factura N° 63 Sangria Alegria | B15: F63 | C15: 44384 | D15: 499800 | L15: 499800 | AK15: =SUM($E15:AJ15) -> 499800
A16: Factura N° 64 Los Laureles | B16: F64 | C16: 44384 | D16: 136017 | Q16: 136017 | AK16: =SUM($E16:AJ16) -> 136017
A17: Factura N° 65 Los Laureles | B17: F65 | C17: 44384 | D17: 45339 | AA17: 45339 | AK17: =SUM($E17:AJ17) -> 45339
A18: BONO PYME | C18: 44392 | D18: 1000000 | T18: 1000000 | AK18: =SUM($E18:AJ18) -> 1000000
A19: Factura N° 66 Sangria Alegria | B19: F66 | C19: 44384 | D19: 15232 | AA19: 15232 | AK19: =SUM($E19:AJ19) -> 15232
A20: Factura N° 67 Jazz Corner | B20: F67 | C20: 44406 | D20: 31333 | AK20: =SUM($E20:AJ20) -> 0
A21: Factura N° 68 Sangria Alegria | B21: F68 | C21: 44407 | D21: 7616 | AK21: =SUM($E21:AJ21) -> 0
A22: SII DEVOLUCION PPM 2019 | C22: 43980 | D22: 10465 | AK22: =SUM($E22:AI22) -> 0
A23: Aporte LV | D23: 0
A24: Aporte ML
A25: SENCE subsidio
A28: TOTAL INGRESOS | F28: =SUM(F5:F27) -> 0 | G28: =SUM(G5:G27) -> 0 | H28: =SUM(H5:H27) -> 0 | I28: =SUM(I5:I27) -> 0 | J28: =SUM(J5:J27) -> 0 | K28: =SUM(K5:K27) -> 0 | L28: =SUM(L5:L27) -> 519078 | M28: =SUM(M5:M27) -> 0 | ... AJ28: =SUM(AJ5:AJ27) -> 0 | AK28: =SUM(AK5:AK23)-AK18 -> 715666
A30: EGRESOS
A31: Boleta N° xxx EMS Remun Junio 2020 | B31: Bxxx | D31: =500000/2 -> 250000
A32: Boleta N° xxx EMS Remun Julio 2020 | B32: Bxxx | D32: =500000/2 -> 250000
A33: Boleta N° xxx EMS Remun Agosto 2020 | B33: Bxxx | D33: =500000/2 -> 250000
A34: Boleta N° xxx EMS Remun Sept 2020 | B34: Bxxx | D34: 250000
A35: Boleta N° xxx EMS Remun Oct 2020 | B35: Bxxx | D35: 500000
A36: Boleta N° xxx EMS Remun Nov 2020 | B36: Bxxx | D36: 500000
A37: Boleta N° xxx EMS Remun Dic2020 | B37: Bxxx | D37: 500000
A38: Boleta N° xxx EMS Remun Ene2021 | B38: Bxxx | D38: 500000
A39: Boleta N° xxx EMS Remun Feb2021 | B39: Bxxx | D39: 500000
A40: Boleta N° xxx EMS Remun Marzo 2021 | B40: Bxxx | D40: 250000
A41: Boleta N°xxx Remun Var. Gte. Mar 2021 | B41: Bxxx | D41: =+'MAR-21'!AK19*0.17 -> 93733.693
A42: ANTAWARA | B42: F5 | C42: 44195 | D42: 240975
A43: LANCER arriendo equipo N°3 2a cuota | B43: F1070818 | C43: 44229 | D43: =60000*1.19 -> 71400 | E43: x | Q43: =60000*1.19 -> 71400
A44: ANTAWARA 2700 lt | B44: F14 | C44: 44235 | D44: =2216970-'MAR-21'!$H$45 -> 1816970
A45: LANCER arriendo equipo N°2 4a cuota | B45: F1071138 | C45: 44259 | D45: 475030 | E45: x | Y45: 475030
A46: LANCER arriendo equipo N°3 3a cuota | B46: F1071139 | C46: 44259 | D46: =60000*1.19 -> 71400 | E46: x | R46: =+D46 -> 71400
A47: LANCER arriendo equipo N°3 4a cuota | B47: F11071495 | C47: 44298 | D47: =262085*1.19 -> 311881.15 | E47: x
A48: Oficina Virtual (semestre) (saldo) | C48: 44269 | D48: =109000-'MAY-21'!L41 -> 59000
A49: Idealbridge Contabilidad Saldo Decl Renta, Rectif y Decl.Juradas | C49: 44316 | D49: 100000 | X49: 100000
A50: Credito FOGAPE | B50: Cuota N° 4 de 25 | D50: 21245 | E50: cargo Cta Vista | M50: 21244
A51: Flete Vitacura Los Laureles Jazz Corner Vitacura | C51: 44356 | D51: =+(7+8.3+14.7)*850/9+310+170+2132 -> 5445.3333 | M51: =+(7+8.3+14.7)*850/9+310+170+2132 -> 5445.3333
A52: Cargadores CO2 | C52: 44365 | D52: 17000 | E52: TC EMS | M52: 17000
A53: Flete Vitacura Lancer Vitacura | C53: 44369 | D53: =+(15.4*2)*900/9+1304+935 -> 5319 | M53: =+(15.4*2)*900/9+1304+935 -> 5319
A54: Flete Vitacura Los Laureles Vitacura | C54: 44379 | D54: =+(7*2)*900/9 -> 1400 | M54: =+(7*2)*900/9 -> 1400
A55: Flete Vitacura LANCER Vitacura | C55: 44382 | D55: =+(15.4*2)*900/9+1304+935 -> 5319 | M55: =+(15.4*2)*900/9+1304+935 -> 5319
A56: Imp. Johanna Balanza gramera | B56: F5234 | C56: 44384 | D56: 6990 | E56: Transfer | L56: 6990
A57: Flete Vitacura Los Laureles Vitacura | C57: 44384 | D57: =+(7*2)*900/9 -> 1400 | M57: =+(7*2)*900/9 -> 1400
A58: F29 Junio | C58: 44387 | D58: 0
A59: GECORP Detergente DESANAMAX 2 unid | B59: F31041 | C59: 44398 | D59: 6305 | E59: TC EMS | AA59: 6305
A60: Flete Vitacura Lancer Clean Ice Vitacura | C60: 44404 | D60: =+(13.3+3.5+12.5)*950/9+1304+935 -> 5331.7778
A61: Clean Ice recarga CO2 2x2kg + 1x9Kg | B61: F33807 | C61: 44404 | D61: =+(1500*9+3000*4)*1.19 -> 30345 | AF61: =+(1500*9+3000*4)*1.19 -> 30345
A65: TOTAL EGRESOS | F65: =SUM(F31:F64) -> 0 | G65: =SUM(G31:G64) -> 0 | H65: =SUM(H31:H64) -> 0 | I65: =SUM(I31:I64) -> 0 | J65: =SUM(J31:J64) -> 0 | K65: =SUM(K31:K64) -> 0 | L65: =SUM(L31:L64) -> 6990 | M65: =SUM(M31:M64) -> 57127.333 | ... AJ65: =SUM(AJ31:AJ64) -> 0
A66: SALDO FINAL | F66: =+F28+F3-F65 -> 10329.454 | G66: =+G3+G28-G65 -> 10329.454 | H66: =+H3+H28-H65 -> 10329.454 | I66: =+I3+I28-I65 -> 10329.454 | J66: =+J3+J28-J65 -> 10329.454 | K66: =+K3+K28-K65 -> 10329.454 | L66: =+L3+L28-L65 -> 522417.45 | M66: =+M3+M28-M65 -> 465290.12 | N66: =+N3+N28-N65 -> 465290.12 | ... AJ66: =+AJ3+AJ28-AJ65 -> 907398.12
E70: Prioridad
A73: LANCER EMBOLSADO | B73: F1170013 | C73: 44182 | D73: 121856 | E73: 3
A74: Oficina Virtual (semestre) | C74: 44269 | D74: 109000 | E74: 4
A75: LANCER arriendo equipo N°3 2a cuota | B75: F1070818 | C75: 44229 | D75: =60000*1.19 -> 71400 | E75: 5
A76: Idealbridge Contabilidad Saldo Decl Renta, Rectif y Decl.Juradas | C76: 44316 | D76: 100000 | E76: 6
A77: LANCER arriendo equipo N°2 4a cuota | B77: F1071138 | C77: 44259 | D77: 475030 | E77: 7
A78: LANCER arriendo equipo N°3 3a cuota | B78: F1071139 | C78: 44259 | D78: =60000*1.19 -> 71400 | E78: 8
A79: LANCER arriendo equipo N°2 4a cuota | B79: F11071495 | C79: 44298 | D79: =262085*1.19 -> 311881.15 | E79: 9
A80: ANTAWARA 2700 lt | B80: F14 | C80: 44235 | D80: =2216970-400000 -> 1816970 | E80: 10
A81: ANTAWARA | B81: F5 | C81: 44195 | D81: 240975 | E81: 11

Sheet AGO-21
B2: N° doc | C2: Fecha | D2: Monto Bruto | E2: Forma Pago | F2: 44409 | G2: 44410 | H2: 44411 | I2: 44412 | J2: 44413 | K2: 44414 | L2: 44415 | M2: 44416 | N2: 44417 | O2: 44418 | P2: 44419 | Q2: 44420 | R2: 44421 | S2: 44422 | T2: 44423 | U2: 44424 | V2: 44425 | W2: 44426 | X2: 44427 | Y2: 44428 | Z2: 44429 | AA2: 44430 | AB2: 44431 | AC2: 44432 | AD2: 44433 | AE2: 44434 | AF2: 44435 | AG2: 44436 | AH2: 44437 | AI2: 44438 | AJ2: 44439 | AK2: TOTAL
A3: SALDO INICIAL | F3: =+'JUL-21'!AJ66 -> 907398.12 | G3: =+F56 -> 907398.12 | H3: =+G56 -> 907398.12 | I3: =+H56 -> 907398.12 | J3: =+I56 -> 848398.12 | K3: =+J56 -> 848398.12 | L3: =+K56 -> 848398.12 | M3: =+L56 -> 848398.12 | N3: =+M56 -> 848398.12 | ... AJ3: =+AI56 -> 59266.97
A4: INGRESOS
A5: Factura N° 10 Sofía Jottar | B5: F10 | C5: 43866 | D5: 33728 | AK5: =SUM($E5:AJ5) -> 0
A6: Factura N° 11 Sofía Jottar | B6: F11 | C6: 43876 | D6: 160200 | AK6: =SUM($E6:AJ6) -> 0
A7: Factura N° 12 Sofía Jottar | B7: F12 | C7: 43882 | D7: 160200 | AK7: =SUM($E7:AJ7) -> 0
A8: Factura N° 13 Sofía Jottar | B8: F13 | C8: 43889 | D8: 160200 | AK8: =SUM($E8:AJ8) -> 0
A9: Factura N° 14 Sofía Jottar | B9: F14 | C9: 43892 | D9: =28475.41*1.19 -> 33885.738 | AK9: =SUM($E9:AJ9) -> 0
A10: Factura N° 15 Sofía Jottar | B10: F15 | C10: 43904 | D10: 160200 | AK10: =SUM($E10:AJ10) -> 0
A11: Factura N° XX Sofía Jottar SPRITZ | B11: FXX | D11: 0 | E11: por facturar | AK11: =SUM($E11:AJ11) -> 0
A12: Factura N° 60 Jazz Corner | B12: F60 | C12: 44328 | D12: 138825 | Q12: 138825 | AK12: =SUM($E12:AJ12) -> 138825
A13: Factura N° 61 Jazz Corner | B13: F61 | C13: 44335 | D13: 76160 | Q13: =200000-Q12 -> 61175 | AE13: =+D13-Q13 -> 14985 | AK13: =SUM($E13:AJ13) -> 76160
A14: Factura N° 67 Jazz Corner | B14: F67 | C14: 44406 | D14: 31333 | AE14: 31333 | AK14: =SUM($E14:AJ14) -> 31333
A15: Factura N° 68 Sangria Alegria | B15: F68 | C15: 44407 | D15: 7616 | AB15: 7616 | AK15: =SUM($E15:AJ15) -> 7616
A16: Factura N° 69 Jazz Corner | B16: F69 | C16: 44411 | D16: 31333 | AE16: 31333 | AK16: =SUM($E16:AJ16) -> 31333
A17: Factura N° 70 Sangria Alegria | B17: F70 | C17: 44415 | D17: =(3200*4+5000)*1.19 -> 21182 | N17: =(3200*4+5000)*1.19 -> 21182 | AK17: =SUM($E17:AJ17) -> 21182
A18: Factura N° 71 Jazz Corner | B18: F71 | C18: 44420 | D18: 31333 | AK18: =SUM($E18:AJ18) -> 0
A19: Nota de Credito N°3 Jazz Corner | B19: NC03 | C19: 44432 | D19: -31333 | AK19: =SUM($E19:AJ19) -> 0
A20: Factura N° 72 Sangria Alegria | B20: F72 | C20: 44434 | D20: =(3200*4+5000)*1.19 -> 21182 | AE20: =(3200*4+5000)*1.19 -> 21182 | AK20: =SUM($E20:AJ20) -> 21182
A21: Factura N° 73 Los Laureles | B21: F73 | C21: 44434 | D21: =(1700*9+5000)*1.19 -> 24157 | AJ21: =(1700*9+5000)*1.19 -> 24157 | AK21: =SUM($E21:AJ21) -> 24157
AK22: =SUM(AK5:AK21) -> 351788
A23: SII DEVOLUCION PPM 2019 | C23: 43980 | D23: 10465
A24: Aporte LV | D24: 0
A25: Aporte ML
A26: SENCE subsidio
A29: TOTAL INGRESOS | F29: =SUM(F5:F28) -> 0 | G29: =SUM(G5:G28) -> 0 | H29: =SUM(H5:H28) -> 0 | I29: =SUM(I5:I28) -> 0 | J29: =SUM(J5:J28) -> 0 | K29: =SUM(K5:K28) -> 0 | L29: =SUM(L5:L28) -> 0 | M29: =SUM(M5:M28) -> 0 | ... AJ29: =SUM(AJ5:AJ28) -> 24157
A31: EGRESOS
A32: Boleta N° 131 EMS Remun Jun-Jul-Ago 2020 | B32: B131 | D32: 750000 | V32: 750000 | AK32: =SUM($F32:AJ32) -> 750000
A33: Boleta N° xxx EMS Remun Sept 2020 | B33: Bxxx | D33: 250000 | AK33: =SUM($F33:AJ33) -> 0
A34: Boleta N° xxx EMS Remun Oct 2020 | B34: Bxxx | D34: 500000 | AK34: =SUM($F34:AJ34) -> 0
A35: Boleta N° xxx EMS Remun Nov 2020 | B35: Bxxx | D35: 500000 | AK35: =SUM($F35:AJ35) -> 0
A36: Boleta N° xxx EMS Remun Dic2020 | B36: Bxxx | D36: 500000 | AK36: =SUM($F36:AJ36) -> 0
A37: Boleta N° xxx EMS Remun Ene2021 | B37: Bxxx | D37: 500000 | AK37: =SUM($F37:AJ37) -> 0
A38: Boleta N° xxx EMS Remun Feb2021 | B38: Bxxx | D38: 500000 | AK38: =SUM($F38:AJ38) -> 0
A39: Boleta N° xxx EMS Remun Marzo 2021 | B39: Bxxx | D39: 250000 | AK39: =SUM($F39:AJ39) -> 0
A40: Boleta N°xxx Remun Var. Gte. Mar 2021 | B40: Bxxx | D40: =+'MAR-21'!AK19*0.17 -> 93733.693 | AK40: =SUM($F40:AJ40) -> 0
A41: ANTAWARA | B41: F5 | C41: 44195 | D41: 240975 | AK41: =SUM($F41:AJ41) -> 0
A42: ANTAWARA 2700 lt | B42: F14 | C42: 44235 | D42: =2216970-'MAR-21'!$H$45 -> 1816970 | AK42: =SUM($F42:AJ42) -> 0
A43: LANCER arriendo equipo N°3 4a cuota | B43: F11071495 | C43: 44298 | D43: =262085*1.19 -> 311881.15 | AI43: =262085*1.19 -> 311881.15 | AK43: =SUM($F43:AJ43) -> 311881.15
A44: F29 Julio | C44: 44419 | D44: 793 | P44: 793 | AK44: =SUM($F44:AJ44) -> 793
A45: Flete Vitacura Lancer Clean Ice Vitacura | C45: 44404 | D45: =+(13.3+3.5+12.5)*950/9+1304+935 -> 5331.7778 | AF45: 5332 | AK45: =SUM($F45:AJ45) -> 5332
A46: Oficina Virtual (semestre) (saldo) | B46: F311 | D46: 59000 | I46: 59000 | AK46: =SUM($F46:AJ46) -> 59000
A47: Flete despacho cobrado Vitacura Los Laureles Vitacura | C47: 44415 | D47: 5000 | AF47: 5000 | AK47: =SUM($F47:AJ47) -> 5000
A48: Francisco Escobar Comision Apertura Los Laureles | B48: B31 | D48: 15240 | U48: 15240 | AK48: =SUM($F48:AJ48) -> 15240
A49: Flete Vitacura Cerrillos Vitacura | D49: =+(28.5*2)*950/9+1989+2999+1010*2 -> 13024.667 | AF49: 13025 | AK49: =SUM($F49:AJ49) -> 13025
A50: Flete despacho cobrado Vitacura Los Laureles Vitacura | C50: 44433 | D50: 5000 | AF50: 5000 | AK50: =SUM($F50:AJ50) -> 5000
A51: Flete despacho CO2 cobrado Vitacura Los Laureles Vitacura | C51: 44434 | D51: 5000 | AF51: 5000 | AK51: =SUM($F51:AJ51) -> 5000
A52: SANGRIA ALEGRIA muestra botella | B52: F176 | C52: 44432 | D52: 5491 | AI52: 5491 | AK52: =SUM($F52:AJ52) -> 5491
A53: Flete Vitacura Jazz Corner Vitacura | C53: 44439 | D53: =+(14.4*2)*925/9+1304+935 -> 5199 | AK53: =SUM($F53:AJ53) -> 0
A55: TOTAL EGRESOS | F55: =SUM(F32:F53) -> 0 | G55: =SUM(G32:G53) -> 0 | H55: =SUM(H32:H53) -> 0 | I55: =SUM(I32:I53) -> 59000 | J55: =SUM(J32:J53) -> 0 | K55: =SUM(K32:K53) -> 0 | L55: =SUM(L32:L53) -> 0 | M55: =SUM(M32:M53) -> 0 | ... AJ55: =SUM(AJ32:AJ53) -> 0
A56: SALDO FINAL | F56: =+F29+F3-F55 -> 907398.12 | G56: =+G3+G29-G55 -> 907398.12 | H56: =+H3+H29-H55 -> 907398.12 | I56: =+I3+I29-I55 -> 848398.12 | J56: =+J3+J29-J55 -> 848398.12 | K56: =+K3+K29-K55 -> 848398.12 | L56: =+L3+L29-L55 -> 848398.12 | M56: =+M3+M29-M55 -> 848398.12 | N56: =+N3+N29-N55 -> 869580.12 | ... AJ56: =+AJ3+AJ29-AJ55 -> 83423.97
E60: Prioridad
A63: LANCER arriendo equipo N°2 4a cuota | B63: F11071495 | C63: 44298 | D63: =262085*1.19 -> 311881.15 | E63: 1
A64: ANTAWARA 2700 lt | B64: F14 | C64: 44235 | D64: =2216970-400000 -> 1816970 | E64: 2
A65: ANTAWARA | B65: F5 | C65: 44195 | D65: 240975 | E65: 3

Sheet SEP-21
B2: N° doc | C2: Fecha | D2: Monto Bruto | E2: Forma Pago | F2: 44440 | G2: 44441 | H2: 44442 | I2: 44443 | J2: 44444 | K2: 44445 | L2: 44446 | M2: 44447 | N2: 44448 | O2: 44449 | P2: 44450 | Q2: 44451 | R2: 44452 | S2: 44453 | T2: 44454 | U2: 44455 | V2: 44456 | W2: 44457 | X2: 44458 | Y2: 44459 | Z2: 44460 | AA2: 44461 | AB2: 44462 | AC2: 44463 | AD2: 44464 | AE2: 44465 | AF2: 44466 | AG2: 44467 | AH2: 44468 | AI2: 44469 | AK2: TOTAL
A3: SALDO INICIAL | F3: =+'AGO-21'!AJ56 -> 83423.97 | G3: =+F42 -> 83423.97 | H3: =+G42 -> 83423.97 | I3: =+H42 -> 83423.97 | J3: =+I42 -> 83423.97 | K3: =+J42 -> 83423.97 | L3: =+K42 -> 83423.97 | M3: =+L42 -> 25423.97 | N3: =+M42 -> 25423.97 | ... AI3: =+AH42 -> 64792.304
A4: INGRESOS
A5: Factura N° 10 Sofía Jottar | B5: F10 | C5: 43866 | D5: 33728 | AK5: =SUM($F5:AI5) -> 0
A6: Factura N° 11 Sofía Jottar | B6: F11 | C6: 43876 | D6: 160200 | AK6: =SUM($F6:AI6) -> 0
A7: Factura N° 12 Sofía Jottar | B7: F12 | C7: 43882 | D7: 160200 | AK7: =SUM($F7:AI7) -> 0
A8: Factura N° 13 Sofía Jottar | B8: F13 | C8: 43889 | D8: 160200 | AK8: =SUM($F8:AI8) -> 0
A9: Factura N° 14 Sofía Jottar | B9: F14 | C9: 43892 | D9: =28475.41*1.19 -> 33885.738 | AK9: =SUM($F9:AI9) -> 0
A10: Factura N° 15 Sofía Jottar | B10: F15 | C10: 43904 | D10: 160200 | AK10: =SUM($F10:AI10) -> 0
A11: Factura N° XX Sofía Jottar SPRITZ | B11: FXX | D11: 0 | E11: por facturar | AK11: =SUM($F11:AI11) -> 0
A12: "Abonos Varios" Bco Estado BONO ESTATAL IVA | D12: 49026 | O12: 49026 | AK12: =SUM($F12:AI12) -> 49026
A13: Factura N° 74 Sangria Alegria | B13: F74 | C13: 44450 | D13: 13566 | R13: 13566 | AK13: =SUM($F13:AI13) -> 13566
AK14: =SUM(AK5:AK15)-AK12 -> 13566
A15: SII DEVOLUCION PPM 2019 | C15: 43980 | D15: 10465
A16: Aporte LV | D16: 0
A17: Aporte ML
A18: SENCE subsidio
A21: TOTAL INGRESOS | F21: =SUM(F5:F20) -> 0 | G21: =SUM(G5:G20) -> 0 | H21: =SUM(H5:H20) -> 0 | I21: =SUM(I5:I20) -> 0 | J21: =SUM(J5:J20) -> 0 | K21: =SUM(K5:K20) -> 0 | L21: =SUM(L5:L20) -> 0 | M21: =SUM(M5:M20) -> 0 | ... AI21: =SUM(AI5:AI20) -> 0
A23: EGRESOS
A24: Boleta N° xxx EMS Remun Sept 2020 | B24: Bxxx | D24: 250000 | AK24: =SUM($F24:AI24) -> 0
A25: Boleta N° xxx EMS Remun Oct 2020 | B25: Bxxx | D25: 500000 | AK25: =SUM($F25:AI25) -> 0
A26: Boleta N° xxx EMS Remun Nov 2020 | B26: Bxxx | D26: 500000 | AK26: =SUM($F26:AI26) -> 0
A27: Boleta N° xxx EMS Remun Dic2020 | B27: Bxxx | D27: 500000 | AK27: =SUM($F27:AI27) -> 0
A28: Boleta N° xxx EMS Remun Ene2021 | B28: Bxxx | D28: 500000 | AK28: =SUM($F28:AI28) -> 0
A29: Boleta N° xxx EMS Remun Feb2021 | B29: Bxxx | D29: 500000 | AK29: =SUM($F29:AI29) -> 0
A30: Boleta N° xxx EMS Remun Marzo 2021 | B30: Bxxx | D30: 250000 | AK30: =SUM($F30:AI30) -> 0
A31: Boleta N°xxx Remun Var. Gte. a Sept 2021 | B31: Bxxx | D31: =+'MAR-21'!AK19*0.17+('ABR-21'!AJ18+'MAY-21'!AK16+'JUN-21'!AK14+'JUL-21'!AK28+'AGO-21'!AK22+'SEP-21'!AK14)*0.17 -> 277507.09 | AK31: =SUM($F31:AI31) -> 0
A32: Remuneración Fija Gte Sept 2021 | D32: 600000
A33: ANTAWARA | B33: F5 | C33: 44195 | D33: 240975 | AK33: =SUM($F33:AI33) -> 0
A34: ANTAWARA 2700 lt | B34: F14 | C34: 44235 | D34: =2216970-'MAR-21'!$H$45 -> 1816970 | AK34: =SUM($F34:AI34) -> 0
A35: Flete Vitacura Jazz Corner Vitacura | C35: 44439 | D35: =+(14.4*2)*925/9+1304+935 -> 5199 | R35: =+(14.4*2)*925/9+1304+935 -> 5199 | AK35: =SUM($F35:AI35) -> 5199
A36: Flete Vitacura Cerrillos Vitacura | C36: 44446 | D36: =+(28.5*2)*950/9+1989+2999+1010*2 -> 13024.667 | R36: =+(28.5*2)*950/9+1989+2999+1010*2 -> 13024.667 | AK36: =SUM($F36:AI36) -> 13024.667
A37: Oficina Virtual Pro (trimestre inicio 16 Junio) | B37: F | D37: 58000 | L37: 58000 | AK37: =SUM($F37:AI37) -> 58000
A38: Flete despacho cobrado Vitacura Los Laureles Vitacura | C38: 44450 | D38: 5000 | R38: 5000 | AK38: =SUM($F38:AI38) -> 5000
A41: TOTAL EGRESOS | F41: =SUM(F24:F40) -> 0 | G41: =SUM(G24:G40) -> 0 | H41: =SUM(H24:H40) -> 0 | I41: =SUM(I24:I40) -> 0 | J41: =SUM(J24:J40) -> 0 | K41: =SUM(K24:K40) -> 0 | L41: =SUM(L24:L40) -> 58000 | M41: =SUM(M24:M40) -> 0 | ... AI41: =SUM(AI24:AI40) -> 0
A42: SALDO FINAL | F42: =+F21+F3-F41 -> 83423.97 | G42: =+G3+G21-G41 -> 83423.97 | H42: =+H3+H21-H41 -> 83423.97 | I42: =+I3+I21-I41 -> 83423.97 | J42: =+J3+J21-J41 -> 83423.97 | K42: =+K3+K21-K41 -> 83423.97 | L42: =+L3+L21-L41 -> 25423.97 | M42: =+M3+M21-M41 -> 25423.97 | N42: =+N3+N21-N41 -> 25423.97 | ... AI42: =+AI3+AI21-AI41 -> 64792.304

Sheet OCT-21
B2: N° doc | C2: Fecha | D2: Monto Bruto | E2: Forma Pago | F2: 44470 | G2: 44471 | H2: 44472 | I2: 44473 | J2: 44474 | K2: 44475 | L2: 44476 | M2: 44477 | N2: 44478 | O2: 44479 | P2: 44480 | Q2: 44481 | R2: 44482 | S2: 44483 | T2: 44484 | U2: 44485 | V2: 44486 | W2: 44487 | X2: 44488 | Y2: 44489 | Z2: 44490 | AA2: 44491 | AB2: 44492 | AC2: 44493 | AD2: 44494 | AE2: 44495 | AF2: 44496 | AG2: 44497 | AH2: 44498 | AI2: 44499 | AJ2: 44500 | AK2: TOTAL
A3: SALDO INICIAL | F3: =+'SEP-21'!AI42 -> 64792.304 | G3: =+F44 -> 64792.304 | H3: =+G44 -> 64792.304 | I3: =+H44 -> 64792.304 | J3: =+I44 -> 64792.304 | K3: =+J44 -> 64792.304 | L3: =+K44 -> 7285.3037 | M3: =+L44 -> 7285.3037 | N3: =+M44 -> 7285.3037 | ... AJ3: =+AI44 -> 77112.77
A4: INGRESOS
A5: Factura N° 10 Sofía Jottar | B5: F10 | C5: 43866 | D5: 33728 | AK5: =SUM($F5:AI5) -> 0
A6: Factura N° 11 Sofía Jottar | B6: F11 | C6: 43876 | D6: 160200 | AK6: =SUM($F6:AI6) -> 0
A7: Factura N° 12 Sofía Jottar | B7: F12 | C7: 43882 | D7: 160200 | AK7: =SUM($F7:AI7) -> 0
A8: Factura N° 13 Sofía Jottar | B8: F13 | C8: 43889 | D8: 160200 | AK8: =SUM($F8:AI8) -> 0
A9: Factura N° 14 Sofía Jottar | B9: F14 | C9: 43892 | D9: =28475.41*1.19 -> 33885.738 | AK9: =SUM($F9:AI9) -> 0
A10: Factura N° 15 Sofía Jottar | B10: F15 | C10: 43904 | D10: 160200 | AK10: =SUM($F10:AI10) -> 0
A11: Factura N° XX Sofía Jottar SPRITZ | B11: FXX | D11: 0 | E11: por facturar | AK11: =SUM($F11:AI11) -> 0
A12: Factura N° 75 Sangria Alegria arriendo equipo | B12: F75 | C12: 44481 | D12: 166600 | R12: 166600 | AK12: =SUM($F12:AI12) -> 166600
A13: Factura N° 76 Sangria Alegria | B13: F76 | C13: 44489 | D13: 21182 | AF13: 21182 | AK13: =SUM($F13:AI13) -> 21182
A14: SII DEVOLUCION PPM 2019 | C14: 43980 | D14: 10465 | AK14: =SUM($F14:AI14) -> 0
A15: Aporte LV | D15: 0
A16: Aporte ML
A17: SENCE subsidio
A19: TOTAL INGRESOS | F19: =SUM(F5:F18) -> 0 | G19: =SUM(G5:G18) -> 0 | H19: =SUM(H5:H18) -> 0 | I19: =SUM(I5:I18) -> 0 | J19: =SUM(J5:J18) -> 0 | K19: =SUM(K5:K18) -> 0 | L19: =SUM(L5:L18) -> 0 | M19: =SUM(M5:M18) -> 0 | ... AJ19: =SUM(AJ5:AJ18) -> 0 | AK19: =SUM(AK5:AK14) -> 187782
A21: EGRESOS
A22: Boleta N° xxx EMS Remun Sept 2020 | B22: Bxxx | D22: 250000 | AK22: =SUM($F22:AI22) -> 0
A23: Boleta N° xxx EMS Remun Oct 2020 | B23: Bxxx | D23: 500000 | AK23: =SUM($F23:AI23) -> 0
A24: Boleta N° xxx EMS Remun Nov 2020 | B24: Bxxx | D24: 500000 | AK24: =SUM($F24:AI24) -> 0
A25: Boleta N° xxx EMS Remun Dic2020 | B25: Bxxx | D25: 500000 | AK25: =SUM($F25:AI25) -> 0
A26: Boleta N° xxx EMS Remun Ene2021 | B26: Bxxx | D26: 500000 | AK26: =SUM($F26:AI26) -> 0
A27: Boleta N° xxx EMS Remun Feb2021 | B27: Bxxx | D27: 500000 | AK27: =SUM($F27:AI27) -> 0
A28: Boleta N° xxx EMS Remun Marzo 2021 | B28: Bxxx | D28: 250000 | AK28: =SUM($F28:AI28) -> 0
A29: Boleta N°xxx Remun Var. Gte. a Sept 2021 | B29: Bxxx | D29: =+'MAR-21'!AK19*0.17+('ABR-21'!AJ18+'MAY-21'!AK16+'JUN-21'!AK14+'JUL-21'!AK28+'AGO-21'!AK22+'SEP-21'!AK14)*0.17 -> 277507.09 | AK29: =SUM($F29:AI29) -> 0
A30: Remuneración Gte. Sept-Oct 2021 | D30: 1200000
A31: ANTAWARA | B31: F5 | C31: 44195 | D31: 240975 | AK31: =SUM($F31:AI31) -> 0
A32: ANTAWARA 2700 lt | B32: F14 | C32: 44235 | D32: =2216970-'MAR-21'!$H$45 -> 1816970 | AK32: =SUM($F32:AI32) -> 0
A33: Sabores Esencia Sangria 1 Kg+Ac. Tartarico | B33: F107311 | C33: 44475 | D33: 41888 | E33: Transfer | K33: 41888 | AK33: =SUM($F33:AI33) -> 41888
A34: SABORES enturbiante 1 Kg | B34: F107338 | C34: 44475 | D34: 15619 | E34: Transfer | K34: 15619 | AK34: =SUM($F34:AI34) -> 15619
A35: UNIMARC 5X2 lt Gato Tinto | B35: F33873476 | C35: 44476 | D35: 16050 | E35: TC EMS | S35: 16050 | AK35: =SUM($F35:AI35) -> 16050
A36: F29 Sept | C36: 44481 | D36: 14 | Q36: 14 | AK36: =SUM($F36:AI36) -> 14
A37: Flete Vitacura Chicureo Vitacura | C37: 44477 | D37: =+(25.1*2)*984/9+2432*2 -> 10352.533 | S37: =+(25.1*2)*984/9+2432*2 -> 10352.533 | AK37: =SUM($F37:AI37) -> 10352.533
A38: Oficina Virtual Pro (trimestre inicio 16 Junio) | B38: F366 | C38: 44530 | D38: 58000 | E38: Transfer | S38: 58000 | AK38: =SUM($F38:AI38) -> 58000
A39: Flete Vitacura Los Laureles Recoleta Vitacura | C39: 44489 | D39: =+((8.8+11+16.2)*950/9)+601+601+331 -> 5333 | AF39: =+(8.8+11+16.2)*950/9+601+601+331 -> 5333 | AK39: =SUM($F39:AI39) -> 5333
A40: Flete Los Laureles cobrado a cliente | C40: 44489 | D40: 5000 | AF40: 5000 | AK40: =SUM($F40:AI40) -> 5000
A41: Clean Ice 9kg+2Kg CO2 | B41: F35914 | D41: 23205 | E41: Transfer | Y41: 23205 | AK41: =SUM($F41:AI41) -> 23205
AK42: =SUM(AK22:AK41) -> 175461.53 | AL42: =+AK19-AK42+F3 -> 77112.77
A43: TOTAL EGRESOS | F43: =SUM(F22:F42) -> 0 | G43: =SUM(G22:G42) -> 0 | H43: =SUM(H22:H42) -> 0 | I43: =SUM(I22:I42) -> 0 | J43: =SUM(J22:J42) -> 0 | K43: =SUM(K22:K42) -> 57507 | L43: =SUM(L22:L42) -> 0 | M43: =SUM(M22:M42) -> 0 | ... AJ43: =SUM(AJ22:AJ42) -> 0
A44: SALDO FINAL | F44: =+F19+F3-F43 -> 64792.304 | G44: =+G3+G19-G43 -> 64792.304 | H44: =+H3+H19-H43 -> 64792.304 | I44: =+I3+I19-I43 -> 64792.304 | J44: =+J3+J19-J43 -> 64792.304 | K44: =+K3+K19-K43 -> 7285.3037 | L44: =+L3+L19-L43 -> 7285.3037 | M44: =+M3+M19-M43 -> 7285.3037 | N44: =+N3+N19-N43 -> 7285.3037 | ... AJ44: =+AJ3+AJ19-AJ43 -> 77112.77

Sheet NOV-21
B2: N° doc | C2: Fecha | D2: Monto Bruto | E2: Forma Pago | F2: 44501 | G2: 44502 | H2: 44503 | I2: 44504 | J2: 44505 | K2: 44506 | L2: 44507 | M2: 44508 | N2: 44509 | O2: 44510 | P2: 44511 | Q2: 44512 | R2: 44513 | S2: 44514 | T2: 44515 | U2: 44516 | V2: 44517 | W2: 44518 | X2: 44519 | Y2: 44520 | Z2: 44521 | AA2: 44522 | AB2: 44523 | AC2: 44524 | AD2: 44525 | AE2: 44526 | AF2: 44527 | AG2: 44528 | AH2: 44529 | AI2: 44530 | AK2: TOTAL
A3: SALDO INICIAL | F3: =+'OCT-21'!AJ44 -> 77112.77 | G3: =+F40 -> 77112.77 | H3: =+G40 -> 77112.77 | I3: =+H40 -> 77112.77 | J3: =+I40 -> 77112.77 | K3: =+J40 -> -0.22966387 | L3: =+K40 -> -0.22966387 | M3: =+L40 -> -0.22966387 | N3: =+M40 -> -0.22966387 | ... AI3: =+AH40 -> 802.77034
A4: INGRESOS
A5: Factura N° 10 Sofía Jottar | B5: F10 | C5: 43866 | D5: 33728 | AK5: =SUM($F5:AI5) -> 0
A6: Factura N° 11 Sofía Jottar | B6: F11 | C6: 43876 | D6: 160200 | AK6: =SUM($F6:AI6) -> 0
A7: Factura N° 12 Sofía Jottar | B7: F12 | C7: 43882 | D7: 160200 | AK7: =SUM($F7:AI7) -> 0
A8: Factura N° 13 Sofía Jottar | B8: F13 | C8: 43889 | D8: 160200 | AK8: =SUM($F8:AI8) -> 0
A9: Factura N° 14 Sofía Jottar | B9: F14 | C9: 43892 | D9: =28475.41*1.19 -> 33885.738 | AK9: =SUM($F9:AI9) -> 0
A10: Factura N° 15 Sofía Jottar | B10: F15 | C10: 43904 | D10: 160200 | AK10: =SUM($F10:AI10) -> 0
A11: Factura N° XX Sofía Jottar SPRITZ | B11: FXX | D11: 0 | E11: por facturar | AK11: =SUM($F11:AI11) -> 0
A12: Préstamo socio para pago Previred | D12: 79236 | J12: 79236 | AK12: =SUM($F12:AI12) -> 79236
A13: Préstamo socio para pago PPM Oct | D13: 1000 | O13: 1000 | AK13: =SUM($F13:AI13) -> 1000
A14: SII DEVOLUCION PPM 2019 | C14: 43980 | D14: 10465 | AK14: =SUM($F14:AI14) -> 0
A15: Aporte LV | D15: 0 | AK15: =SUM(AK5:AK14) -> 80236
A16: Aporte ML
A17: SENCE subsidio
A19: TOTAL INGRESOS | F19: =SUM(F5:F18) -> 0 | G19: =SUM(G5:G18) -> 0 | H19: =SUM(H5:H18) -> 0 | I19: =SUM(I5:I18) -> 0 | J19: =SUM(J5:J18) -> 79236 | K19: =SUM(K5:K18) -> 0 | L19: =SUM(L5:L18) -> 0 | M19: =SUM(M5:M18) -> 0 | ... AI19: =SUM(AI5:AI18) -> 0
A21: EGRESOS
A22: Boleta N° xxx EMS Remun Sept 2020 | B22: Bxxx | D22: 250000 | AK22: =SUM($F22:AI22) -> 0
A23: Boleta N° xxx EMS Remun Oct 2020 | B23: Bxxx | D23: 500000 | AK23: =SUM($F23:AI23) -> 0
A24: Boleta N° xxx EMS Remun Nov 2020 | B24: Bxxx | D24: 500000 | AK24: =SUM($F24:AI24) -> 0
A25: Boleta N° xxx EMS Remun Dic2020 | B25: Bxxx | D25: 500000 | AK25: =SUM($F25:AI25) -> 0
A26: Boleta N° xxx EMS Remun Ene2021 | B26: Bxxx | D26: 500000 | AK26: =SUM($F26:AI26) -> 0
A27: Boleta N° xxx EMS Remun Feb2021 | B27: Bxxx | D27: 500000 | AK27: =SUM($F27:AI27) -> 0
A28: Boleta N° xxx EMS Remun Marzo 2021 | B28: Bxxx | D28: 250000 | AK28: =SUM($F28:AI28) -> 0
A29: Boleta N°xxx Remun Var. Gte. a Sept 2021 | B29: Bxxx | D29: =+'MAR-21'!AK19*0.17+('ABR-21'!AJ18+'MAY-21'!AK16+'JUN-21'!AK14+'JUL-21'!AK28+'AGO-21'!AK22+'SEP-21'!AK14)*0.17 -> 277507.09 | AK29: =SUM($F29:AI29) -> 0
A30: Remuneración Gte. Sept-Oct-Nov 2021 | D30: 1800000
A31: Previred Sept | D31: 156349 | J31: 156349
A32: ANTAWARA | B32: F5 | C32: 44195 | D32: 240975 | AK32: =SUM($F32:AI32) -> 0
A33: ANTAWARA 2700 lt | B33: F14 | C33: 44235 | D33: =2216970-'MAR-21'!$H$45 -> 1816970 | AK33: =SUM($F33:AI33) -> 0
A34: F29 Oct | C34: 44510 | D34: 197 | O34: 197
A35: GODADDY | C35: 44522 | D35: =4.69*835 -> 3916.15 | E35: TC EMS
A36: Zapatilla electrica | C36: 44524 | D36: 9990 | E36: TC EMS | AK36: =SUM(AK22:AK33) -> 0 | AL36: =+AK15-AK36+F3 -> 157348.77
A37: Préstamo socio EMS | C37: 44870 | D37: 79236 | E37: transfer
A38: Préstamo socio EMS | C38: 44875 | D38: 1000 | E38: transfer
A39: TOTAL EGRESOS | F39: =SUM(F22:F36) -> 0 | G39: =SUM(G22:G36) -> 0 | H39: =SUM(H22:H36) -> 0 | I39: =SUM(I22:I36) -> 0 | J39: =SUM(J22:J36) -> 156349 | K39: =SUM(K22:K36) -> 0 | L39: =SUM(L22:L36) -> 0 | M39: =SUM(M22:M36) -> 0 | ... AI39: =SUM(AI22:AI36) -> 0
A40: SALDO FINAL | F40: =+F19+F3-F39 -> 77112.77 | G40: =+G3+G19-G39 -> 77112.77 | H40: =+H3+H19-H39 -> 77112.77 | I40: =+I3+I19-I39 -> 77112.77 | J40: =+J3+J19-J39 -> -0.22966387 | K40: =+K3+K19-K39 -> -0.22966387 | L40: =+L3+L19-L39 -> -0.22966387 | M40: =+M3+M19-M39 -> -0.22966387 | N40: =+N3+N19-N39 -> -0.22966387 | ... AI40: =+AI3+AI19-AI39 -> 802.77034

Sheet DIC-21
B2: N° doc | C2: Fecha | D2: Monto Bruto | E2: Forma Pago | F2: 44531 | G2: 44532 | H2: 44533 | I2: 44534 | J2: 44535 | K2: 44536 | L2: 44537 | M2: 44538 | N2: 44539 | O2: 44540 | P2: 44541 | Q2: 44542 | R2: 44543 | S2: 44544 | T2: 44545 | U2: 44546 | V2: 44547 | W2: 44548 | X2: 44549 | Y2: 44550 | Z2: 44551 | AA2: 44552 | AB2: 44553 | AC2: 44554 | AD2: 44555 | AE2: 44556 | AF2: 44557 | AG2: 44558 | AH2: 44559 | AI2: 44560 | AJ2: 44561 | AK2: TOTAL
A3: SALDO INICIAL | F3: =+'NOV-21'!AI40 -> 802.77034 | G3: =+F38 -> 802.77034 | H3: =+G38 -> 802.77034 | I3: =+H38 -> 802.77034 | J3: =+I38 -> 802.77034 | K3: =+J38 -> 802.77034 | L3: =+K38 -> 802.77034 | M3: =+L38 -> 802.77034 | N3: =+M38 -> 802.77034 | ... AJ3: =+AI38 -> 802.77034
A4: INGRESOS
A5: Factura N° 10 Sofía Jottar | B5: F10 | C5: 43866 | D5: 33728 | AK5: =SUM($F5:AI5) -> 0
A6: Factura N° 11 Sofía Jottar | B6: F11 | C6: 43876 | D6: 160200 | AK6: =SUM($F6:AI6) -> 0
A7: Factura N° 12 Sofía Jottar | B7: F12 | C7: 43882 | D7: 160200 | AK7: =SUM($F7:AI7) -> 0
A8: Factura N° 13 Sofía Jottar | B8: F13 | C8: 43889 | D8: 160200 | AK8: =SUM($F8:AI8) -> 0
A9: Factura N° 14 Sofía Jottar | B9: F14 | C9: 43892 | D9: =28475.41*1.19 -> 33885.738 | AK9: =SUM($F9:AI9) -> 0
A10: Factura N° 15 Sofía Jottar | B10: F15 | C10: 43904 | D10: 160200 | AK10: =SUM($F10:AI10) -> 0
A11: Factura N° XX Sofía Jottar SPRITZ | B11: FXX | D11: 0 | E11: por facturar | AK11: =SUM($F11:AI11) -> 0
A12: SII DEVOLUCION PPM 2019 | C12: 43980 | D12: 10465 | AK12: =SUM($F12:AI12) -> 0
A13: Aporte LV | D13: 0 | AK13: =SUM(AK5:AK12) -> 0
A14: Aporte ML
A15: SENCE subsidio
A17: TOTAL INGRESOS | F17: =SUM(F5:F16) -> 0 | G17: =SUM(G5:G16) -> 0 | H17: =SUM(H5:H16) -> 0 | I17: =SUM(I5:I16) -> 0 | J17: =SUM(J5:J16) -> 0 | K17: =SUM(K5:K16) -> 0 | L17: =SUM(L5:L16) -> 0 | M17: =SUM(M5:M16) -> 0 | ... AJ17: =SUM(AJ5:AJ16) -> 0
A19: EGRESOS
A20: Boleta N° xxx EMS Remun Sept 2020 | B20: Bxxx | D20: 250000 | AK20: =SUM($F20:AI20) -> 0
A21: Boleta N° xxx EMS Remun Oct 2020 | B21: Bxxx | D21: 500000 | AK21: =SUM($F21:AI21) -> 0
A22: Boleta N° xxx EMS Remun Nov 2020 | B22: Bxxx | D22: 500000 | AK22: =SUM($F22:AI22) -> 0
A23: Boleta N° xxx EMS Remun Dic2020 | B23: Bxxx | D23: 500000 | AK23: =SUM($F23:AI23) -> 0
A24: Boleta N° xxx EMS Remun Ene2021 | B24: Bxxx | D24: 500000 | AK24: =SUM($F24:AI24) -> 0
A25: Boleta N° xxx EMS Remun Feb2021 | B25: Bxxx | D25: 500000 | AK25: =SUM($F25:AI25) -> 0
A26: Boleta N° xxx EMS Remun Marzo 2021 | B26: Bxxx | D26: 250000 | AK26: =SUM($F26:AI26) -> 0
A27: Boleta N°xxx Remun Var. Gte. a Dic 2021 | B27: Bxxx | D27: =+'MAR-21'!AK19*0.17+('ABR-21'!AJ18+'MAY-21'!AK16+'JUN-21'!AK14+'JUL-21'!AK28+'AGO-21'!AK22+'SEP-21'!AK14+'OCT-21'!AK19)*0.17 -> 309430.03 | AK27: =SUM($F27:AI27) -> 0
A28: Remuneración Gte. Sept a Dic 2021 | D28: 2400000
A29: ANTAWARA 2700 lt | B29: F14 | C29: 44235 | D29: =-'MAR-21'!$H$45+870366 -> 470366 | E29: cheque EMS | AK29: =SUM($F29:AI29) -> 0
A30: GODADDY | C30: 44536 | D30: =49.02*835 -> 40931.7 | E30: TC EMS
A31: GODADDY | C31: 44522 | D31: =4.69*835 -> 3916.15 | E31: TC EMS | AK31: =SUM(AK20:AK29) -> 0 | AL31: =+AK13-AK31+F3 -> 802.77034
A32: Zapatilla electrica | B32: F11 | C32: 44524 | D32: 9990 | E32: TC EMS
A33: Préstamo socio EMS | C33: 44870 | D33: 79236 | E33: transfer
A34: Préstamo socio EMS | C34: 44875 | D34: 1000 | E34: transfer
A35: Préstamo socio EMS | C35: 44918 | D35: =-'MAR-21'!$H$45+870366 -> 470366 | E35: cheque EMS
A37: TOTAL EGRESOS | F37: =SUM(F20:F31) -> 0 | G37: =SUM(G20:G31) -> 0 | H37: =SUM(H20:H31) -> 0 | I37: =SUM(I20:I31) -> 0 | J37: =SUM(J20:J31) -> 0 | K37: =SUM(K20:K31) -> 0 | L37: =SUM(L20:L31) -> 0 | M37: =SUM(M20:M31) -> 0 | ... AJ37: =SUM(AJ20:AJ31) -> 0
A38: SALDO FINAL | F38: =+F17+F3-F37 -> 802.77034 | G38: =+G3+G17-G37 -> 802.77034 | H38: =+H3+H17-H37 -> 802.77034 | I38: =+I3+I17-I37 -> 802.77034 | J38: =+J3+J17-J37 -> 802.77034 | K38: =+K3+K17-K37 -> 802.77034 | L38: =+L3+L17-L37 -> 802.77034 | M38: =+M3+M17-M37 -> 802.77034 | N38: =+N3+N17-N37 -> 802.77034 | ... AJ38: =+AJ3+AJ17-AJ37 -> 802.77034

Sheet ENE-22
B2: N° doc | C2: Fecha | D2: Monto Bruto | E2: Forma Pago | F2: 44562 | G2: 44563 | H2: 44564 | I2: 44565 | J2: 44566 | K2: 44567 | L2: 44568 | M2: 44569 | N2: 44570 | O2: 44571 | P2: 44572 | Q2: 44573 | R2: 44574 | S2: 44575 | T2: 44576 | U2: 44577 | V2: 44578 | W2: 44579 | X2: 44580 | Y2: 44581 | Z2: 44582 | AA2: 44583 | AB2: 44584 | AC2: 44585 | AD2: 44586 | AE2: 44587 | AF2: 44588 | AG2: 44589 | AH2: 44590 | AI2: 44591 | AJ2: 44592 | AK2: TOTAL
A3: SALDO INICIAL | F3: =+'DIC-21'!AJ38 -> 802.77034 | G3: =+F40 -> 802.77034 | H3: =+G40 -> 802.77034 | I3: =+H40 -> 802.77034 | J3: =+I40 -> 802.77034 | K3: =+J40 -> 802.77034 | L3: =+K40 -> 802.77034 | M3: =+L40 -> 802.77034 | N3: =+M40 -> 802.77034 | ... AJ3: =+AI40 -> 802.77034
A4: INGRESOS
A5: Factura N° 10 Sofía Jottar | B5: F10 | C5: 43866 | D5: 33728 | AK5: =SUM($F5:AI5) -> 0
A6: Factura N° 11 Sofía Jottar | B6: F11 | C6: 43876 | D6: 160200 | AK6: =SUM($F6:AI6) -> 0
A7: Factura N° 12 Sofía Jottar | B7: F12 | C7: 43882 | D7: 160200 | AK7: =SUM($F7:AI7) -> 0
A8: Factura N° 13 Sofía Jottar | B8: F13 | C8: 43889 | D8: 160200 | AK8: =SUM($F8:AI8) -> 0
A9: Factura N° 14 Sofía Jottar | B9: F14 | C9: 43892 | D9: =28475.41*1.19 -> 33885.738 | AK9: =SUM($F9:AI9) -> 0
A10: Factura N° 15 Sofía Jottar | B10: F15 | C10: 43904 | D10: 160200 | AK10: =SUM($F10:AI10) -> 0
A11: Factura N° XX Sofía Jottar SPRITZ | B11: FXX | D11: 0 | E11: por facturar | AK11: =SUM($F11:AI11) -> 0
A12: SII DEVOLUCION PPM 2019 | C12: 43980 | D12: 10465 | AK12: =SUM($F12:AI12) -> 0
A13: Abono EMS para pago credito FOGAPE | C13: 44579 | D13: =+D37 -> 1000 | W13: 14074 | AK13: =SUM($F13:AI13) -> 14074
A14: Aporte LV | D14: 0 | AK14: =SUM(AK5:AK12) -> 0
A15: Aporte ML
A17: TOTAL INGRESOS | F17: =SUM(F5:F16) -> 0 | G17: =SUM(G5:G16) -> 0 | H17: =SUM(H5:H16) -> 0 | I17: =SUM(I5:I16) -> 0 | J17: =SUM(J5:J16) -> 0 | K17: =SUM(K5:K16) -> 0 | L17: =SUM(L5:L16) -> 0 | M17: =SUM(M5:M16) -> 0 | ... AJ17: =SUM(AJ5:AJ16) -> 0
A19: EGRESOS
A20: Boleta N° xxx EMS Remun Sept 2020 | B20: Bxxx | D20: 250000 | AK20: =SUM($F20:AI20) -> 0
A21: Boleta N° xxx EMS Remun Oct 2020 | B21: Bxxx | D21: 500000 | AK21: =SUM($F21:AI21) -> 0
A22: Boleta N° xxx EMS Remun Nov 2020 | B22: Bxxx | D22: 500000 | AK22: =SUM($F22:AI22) -> 0
A23: Boleta N° xxx EMS Remun Dic2020 | B23: Bxxx | D23: 500000 | AK23: =SUM($F23:AI23) -> 0
A24: Boleta N° xxx EMS Remun Ene2021 | B24: Bxxx | D24: 500000 | AK24: =SUM($F24:AI24) -> 0
A25: Boleta N° xxx EMS Remun Feb2021 | B25: Bxxx | D25: 500000 | AK25: =SUM($F25:AI25) -> 0
A26: Boleta N° xxx EMS Remun Marzo 2021 | B26: Bxxx | D26: 250000 | AK26: =SUM($F26:AI26) -> 0
A27: Boleta N°xxx Remun Var. Gte.Ene a Dic 2021 | B27: Bxxx | D27: =+'MAR-21'!AK19*0.17+('ABR-21'!AJ18+'MAY-21'!AK16+'JUN-21'!AK14+'JUL-21'!AK28+'AGO-21'!AK22+'SEP-21'!AK14+'OCT-21'!AK19)*0.17 -> 309430.03 | AK27: =SUM($F27:AI27) -> 0
A28: Remuneración Fija Gte. Sept a Dic 2021 | D28: 2400000 | AK28: =SUM($F28:AI28) -> 0
A29: Remuneración Fija Gte. Ene 2022 | D29: 600000 | AK29: =SUM($F29:AI29) -> 0
A30: ANTAWARA 2700 lt | B30: F14 | C30: 44235 | D30: =-'MAR-21'!$H$45+870366 -> 470366 | E30: cheque EMS | AK30: =SUM($F30:AI30) -> 0
A31: GODADDY | C31: 44522 | D31: =4.69*835 -> 3916.15 | E31: TC EMS | AK31: =SUM($F31:AI31) -> 0
A32: Zapatilla electrica | B32: F11 | C32: 44524 | D32: 9990 | E32: TC EMS | AK32: =SUM($F32:AI32) -> 0
A33: GODADDY | C33: 44536 | D33: =49.02*835 -> 40931.7 | E33: TC EMS | AK33: =SUM($F33:AI33) -> 0
A34: Cuota N°1 Credito FOGAPE repactado | C34: 44579 | D34: 14074 | E34: transfer EMS | W34: 14074 | AK34: =SUM($F34:AI34) -> 14074 | AL34: GF
A35: LIDER 2x2 lt vino bl 1 lt vino tinto | B35: F54148164 | C35: 44579 | D35: 9720 | E35: TC EMS | AK35: =SUM($F35:AI35) -> 0
A36: Préstamo socio EMS | C36: 44870 | D36: 79236 | E36: transfer | AK36: =SUM($F36:AI36) -> 0
A37: Préstamo socio EMS | C37: 44875 | D37: 1000 | E37: transfer | AK37: =SUM($F37:AI37) -> 0
AK38: =SUM($F38:AI38) -> 0
A39: TOTAL EGRESOS | F39: =SUM(F20:F38) -> 0 | G39: =SUM(G20:G38) -> 0 | H39: =SUM(H20:H38) -> 0 | I39: =SUM(I20:I38) -> 0 | J39: =SUM(J20:J38) -> 0 | K39: =SUM(K20:K38) -> 0 | L39: =SUM(L20:L38) -> 0 | M39: =SUM(M20:M38) -> 0 | ... AK39: =SUM(AK20:AK38) -> 14074
A40: SALDO FINAL | F40: =+F17+F3-F39 -> 802.77034 | G40: =+G3+G17-G39 -> 802.77034 | H40: =+H3+H17-H39 -> 802.77034 | I40: =+I3+I17-I39 -> 802.77034 | J40: =+J3+J17-J39 -> 802.77034 | K40: =+K3+K17-K39 -> 802.77034 | L40: =+L3+L17-L39 -> 802.77034 | M40: =+M3+M17-M39 -> 802.77034 | N40: =+N3+N17-N39 -> 802.77034 | ... AJ40: =+AJ3+AJ17-AJ39 -> 802.77034

Sheet FEB-22
B2: N° doc | C2: Fecha | D2: Monto Bruto | E2: Forma Pago | F2: 44593 | G2: 44594 | H2: 44595 | I2: 44596 | J2: 44597 | K2: 44598 | L2: 44599 | M2: 44600 | N2: 44601 | O2: 44602 | P2: 44603 | Q2: 44604 | R2: 44605 | S2: 44606 | T2: 44607 | U2: 44608 | V2: 44609 | W2: 44610 | X2: 44611 | Y2: 44612 | Z2: 44613 | AA2: 44614 | AB2: 44615 | AC2: 44616 | AD2: 44617 | AE2: 44618 | AF2: 44619 | AG2: 44620 | AK2: TOTAL
A3: SALDO INICIAL | F3: =+'ENE-22'!AJ40 -> 802.77034 | G3: =+F61 -> 802.77034 | H3: =+G61 -> 802.77034 | I3: =+H61 -> 802.77034 | J3: =+I61 -> 802.77034 | K3: =+J61 -> 802.77034 | L3: =+K61 -> 802.77034 | M3: =+L61 -> 802.77034 | N3: =+M61 -> 802.77034 | ... AG3: =+AF61 -> 2394319.9
A4: INGRESOS
A5: Factura N° 10 Sofía Jottar | B5: F10 | C5: 43866 | D5: 33728 | AK5: =SUM($F5:AI5) -> 0
A6: Factura N° 11 Sofía Jottar | B6: F11 | C6: 43876 | D6: 160200 | AK6: =SUM($F6:AI6) -> 0
A7: Factura N° 12 Sofía Jottar | B7: F12 | C7: 43882 | D7: 160200 | AK7: =SUM($F7:AI7) -> 0
A8: Factura N° 13 Sofía Jottar | B8: F13 | C8: 43889 | D8: 160200 | AK8: =SUM($F8:AI8) -> 0
A9: Factura N° 14 Sofía Jottar | B9: F14 | C9: 43892 | D9: =28475.41*1.19 -> 33885.738 | AK9: =SUM($F9:AI9) -> 0
A10: Factura N° 15 Sofía Jottar | B10: F15 | C10: 43904 | D10: 160200 | AK10: =SUM($F10:AI10) -> 0
A11: Factura N° XX Sofía Jottar SPRITZ | B11: FXX | D11: 0 | E11: por facturar | AK11: =SUM($F11:AI11) -> 0
A12: Factura N° 86 Fukai Mañio | B12: F86 | C12: 44616 | D12: 85642 | AK12: =SUM($F12:AI12) -> 0
A13: NC N° 04 Fukai Mañio | B13: NC 04 | C13: 44616 | D13: -85642 | AK13: =SUM($F13:AI13) -> 0
A14: Factura N° 87 Fukai Mañio | B14: F87 | C14: 44616 | D14: 85642 | E14: F | AK14: =SUM($F14:AI14) -> 0
A15: Factura N° 88 Rosita Mañio | B15: F88 | C15: 44616 | D15: 85642 | E15: F | AK15: =SUM($F15:AI15) -> 0
A16: Factura N° 89 Rosita Ñuñoa | B16: F89 | C16: 44617 | D16: 85642 | E16: F | AK16: =SUM($F16:AI16) -> 0
A17: Factura N° 90 Los Laureles | B17: F90 | C17: 44618 | D17: 56708 | E17: F | AK17: =SUM($F17:AI17) -> 0
A18: Factura N° 92 Rosita Bellavista | B18: F92 | C18: 44618 | D18: 85642 | E18: F | AK18: =SUM($F18:AI18) -> 0
A19: SII DEVOLUCION PPM 2019 | C19: 43980 | D19: 10465 | AK19: =SUM($F19:AI19) -> 0
A20: Abono EMS para pago credito FOGAPE | C20: 44606 | D20: =13193+1000 -> 14193 | S20: 13193 | T20: 1000 | AK20: =SUM($F20:AI20) -> 14193
A21: MUTUO CORMORAN | C21: 44616 | D21: 3000000 | AC21: 3000000 | AK21: =SUM($F21:AI21) -> 3000000
AK23: =SUM(AK5:AK22) -> 3014193
A25: TOTAL INGRESOS | F25: =SUM(F5:F24) -> 0 | G25: =SUM(G5:G24) -> 0 | H25: =SUM(H5:H24) -> 0 | I25: =SUM(I5:I24) -> 0 | J25: =SUM(J5:J24) -> 0 | K25: =SUM(K5:K24) -> 0 | L25: =SUM(L5:L24) -> 0 | M25: =SUM(M5:M24) -> 0 | ... AG25: =SUM(AG5:AG24) -> 0
A27: EGRESOS
A28: Boleta N° xxx EMS Remun Sept 2020 | B28: Bxxx | D28: 250000 | AK28: =SUM($F28:AI28) -> 0
A29: Boleta N° xxx EMS Remun Oct 2020 | B29: Bxxx | D29: 500000 | AK29: =SUM($F29:AI29) -> 0
A30: Boleta N° xxx EMS Remun Nov 2020 | B30: Bxxx | D30: 500000 | AK30: =SUM($F30:AI30) -> 0
A31: Boleta N° xxx EMS Remun Dic2020 | B31: Bxxx | D31: 500000 | AK31: =SUM($F31:AI31) -> 0
A32: Boleta N° xxx EMS Remun Ene2021 | B32: Bxxx | D32: 500000 | AK32: =SUM($F32:AI32) -> 0
A33: Boleta N° xxx EMS Remun Feb2021 | B33: Bxxx | D33: 500000 | AK33: =SUM($F33:AI33) -> 0
A34: Boleta N° xxx EMS Remun Marzo 2021 | B34: Bxxx | D34: 250000 | AK34: =SUM($F34:AI34) -> 0
A35: Boleta N°xxx Remun Var. Gte.Ene a Dic 2021 | B35: Bxxx | D35: =+'MAR-21'!AK19*0.17+('ABR-21'!AJ18+'MAY-21'!AK16+'JUN-21'!AK14+'JUL-21'!AK28+'AGO-21'!AK22+'SEP-21'!AK14+'OCT-21'!AK19)*0.17 -> 309430.03 | AK35: =SUM($F35:AI35) -> 0
A36: Remuneración Fija Gte. Sept a Dic 2021 | D36: 2400000
A37: Remuneración Fija Gte. Ene- Feb 2022 | D37: 1200000
A38: ANTAWARA 2700 lt | B38: F14 | C38: 44235 | D38: =-'MAR-21'!$H$45+870366 -> 470366 | E38: cheque EMS | AK38: =SUM($F38:AI38) -> 0
A39: Préstamo socio EMS | C39: 44505 | D39: 79236 | E39: transfer | AD39: 79236 | AK39: =SUM($F39:AI39) -> 79236 | AL39: GF
A40: Préstamo socio EMS | C40: 44510 | D40: 1000 | E40: transfer | AD40: 1000 | AK40: =SUM($F40:AI40) -> 1000 | AL40: GF
A41: GODADDY | C41: 44522 | D41: =4.69*835 -> 3916.15 | E41: TC EMS | AD41: =4.69*835 -> 3916.15 | AK41: =SUM($F41:AI41) -> 3916.15 | AL41: GAV
A42: Zapatilla electrica | B42: F11 | C42: 44524 | D42: 9990 | E42: TC EMS | AD42: 9990 | AK42: =SUM($F42:AI42) -> 9990 | AL42: AF
A43: GODADDY | C43: 44536 | D43: =49.02*835 -> 40931.7 | E43: TC EMS | AD43: =49.02*835 -> 40931.7 | AK43: =SUM($F43:AI43) -> 40931.7 | AL43: GAV
A44: LIDER 2x2 lt vino bl 1 lt vino tinto | B44: F54148164 | C44: 44579 | D44: 9720 | E44: TC EMS | AD44: 9720 | AK44: =SUM($F44:AI44) -> 9720 | AL44: CD
A45: Cuota N°1 Credito FOGAPE repactado | C45: 44579 | D45: 14074 | E45: transfer EMS | AD45: 14074 | AK45: =SUM($F45:AI45) -> 14074 | AL45: GF
A46: Cuota N°2 Credito FOGAPE repactado | C46: 44607 | D46: 14009 | E46: transfer EMS | T46: 14009 | AD46: 14009 | AK46: =SUM($F46:AI46) -> 28018 | AL46: GF
A47: UNIMARC AZUCAR VINO | B47: F34409459 | C47: 44609 | D47: 3900 | E47: TC EMS | AD47: 3900 | AK47: =SUM($F47:AI47) -> 3900 | AL47: CD
A48: Notaria+impuesto Mutuo | C48: 44609 | D48: 26000 | E48: transfer EMS | AK48: =SUM($F48:AI48) -> 0 | AL48: GAV
A49: LAS PIRCAS | C49: 44614 | D49: 36000 | E49: transfer EMS | AD49: 36000 | AK49: =SUM($F49:AI49) -> 36000 | AL49: CD
A50: Flete Santiago-I de Maipo-Santiago | C50: 44614 | D50: =75*2*1050/9+6000 -> 23500 | AD50: =75*2*1050/9+6000 -> 23500 | AK50: =SUM($F50:AI50) -> 23500 | AL50: GAV
A51: UNIMARC AZUCAR AGUA | B51: F34513008 | C51: 44615 | D51: 23790 | E51: TC EMS | AD51: 23790 | AK51: =SUM($F51:AI51) -> 23790 | AL51: CD
A52: LANCER 3 bombas +acc+bolsas | B52: F1074625 | C52: 44615 | D52: 446484 | AK52: =SUM($F52:AI52) -> 0
A53: CASA TRINIDAD 4 torres 1s 4bandejas | B53: F34988 | C53: 44616 | D53: 333200 | E53: TC EMS | AD53: 333200 | AK53: =SUM($F53:AI53) -> 333200 | AL53: AF
A54: FERRETERIA CAVEM abrazaderas | B54: F82342 | C54: 44616 | D54: 13400 | E54: TC EMS | AD54: 13400 | AK54: =SUM($F54:AI54) -> 13400 | AL54: AF
A55: Flete Vitacura-Ñuñoa -Vitacura | C55: 44618 | D55: =13.9*1050/9+2000 -> 3621.6667 | AK55: =SUM($F55:AI55) -> 0
A56: UNIMARC AGUA 6x6.5 lt | B56: F34552020 | C56: 44618 | D56: 10430 | E56: TC EMS | AK56: =SUM($F56:AI56) -> 0
A57: Flete Vitacura- Bellavista -Vitacura | C57: 44618 | D57: =12.9*1050/9+2000 -> 3505 | E57: TC EMS | AK57: =SUM($F57:AI57) -> 0
A58: Estacionamiento | C58: 44618 | D58: 2600 | E58: TC EMS | AK58: =SUM($F58:AI58) -> 0
A60: TOTAL EGRESOS | F60: =SUM(F28:F52) -> 0 | G60: =SUM(G28:G52) -> 0 | H60: =SUM(H28:H52) -> 0 | I60: =SUM(I28:I52) -> 0 | J60: =SUM(J28:J52) -> 0 | K60: =SUM(K28:K52) -> 0 | L60: =SUM(L28:L52) -> 0 | M60: =SUM(M28:M52) -> 0 | ... S60: =SUM(S28:S52) -> 0 | T60: =SUM(T28:T58) -> 14009 | U60: =SUM(U28:U58) -> 0 | V60: =SUM(V28:V58) -> 0 | W60: =SUM(W28:W58) -> 0 | X60: =SUM(X28:X58) -> 0 | Y60: =SUM(Y28:Y58) -> 0 | Z60: =SUM(Z28:Z58) -> 0 | AA60: =SUM(AA28:AA58) -> 0 | ... AK60: =SUM(AK28:AK58) -> 620675.85
A61: SALDO FINAL | F61: =+F25+F3-F60 -> 802.77034 | G61: =+G3+G25-G60 -> 802.77034 | H61: =+H3+H25-H60 -> 802.77034 | I61: =+I3+I25-I60 -> 802.77034 | J61: =+J3+J25-J60 -> 802.77034 | K61: =+K3+K25-K60 -> 802.77034 | L61: =+L3+L25-L60 -> 802.77034 | M61: =+M3+M25-M60 -> 802.77034 | N61: =+N3+N25-N60 -> 802.77034 | ... AJ61: =+AJ3+AJ25-AJ60 -> #VALUE!

Sheet MAR-22
B2: N° doc | C2: Fecha | D2: Monto Bruto | E2: Forma Pago | F2: 44621 | G2: 44622 | H2: 44623 | I2: 44624 | J2: 44625 | K2: 44626 | L2: 44627 | M2: 44628 | N2: 44629 | O2: 44630 | P2: 44631 | Q2: 44632 | R2: 44633 | S2: 44634 | T2: 44635 | U2: 44636 | V2: 44637 | W2: 44638 | X2: 44639 | Y2: 44640 | Z2: 44641 | AA2: 44642 | AB2: 44643 | AC2: 44644 | AD2: 44645 | AE2: 44646 | AF2: 44647 | AG2: 44648 | AH2: 44649 | AI2: 44650 | AJ2: 44651 | AK2: TOTAL
A3: SALDO INICIAL | F3: =+'FEB-22'!AG61 -> 2394319.9 | G3: =+F87 -> 1874902.9 | H3: =+G87 -> 1652954.9 | I3: =+H87 -> 1652954.9 | J3: =+I87 -> 1206470.9 | K3: =+J87 -> 1206470.9 | L3: =+K87 -> 1206470.9 | M3: =+L87 -> 942565.92 | N3: =+M87 -> 942565.92 | ... AJ3: =+AI87 -> 128360.59
A4: INGRESOS
A5: Factura N° 10 Sofía Jottar | B5: F10 | C5: 43866 | D5: 33728 | AJ5: 33728 | AK5: =SUM($F5:AJ5) -> 33728
A6: Factura N° 11 Sofía Jottar | B6: F11 | C6: 43876 | D6: 160200 | AJ6: 160200 | AK6: =SUM($F6:AJ6) -> 160200
A7: Factura N° 12 Sofía Jottar | B7: F12 | C7: 43882 | D7: 160200 | AK7: =SUM($F7:AJ7) -> 0
A8: Factura N° 13 Sofía Jottar | B8: F13 | C8: 43889 | D8: 160200 | AK8: =SUM($F8:AJ8) -> 0
A9: Factura N° 14 Sofía Jottar | B9: F14 | C9: 43892 | D9: =28475.41*1.19 -> 33885.738 | AJ9: 33886 | AK9: =SUM($F9:AJ9) -> 33886
A10: Factura N° 15 Sofía Jottar | B10: F15 | C10: 43904 | D10: 160200 | AK10: =SUM($F10:AJ10) -> 0
A11: Factura N° 86 Fukai Mañio | B11: F86 | C11: 44616 | D11: 85642 | AK11: =SUM($F11:AJ11) -> 0
A12: NC N° 04 Fukai Mañio | B12: NC 04 | C12: 44616 | D12: -85642 | AK12: =SUM($F12:AJ12) -> 0
A13: Factura N° 87 Fukai Mañio | B13: F87 | C13: 44616 | D13: 85642 | T13: 85642 | AK13: =SUM($F13:AJ13) -> 85642
A14: Factura N° 88 Rosita Mañio | B14: F88 | C14: 44616 | D14: 85642 | T14: 85642 | AK14: =SUM($F14:AJ14) -> 85642
A15: Factura N° 89 Rosita Ñuñoa | B15: F89 | C15: 44617 | D15: 85642 | T15: 85642 | AK15: =SUM($F15:AJ15) -> 85642
A16: Factura N° 90 Los Laureles | B16: F90 | C16: 44618 | D16: 56708 | AK16: =SUM($F16:AJ16) -> 0
A17: Factura N° 92 Rosita Bellavista | B17: F92 | C17: 44618 | D17: 85642 | T17: 85642 | AK17: =SUM($F17:AJ17) -> 85642
A18: Factura N° 93 Fulai Bellavista | B18: F93 | C18: 44621 | D18: 85642 | E18: F | T18: 85642 | AK18: =SUM($F18:AJ18) -> 85642
A19: Factura N° 94 Fulai Mañio | B19: F94 | C19: 44639 | D19: 85642 | E19: F | AG19: 85642 | AK19: =SUM($F19:AJ19) -> 85642
A20: Factura N° 95 Rosita Mañio | B20: F95 | C20: 44639 | D20: 85642 | E20: F | AG20: 85642 | AK20: =SUM($F20:AJ20) -> 85642
A21: Factura N° 98 Fukai Mañio | B21: F98 | C21: 44648 | D21: 85642 | E21: F | AK21: =SUM($F21:AJ21) -> 0
A22: Factura N° 99 Rosita Mañio | B22: F99 | C22: 44648 | D22: 85642 | E22: F | AK22: =SUM($F22:AJ22) -> 0
A23: Factura N° 100 Rosita Ñuñoa | B23: F100 | C23: 44650 | D23: 85642 | E23: F | AK23: =SUM($F23:AJ23) -> 0
A24: Factura N° XX Sofía Jottar SPRITZ | B24: FXX | D24: 0 | E24: por facturar | AK24: =SUM($F24:AJ24) -> 0
A25: SII DEVOLUCION PPM 2019 | C25: 43980 | D25: 10465 | AK25: =SUM($F25:AJ25) -> 0
AK26: =SUM($F26:AJ26) -> 0
AK27: =SUM($F27:AJ27) -> 0
AK28: =SUM(AK5:AK27) -> 827308
A29: TOTAL INGRESOS | F29: =SUM(F5:F28) -> 0 | G29: =SUM(G5:G28) -> 0 | H29: =SUM(H5:H28) -> 0 | I29: =SUM(I5:I28) -> 0 | J29: =SUM(J5:J28) -> 0 | K29: =SUM(K5:K28) -> 0 | L29: =SUM(L5:L28) -> 0 | M29: =SUM(M5:M28) -> 0 | ... AJ29: =SUM(AJ5:AJ28) -> 227814
A31: EGRESOS
A32: Boleta N°133 EMS Remun Sept 2020 | B32: B132 | D32: 250000 | L32: 250000 | AK32: =SUM($F32:AJ32) -> 250000 | AL32: GAV
A33: Boleta N° xxx EMS Remun Oct 2020 | B33: Bxxx | D33: 500000 | AK33: =SUM($F33:AJ33) -> 0
A34: Boleta N° xxx EMS Remun Nov 2020 | B34: Bxxx | D34: 500000 | AK34: =SUM($F34:AJ34) -> 0
A35: Boleta N° xxx EMS Remun Dic2020 | B35: Bxxx | D35: 500000 | AK35: =SUM($F35:AJ35) -> 0
A36: Boleta N° xxx EMS Remun Ene2021 | B36: Bxxx | D36: 500000 | AK36: =SUM($F36:AJ36) -> 0
A37: Boleta N° xxx EMS Remun Feb2021 | B37: Bxxx | D37: 500000 | AK37: =SUM($F37:AJ37) -> 0
A38: Boleta N° xxx EMS Remun Marzo 2021 | B38: Bxxx | D38: 250000 | AK38: =SUM($F38:AJ38) -> 0
A39: Boleta N°xxx Remun Var. Gte.Ene a Dic 2021 | B39: Bxxx | D39: =+'MAR-21'!AK19*0.17+('ABR-21'!AJ18+'MAY-21'!AK14+'JUN-21'!AK14+'JUL-21'!AK28+'AGO-21'!AK22+'SEP-21'!AK14+'OCT-21'!AK19)*0.17 -> 309430.03 | AK39: =SUM($F39:AJ39) -> 0
A40: Boleta N°xxx Remun Var. Gte.Ene a Mar 2022 | B40: Bxxx | D40: =AK28*0.17 -> 140642.36 | AK40: =SUM($F40:AJ40) -> 0
A41: Remuneración Fija Gte. Sept a Dic 2021 | D41: =600000*4 -> 2400000 | AK41: =SUM($F41:AJ41) -> 0
A42: Remuneración Fija Gte. Ene- Feb-Mar 2022 | D42: =600000*3 -> 1800000 | AK42: =SUM($F42:AJ42) -> 0
A43: ANTAWARA 2700 lt | B43: F14 | C43: 44235 | D43: =-'MAR-21'!$H$45+870366 -> 470366 | V43: =-'MAR-21'!$H$45+870366 -> 470366 | AK43: =SUM($F43:AJ43) -> 470366 | AL43: CD
A44: Notaria+impuesto Mutuo | C44: 44609 | D44: 26000 | E44: transfer EMS | Z44: 26000 | AK44: =SUM($F44:AJ44) -> 26000 | AL44: GAV
A45: LANCER 3 bombas +acc+bolsas | B45: F1074625 | C45: 44615 | D45: 446484 | I45: 446484 | AK45: =SUM($F45:AJ45) -> 446484 | AL45: AF
A46: UNIMARC AGUA 6x6.5 lt | B46: F34552020 | C46: 44618 | D46: 10430 | E46: TC EMS | Z46: 10430 | AK46: =SUM($F46:AJ46) -> 10430 | AL46: CD
A47: Flete Vitacura- Bellavista -Vitacura | C47: 44618 | D47: =12.9*1050/9+2000 -> 3505 | Z47: =12.9*1050/9+2000 -> 3505 | AK47: =SUM($F47:AJ47) -> 3505 | AL47: GAV
A48: Estacionamiento | C48: 44618 | D48: 2600 | E48: TC EMS | Z48: 2600 | AK48: =SUM($F48:AJ48) -> 2600 | AL48: GAV
A49: ISAPRE EMS | C49: 44621 | D49: 68151 | E49: previred | F49: 68151 | AK49: =SUM($F49:AJ49) -> 68151 | AL49: GAV
A50: AFP | C50: 44621 | D50: 109301 | E50: previred | F50: 109301 | AK50: =SUM($F50:AJ50) -> 109301 | AL50: GAV
A51: AFP | C51: 44621 | D51: 106392 | E51: previred | F51: 106392 | AK51: =SUM($F51:AJ51) -> 106392 | AL51: GAV
A52: AFP | C52: 44621 | D52: 103286 | E52: previred | F52: 103286 | AK52: =SUM($F52:AJ52) -> 103286 | AL52: GAV
A53: ISAPRE EMS | C53: 44621 | D53: 65434 | E53: previred | F53: 65434 | AK53: =SUM($F53:AJ53) -> 65434 | AL53: GAV
A54: ISAPRE EMS | C54: 44621 | D54: 66853 | E54: previred | F54: 66853 | AK54: =SUM($F54:AJ54) -> 66853 | AL54: GAV
A55: OFICINA VIRTUAL PRO | C55: 44621 | D55: 58000 | G55: 58000 | AK55: =SUM($F55:AJ55) -> 58000 | AL55: GAV
A56: Flete Vitacura- Bellavista -Vitacura | C56: 44621 | D56: =12.9*1050/9+2000 -> 3505 | Z56: =12.9*1050/9+2000 -> 3505 | AK56: =SUM($F56:AJ56) -> 3505 | AL56: GAV
A57: Estacionamiento | C57: 44621 | D57: =1700+1900 -> 3600 | E57: TC EMS | Z57: =1700+1900 -> 3600 | AK57: =SUM($F57:AJ57) -> 3600 | AL57: GAV
A58: ISAPRE EMS | C58: 44622 | D58: 63910 | E58: previred | G58: 63910 | AK58: =SUM($F58:AJ58) -> 63910 | AL58: GAV
A59: AFP | C59: 44622 | D59: 100038 | E59: previred | G59: 100038 | AK59: =SUM($F59:AJ59) -> 100038 | AL59: GAV
A60: PAC CREDITO CUOTA 3 DE 36 | C60: 44627 | D60: 13905 | L60: 13905 | AK60: =SUM($F60:AJ60) -> 13905 | AL60: GF
A61: Bolsas para ingredientes | B61: b154937 | C61: 44628 | D61: 2083 | E61: TC EMS | Z61: 2083 | AK61: =SUM($F61:AJ61) -> 2083 | AL61: GAV
A62: NAHUEL probeta +pipetas | B62: F38859 | C62: 44629 | D62: 12800 | E62: TC EMS | Z62: 12800 | AK62: =SUM($F62:AJ62) -> 12800 | AL62: AF
A63: GECORP detergente | B63: F36934 | C63: 44630 | D63: 5298 | E63: M.LIBERONA | AK63: =SUM($F63:AJ63) -> 0
A64: F29 Feb | B64: F29 Feb | C64: 44630 | D64: 419 | O64: 419 | AK64: =SUM($F64:AJ64) -> 419 | AL64: GAV
A65: COTIZACIONES SALUD Feb | C65: 44634 | D65: 39214 | S65: 39214 | AK65: =SUM($F65:AJ65) -> 39214 | AL65: GAV
A66: AFP Feb | C66: 44634 | D66: 97740 | S66: 97740 | AK66: =SUM($F66:AJ66) -> 97740 | AL66: GAV
A67: Clean Ice 3 X 2 Kg CO2 | B67: F40626 | C67: 44638 | D67: 21420 | W67: 21420 | AK67: =SUM($F67:AJ67) -> 21420 | AL67: GAV
A68: LANCER John Guest 1/4 x 3/8 | B68: F1074745 | C68: 44638 | D68: 5236 | AK68: =SUM($F68:AJ68) -> 0 | AL68: GAV
A69: Flete Vitacura- Recoleta -Vitacura | C69: 44638 | D69: =13.3*2*1050/9+2000 -> 5103.3333 | Z69: =13.3*2*1050/9+2000 -> 5103.3333 | AK69: =SUM($F69:AJ69) -> 5103.3333 | AL69: GAV
A70: UNIMARC AGUA +10 X 2LT VINO TETRA+AZUCAR | B70: F34648565 | C70: 44639 | D70: 44832 | E70: TC EMS | Z70: 44832 | AK70: =SUM($F70:AJ70) -> 44832 | AL70: CD
A71: Flete Vitacura- El Mañío-Vitacura | C71: 44639 | D71: =6.9*2*1050/9+2000 -> 3610 | Z71: =6.9*2*1050/9+2000 -> 3610 | AK71: =SUM($F71:AJ71) -> 3610 | AL71: GAV
A72: Flete Vitacura- Bellavista -Vitacura | C72: 44642 | D72: =12.9*1050/9+1100+1068+1736 -> 5409 | AG72: =12.9*1050/9+1100+1068+1736 -> 5409 | AK72: =SUM($F72:AJ72) -> 5409 | AL72: GAV
A73: LIDER AGUA +10 X 2LT VINO TETRA+AZUCAR | B73: F54244476 | C73: 44642 | D73: 44730 | E73: TC EMS | AG73: 44730 | AK73: =SUM($F73:AJ73) -> 44730 | AL73: CD
A74: SABORES Enturbiante | B74: F114563 | C74: 44643 | D74: 50137 | E74: TC EMS | AG74: 50137 | AK74: =SUM($F74:AJ74) -> 50137 | AL74: CD
A75: LAS PIRCAS 240 lt genérico | B75: F2928 | C75: 44645 | D75: 114240 | AG75: 114240 | AK75: =SUM($F75:AJ75) -> 114240 | AL75: CD
A76: Flete Santiago-I de Maipo-Santiago | C76: 44645 | D76: =82*2*1080/9+6000 -> 25680 | AG76: =82*2*1080/9+6000 -> 25680 | AK76: =SUM($F76:AJ76) -> 25680 | AL76: GAV
A77: Pago Mutuo 1 de 8 CORMORAN UF 95,69 | B77: =95.69/8 -> 11.96125 | C77: 44645 | D77: =+B77*D85 -> 379283.46 | AG77: 379283 | AK77: =SUM($F77:AJ77) -> 379283 | AL77: GF
A78: Clean Ice 2 X 2 Kg CO2 | B78: F40891 | C78: 44648 | D78: 16993 | AH78: 16993 | AK78: =SUM($F78:AJ78) -> 16993 | AL78: GAV
A79: UNIMARC AGUA +AZUCAR | B79: F34686907 | C79: 44648 | D79: 8509 | E79: TC EMS | AK79: =SUM($F79:AJ79) -> 0 | AL79: CD
A80: OSCAR POO plataforma para torre | C80: 44649 | D80: 30000 | AH80: 30000 | AK80: =SUM($F80:AJ80) -> 30000 | AL80: AF
A81: Flete Vitacura- El Mañío-Vitacura | C81: 44649 | D81: =6.9*2*1050/9+2000 -> 3610 | AK81: =SUM($F81:AJ81) -> 0
A82: Flete Vitacura- Recoleta -Vitacura | C82: 44649 | D82: =13.3*2*1050/9+2000 -> 5103.3333 | AK82: =SUM($F82:AJ82) -> 0
A83: Flete Vitacura-Ñuñoa -Vitacura | C83: 44650 | D83: =13.9*1050/9+2000 -> 3621.6667 | AK83: =SUM($F83:AJ83) -> 0
A84: UNIMARC AGUA +AZUCAR | B84: F34725734 | C84: 44650 | D84: 4740 | E84: TC EMS | AK84: =SUM($F84:AJ84) -> 0
C85: UF | D85: 31709.35
A86: TOTAL EGRESOS | F86: =SUM(F32:F85) -> 519417 | G86: =SUM(G32:G85) -> 221948 | H86: =SUM(H32:H85) -> 0 | I86: =SUM(I32:I85) -> 446484 | J86: =SUM(J32:J85) -> 0 | K86: =SUM(K32:K85) -> 0 | L86: =SUM(L32:L85) -> 263905 | M86: =SUM(M32:M85) -> 0 | ... AJ86: =SUM(AJ32:AJ85) -> 0 | AK86: =SUM(AK32:AK77) -> 2818460.3
A87: SALDO FINAL | F87: =+F29+F3-F86 -> 1874902.9 | G87: =+G3+G29-G86 -> 1652954.9 | H87: =+H3+H29-H86 -> 1652954.9 | I87: =+I3+I29-I86 -> 1206470.9 | J87: =+J3+J29-J86 -> 1206470.9 | K87: =+K3+K29-K86 -> 1206470.9 | L87: =+L3+L29-L86 -> 942565.92 | M87: =+M3+M29-M86 -> 942565.92 | N87: =+N3+N29-N86 -> 942565.92 | ... AJ87: =+AJ3+AJ29-AJ86 -> 356174.59
G91: 44630 | H91: 942.147
G92: 44634 | H92: 902.933 | AD92: =123*800 -> 98400
G93: 44634 | H93: 805.193

Sheet ABR-22
B2: N° doc | C2: Fecha | D2: Monto Bruto | E2: Forma Pago | F2: 44652 | G2: 44653 | H2: 44654 | I2: 44655 | J2: 44656 | K2: 44657 | L2: 44658 | M2: 44659 | N2: 44660 | O2: 44661 | P2: 44662 | Q2: 44663 | R2: 44664 | S2: 44665 | T2: 44666 | U2: 44667 | V2: 44668 | W2: 44669 | X2: 44670 | Y2: 44671 | Z2: 44672 | AA2: 44673 | AB2: 44674 | AC2: 44675 | AD2: 44676 | AE2: 44677 | AF2: 44678 | AG2: 44679 | AH2: 44680 | AI2: 44681 | AK2: TOTAL
A3: SALDO INICIAL | F3: =+'MAR-22'!AJ87 -> 356174.59 | G3: =+F72 -> 210098.59 | H3: =+G72 -> 210098.59 | I3: =+H72 -> 210098.59 | J3: =+I72 -> 210098.59 | K3: =+J72 -> 190193.59 | L3: =+K72 -> 190193.59 | M3: =+L72 -> 190193.59 | N3: =+M72 -> 184958.59 | ... AJ3: =+AI72 -> 107113.52
A4: INGRESOS
A5: Factura N° 12 Sofía Jottar | B5: F12 | C5: 43882 | D5: 160200 | AK5: =SUM($F5:AJ5) -> 0
A6: Factura N° 13 Sofía Jottar | B6: F13 | C6: 43889 | D6: 160200 | AK6: =SUM($F6:AJ6) -> 0
A7: Factura N° 15 Sofía Jottar | B7: F15 | C7: 43904 | D7: 160200 | AK7: =SUM($F7:AJ7) -> 0
A8: Factura N° 90 Los Laureles | B8: F90 | C8: 44618 | D8: 56708 | AK8: =SUM($F8:AJ8) -> 0
A9: Factura N° 98 Fukai Mañio | B9: F98 | C9: 44648 | D9: 85642 | P9: 85642 | AK9: =SUM($F9:AJ9) -> 85642
A10: Factura N° 99 Rosita Mañio | B10: F99 | C10: 44648 | D10: 85642 | P10: 85642 | AK10: =SUM($F10:AJ10) -> 85642
A11: Factura N° 100 Rosita Ñuñoa | B11: F100 | C11: 44650 | D11: 85642 | P11: 85642 | AK11: =SUM($F11:AJ11) -> 85642
A12: Factura N° 101 Fukai Bellavista | B12: F101 | C12: 44658 | D12: 126975 | E12: F | X12: 126975 | AK12: =SUM($F12:AJ12) -> 126975
A13: Factura N° 102 Rosita Bellavista | B13: F102 | C13: 44658 | D13: 44308 | E13: F | X13: 44308 | AK13: =SUM($F13:AJ13) -> 44308
A14: Factura N° 103 Fukai Bellavista | B14: F103 | C14: 44665 | D14: 85642 | E14: F | AD14: 85642 | AK14: =SUM($F14:AJ14) -> 85642
A15: Factura N° 104 Fukai Mañio | B15: F104 | C15: 44668 | D15: 85642 | E15: F | AD15: 85642 | AK15: =SUM($F15:AJ15) -> 85642
A16: Factura N° 105 Rosita Mañio | B16: F105 | C16: 44668 | D16: 85642 | E16: F | AK16: =SUM($F16:AJ16) -> 0
A17: Factura N° 106 Rosita Ñuñoa | B17: F106 | C17: 44676 | D17: 85642 | E17: F | AK17: =SUM($F17:AJ17) -> 0
A18: Factura N° 107 Fukai El Mañío | B18: F107 | C18: 44680 | D18: 93496 | E18: F | AK18: =SUM($F18:AJ18) -> 0
A19: Factura N° 108 RositaEl Mañío | B19: F108 | C19: 44680 | D19: 93496 | E19: F | AK19: =SUM($F19:AJ19) -> 0
A20: Factura N° 109 Rosita Bellavista | B20: F109 | C20: 44680 | D20: 44308 | E20: F | AK20: =SUM($F20:AJ20) -> 0
A21: Factura N° 110 Fukai Bellavista | B21: F110 | C21: 44680 | D21: 52162 | E21: F | AK21: =SUM($F21:AJ21) -> 0
A22: Reembolso Pago Duplicado AFP | C22: 44680 | D22: 81917 | AH22: 81917 | AK22: =SUM($F22:AJ22) -> 81917
AK23: =SUM($F23:AJ23) -> 0
A24: Factura N° XX Sofía Jottar SPRITZ | B24: FXX | D24: 0 | E24: por facturar | AK24: =SUM($F24:AJ24) -> 0
AK25: =SUM($F25:AJ25) -> 0
AK26: =SUM(AK5:AK25) -> 681410
A27: TOTAL INGRESOS | F27: =SUM(F5:F26) -> 0 | G27: =SUM(G5:G26) -> 0 | H27: =SUM(H5:H26) -> 0 | I27: =SUM(I5:I26) -> 0 | J27: =SUM(J5:J26) -> 0 | K27: =SUM(K5:K26) -> 0 | L27: =SUM(L5:L26) -> 0 | M27: =SUM(M5:M26) -> 0 | ... AJ27: =SUM(AJ5:AJ26) -> 0
A29: EGRESOS
A30: Boleta N° xxx EMS Remun Oct 2020 | B30: Bxxx | D30: 500000 | AK30: =SUM($F30:AJ30) -> 0
A31: Boleta N° xxx EMS Remun Nov 2020 | B31: Bxxx | D31: 500000 | AK31: =SUM($F31:AJ31) -> 0
A32: Boleta N° xxx EMS Remun Dic2020 | B32: Bxxx | D32: 500000 | AK32: =SUM($F32:AJ32) -> 0
A33: Boleta N° xxx EMS Remun Ene2021 | B33: Bxxx | D33: 500000 | AK33: =SUM($F33:AJ33) -> 0
A34: Boleta N° xxx EMS Remun Feb2021 | B34: Bxxx | D34: 500000 | AK34: =SUM($F34:AJ34) -> 0
A35: Boleta N° xxx EMS Remun Marzo 2021 | B35: Bxxx | D35: 250000 | AK35: =SUM($F35:AJ35) -> 0
A36: Boleta N°xxx Remun Var. Gte.Ene a Dic 2021 | B36: Bxxx | D36: =+'MAR-21'!AK19*0.17+('ABR-21'!AJ18+'MAY-21'!AK16+'JUN-21'!AK14+'JUL-21'!AK28+'AGO-21'!AK22+'SEP-21'!AK14+'OCT-21'!AK19)*0.17 -> 309430.03 | AK36: =SUM($F36:AJ36) -> 0
A37: Boleta N°xxx Remun Var. Gte.a Abr 2022 | B37: Bxxx | D37: =+'MAR-22'!D40+(AK26-AK22)*0.17 -> 242556.17 | AK37: =SUM($F37:AJ37) -> 0
A38: Remuneración Fija Gte. Sept a Dic 2021 | D38: 2400000 | AK38: =SUM($F38:AJ38) -> 0
A39: Remuneración Fija Gte. Ene- Feb-Mar 2022 | D39: 2400000 | AK39: =SUM($F39:AJ39) -> 0
A40: LANCER John Guest 1/4 x 3/8 | B40: F1074745 | C40: 44638 | D40: 5235 | M40: 5235 | AK40: =SUM($F40:AJ40) -> 5235 | AL40: AF
A41: UNIMARC AGUA +AZUCAR | B41: F34686907 | C41: 44648 | D41: 8509 | E41: TC EMS | AH41: 8509 | AK41: =SUM($F41:AJ41) -> 8509 | AL41: CD
A42: Flete Vitacura- El Mañío-Vitacura | C42: 44649 | D42: =6.9*2*1050/9+2000 -> 3610 | AH42: 3610 | AK42: =SUM($F42:AJ42) -> 3610 | AL42: GAV
A43: Flete Vitacura- Recoleta -Vitacura | C43: 44649 | D43: =13.3*2*1050/9+2000 -> 5103.3333 | AH43: 5103.3333 | AK43: =SUM($F43:AJ43) -> 5103.3333 | AL43: GAV
A44: Flete Vitacura-Ñuñoa -Vitacura | C44: 44650 | D44: =13.9*1050/9+2000 -> 3621.6667 | AH44: 3621.6667 | AK44: =SUM($F44:AJ44) -> 3621.6667 | AL44: GAV
A45: UNIMARC AGUA +AZUCAR | B45: F34725734 | C45: 44650 | D45: 4740 | E45: TC EMS | AH45: 4740 | AK45: =SUM($F45:AJ45) -> 4740 | AL45: CD
A46: AFP | C46: 44652 | D46: 81917 | F46: 81917 | AK46: =SUM($F46:AJ46) -> 81917 | AL46: GAV
A47: SALUD | C47: 44652 | D47: 64159 | F47: 64159 | AK47: =SUM($F47:AJ47) -> 64159 | AL47: GAV
A48: PAC CREDITO CUOTA 4 DE 36 | C48: 44656 | D48: 13905 | J48: 13905 | AK48: =SUM($F48:AJ48) -> 13905 | AL48: GF
A49: Freddy Quintana retorno 6 bolsas | C49: 44656 | D49: 6000 | J49: 6000 | AK49: =SUM($F49:AJ49) -> 6000 | AL49: CD
A50: UNIMARC AGUA +AZUCAR | B50: F34604402 | C50: 44658 | D50: 11253 | E50: TC EMS | AH50: 11253 | AK50: =SUM($F50:AJ50) -> 11253 | AL50: CD
A51: Flete Vitacura- Bellavista -Vitacura | C51: 44658 | D51: =12.9*1050/9+1100+1068+1736 -> 5409 | AH51: 5409 | AK51: =SUM($F51:AJ51) -> 5409 | AL51: GAV
A52: LANCER 10 bolsas 10lt | B52: F1074910 | C52: 44662 | D52: =1400*10*1.19 -> 16660 | W52: =1400*10*1.19 -> 16660 | AK52: =SUM($F52:AJ52) -> 16660 | AL52: CD
A53: F29 Marzo | C53: 44662 | D53: 45525 | P53: 45525 | AK53: =SUM($F53:AJ53) -> 45525 | AL53: GAV
A54: AFP | C54: 44664 | D54: 97740 | R54: 97740 | AK54: =SUM($F54:AJ54) -> 97740 | AL54: GAV
A55: SALUD | C55: 44664 | D55: 39214 | R55: 39214 | AK55: =SUM($F55:AJ55) -> 39214 | AL55: GAV
A56: Flete Vitacura- Bellavista -Vitacura | C56: 44665 | D56: =12.9*1050/9+1100+1068+1736 -> 5409 | AH56: 5409 | AK56: =SUM($F56:AJ56) -> 5409 | AL56: GAV
A57: Flete Vitacura- El Mañío-Vitacura | C57: 44667 | D57: =6.9*2*1050/9+2000 -> 3610 | AH57: 3610 | AK57: =SUM($F57:AJ57) -> 3610 | AL57: GAV
A58: UNIMARC AGUA +AZUCAR | B58: F34744883 | C58: 44665 | D58: 9821 | E58: TC EMS | AH58: 9821 | AK58: =SUM($F58:AJ58) -> 9821 | AL58: CD
A59: UNIMARC AGUA +AZUCAR | B59: F34802162 | C59: 44667 | D59: 7680 | E59: TC EMS | AH59: 7680 | AK59: =SUM($F59:AJ59) -> 7680 | AL59: CD
A60: OFICINA VIRTUAL | B60: F480 | C60: 44669 | D60: 58000 | W60: 58000 | AK60: =SUM($F60:AJ60) -> 58000 | AL60: GAV
A61: CLEAN ICE 2X2 KG | B61: F41674 | C61: 44671 | D61: =4*3000*1.19 -> 14280 | Z61: 14280 | AK61: =SUM($F61:AJ61) -> 14280 | AL61: GAV
A62: Flete Vitacura-Ñuñoa -Vitacura | C62: 44676 | D62: =13.9*1050/9+2000 -> 3621.6667 | AH62: 3621.6667 | AK62: =SUM($F62:AJ62) -> 3621.6667 | AL62: GAV
A63: UNIMARC AGUA +AZUCAR | B63: F34822137 | C63: 44676 | D63: 2560 | E63: TC EMS | AH63: 2560 | AK63: =SUM($F63:AJ63) -> 2560 | AL63: GAV
A64: CLEAN ICE 1X2 KG | B64: F41803 | C64: 44676 | D64: =2*3000*1.19 -> 7140 | AE64: =2*3000*1.19 -> 7140 | AK64: =SUM($F64:AJ64) -> 7140 | AL64: GAV
A65: Pago Mutuo 2 de 8 CORMORAN UF 95,69 | B65: =95.69/8 -> 11.96125 | C65: 44679 | D65: =+B65*D70 -> 384388.4 | AH65: 384388.4 | AK65: =SUM($F65:AJ65) -> 384388.4 | AL65: GF
A66: Flete Vitacura- El Mañío-Vitacura | C66: 44679 | D66: =6.9*2*1050/9+2000 -> 3610 | AH66: 3610 | AK66: =SUM($F66:AJ66) -> 3610 | AL66: GAV
A67: Flete Vitacura- Bellavista -Vitacura | C67: 44680 | D67: =12.9*1050/9+1100+1068+1736 -> 5409 | AH67: 5410 | AK67: =SUM($F67:AJ67) -> 5410 | AL67: GAV
A68: UNIMARC AGUA +AZUCAR | B68: F34851076 | C68: 44679 | D68: 12340 | E68: TC EMS | AH68: 12340 | AK68: =SUM($F68:AJ68) -> 12340 | AL68: CD | AM68: 96307
C70: UF | D70: 32136.14
A71: TOTAL EGRESOS | F71: =SUM(F30:F70) -> 146076 | G71: =SUM(G30:G70) -> 0 | H71: =SUM(H30:H70) -> 0 | I71: =SUM(I30:I70) -> 0 | J71: =SUM(J30:J70) -> 19905 | K71: =SUM(K30:K70) -> 0 | L71: =SUM(L30:L70) -> 0 | M71: =SUM(M30:M70) -> 5235 | ... AJ71: =SUM(AJ30:AJ70) -> 0 | AK71: =SUM(AK30:AK64) -> 524722.67
A72: SALDO FINAL | F72: =+F27+F3-F71 -> 210098.59 | G72: =+G27+G3-G71 -> 210098.59 | H72: =+H27+H3-H71 -> 210098.59 | I72: =+I27+I3-I71 -> 210098.59 | J72: =+J27+J3-J71 -> 190193.59 | K72: =+K27+K3-K71 -> 190193.59 | L72: =+L27+L3-L71 -> 190193.59 | M72: =+M27+M3-M71 -> 184958.59 | ... AI72: =+AI27+AI3-AI71 -> 107113.52 | AJ72: =+AJ3+AJ27-AJ71 -> 107113.52

Sheet May-22
B2: N° doc | C2: Fecha | D2: Monto Bruto | E2: Forma Pago | F2: 44682 | G2: 44683 | H2: 44684 | I2: 44685 | J2: 44686 | K2: 44687 | L2: 44688 | M2: 44689 | N2: 44690 | O2: 44691 | P2: 44692 | Q2: 44693 | R2: 44694 | S2: 44695 | T2: 44696 | U2: 44697 | V2: 44698 | W2: 44699 | X2: 44700 | Y2: 44701 | Z2: 44702 | AA2: 44703 | AB2: 44704 | AC2: 44705 | AD2: 44706 | AE2: 44707 | AF2: 44708 | AG2: 44709 | AH2: 44710 | AI2: 44711 | AJ2: 44712 | AK2: TOTAL
A3: SALDO INICIAL | F3: =+'ABR-22'!AI72 -> 107113.52 | G3: =+F75 -> 107113.52 | H3: =+G75 -> 278397.52 | I3: =+H75 -> 278397.52 | J3: =+I75 -> 158397.52 | K3: =+J75 -> 24492.516 | L3: =+K75 -> 24492.516 | M3: =+L75 -> 24492.516 | N3: =+M75 -> 24492.516 | ... AJ3: =+AI75 -> 813995.95
A4: INGRESOS
A5: Factura N° 12 Sofía Jottar | B5: F12 | C5: 43882 | D5: 160200 | AK5: =SUM($F5:AJ5) -> 0
A6: Factura N° 13 Sofía Jottar | B6: F13 | C6: 43889 | D6: 160200 | AK6: =SUM($F6:AJ6) -> 0
A7: Factura N° 15 Sofía Jottar | B7: F15 | C7: 43904 | D7: 160200 | AK7: =SUM($F7:AJ7) -> 0
A8: Factura N° 90 Los Laureles | B8: F90 | C8: 44618 | D8: 56708 | AK8: =SUM($F8:AJ8) -> 0
A9: Factura N° 105 Rosita Mañio | B9: F105 | C9: 44668 | D9: 85642 | G9: 85642 | AK9: =SUM($F9:AJ9) -> 85642
A10: Factura N° 106 Rosita Ñuñoa | B10: F106 | C10: 44676 | D10: 85642 | G10: 85642 | AK10: =SUM($F10:AJ10) -> 85642
A11: Factura N° 107 Fukai El Mañío | B11: F107 | C11: 44680 | D11: 93496 | N11: 93496 | AK11: =SUM($F11:AJ11) -> 93496
A12: Factura N° 108 RositaEl Mañío | B12: F108 | C12: 44680 | D12: 93496 | N12: 93496 | AK12: =SUM($F12:AJ12) -> 93496
A13: Factura N° 109 Rosita Bellavista | B13: F109 | C13: 44680 | D13: 44308 | N13: 44308 | AK13: =SUM($F13:AJ13) -> 44308
A14: Factura N° 110 Fukai Bellavista | B14: F110 | C14: 44680 | D14: 52162 | N14: 52162 | AK14: =SUM($F14:AJ14) -> 52162
A15: Factura N° 111 Fukai Bellavista | B15: F111 | C15: 44687 | D15: 44308 | E15: F | U15: 44308 | AK15: =SUM($F15:AJ15) -> 44308
A16: Factura N° 112 Rosita Bellavista | B16: F112 | C16: 44687 | D16: 44308 | E16: F | U16: 44308 | AK16: =SUM($F16:AJ16) -> 44308
A17: Factura N° 113 Marina | B17: F113 | C17: 44687 | D17: 293399 | E17: F | AK17: =SUM($F17:AJ17) -> 0
A18: Factura N° 114 Rosita Ñuñoa | B18: F114 | C18: 44694 | D18: 85642 | E18: F | AE18: 85642 | AK18: =SUM($F18:AJ18) -> 85642
A19: Factura N° 115 Rosita Bellavista | B19: F115 | C19: 44694 | D19: 44308 | E19: F | AE19: 44308 | AK19: =SUM($F19:AJ19) -> 44308
A20: Factura N° 116 Fukai El Mañío | B20: F116 | C20: 44694 | D20: 44308 | E20: F | AE20: 44308 | AK20: =SUM($F20:AJ20) -> 44308
A21: Factura N° 117 RositaEl Mañío | B21: F117 | C21: 44694 | D21: 44308 | E21: F | AE21: 44308 | AK21: =SUM($F21:AJ21) -> 44308
A22: Factura N° 119 Fukai El Mañío | B22: F119 | C22: 44701 | D22: 44308 | E22: F | AK22: =SUM($F22:AJ22) -> 0
A23: Factura N° 120 RositaEl Mañío | B23: F120 | C23: 44701 | D23: 85642 | E23: F | AK23: =SUM($F23:AJ23) -> 0
A24: Factura N° 121 Rosita Bellavista | B24: F121 | C24: 44708 | D24: 85642 | E24: F | AK24: =SUM($F24:AJ24) -> 0
A25: Factura N° 122 Fukai Bellavista | B25: F122 | C25: 44708 | D25: 44308 | E25: F | AK25: =SUM($F25:AJ25) -> 0
A26: MUTUO CORMORAN | D26: 3000000 | AC26: 3000000 | AK26: =SUM($F26:AJ26) -> 3000000
A27: Factura N° 121 Rosita Bellavista | B27: F121 | C27: 44708 | D27: 85642 | AK27: =SUM($F27:AJ27) -> 0
A28: Factura N° 122 Fukai Bellavista | B28: F122 | C28: 44708 | D28: 44308 | AK28: =SUM($F28:AJ28) -> 0
A29: Factura N° XX Sofía Jottar SPRITZ | B29: FXX | D29: 0 | E29: por facturar | AK29: =SUM($F29:AJ29) -> 0
AK31: =SUM(AK5:AK30) -> 3761928 | AL31: =+D33-AK31 -> -1779443
A32: TOTAL INGRESOS | D32: =SUM(D15:D28)-D26 -> 990431 | F32: =SUM(F5:F31) -> 0 | G32: =SUM(G5:G31) -> 171284 | H32: =SUM(H5:H31) -> 0 | I32: =SUM(I5:I31) -> 0 | J32: =SUM(J5:J31) -> 0 | K32: =SUM(K5:K31) -> 0 | L32: =SUM(L5:L31) -> 0 | M32: =SUM(M5:M31) -> 0 | ... AJ32: =SUM(AJ5:AJ31) -> 0
D33: =SUM(D5:D28)-D26 -> 1982485
A34: EGRESOS
A35: Boleta N° 135 EMS Remun Oct 2020 | B35: B135 | C35: 44706 | D35: 500000 | AC35: 500000 | AK35: =SUM($F35:AJ35) -> 500000
A36: Boleta N° 135 EMS Remun Nov 2020 | B36: B135 | C36: 44706 | D36: 500000 | AC36: 500000 | AK36: =SUM($F36:AJ36) -> 500000
A37: Boleta N° 135 EMS Remun Dic2020 | B37: B135 | C37: 44706 | D37: 500000 | AC37: 500000 | AK37: =SUM($F37:AJ37) -> 500000
A38: Boleta N° 135 EMS Remun Ene2021 | B38: B135 | C38: 44706 | D38: 500000 | AC38: 337079 | AD38: =500000-AC38 -> 162921 | AK38: =SUM($F38:AJ38) -> 500000
A39: Boleta N° xxx EMS Remun Feb2021 | B39: Bxxx | D39: 500000 | AK39: =SUM($F39:AJ39) -> 0
A40: Boleta N° xxx EMS Remun Marzo 2021 | B40: Bxxx | D40: 250000 | AK40: =SUM($F40:AJ40) -> 0
A41: Boleta N°xxx Remun Var. Gte.Ene a Dic 2021 | B41: Bxxx | D41: =+'MAR-21'!AK19*0.17+('ABR-21'!AJ18+'MAY-21'!AK16+'JUN-21'!AK14+'JUL-21'!AK28+'AGO-21'!AK22+'SEP-21'!AK14+'OCT-21'!AK19)*0.17 -> 309430.03 | AK41: =SUM($F41:AJ41) -> 0
A42: Boleta N°xxx Remun Var. Gte.Ene a Abr 2022 | B42: Bxxx | D42: =+'ABR-22'!D37 -> 242556.17 | AK42: =SUM($F42:AJ42) -> 0
A43: Boleta N°xxx Remun Var. Gte. May 2022 | B43: Bxxx | D43: =+(AK31-AK26)*0.17 -> 129527.76 | AK43: =SUM($F43:AJ43) -> 0
A44: Remuneración Fija Gte. Sept a Dic 2021 | D44: 2400000 | AK44: =SUM($F44:AJ44) -> 0
A45: Remuneración Fija Gte. Ene- Feb-Mar-Abr-May 2022 | D45: 2400000 | AK45: =SUM($F45:AJ45) -> 0
A46: PAC CREDITO CUOTA 5 DE 36 | C46: 44656 | D46: 13905 | J46: 13905 | AK46: =SUM($F46:AJ46) -> 13905
A47: UNIMARC AGUA +AZUCAR | B47: F34822151 | C47: 44683 | D47: 5318 | E47: TC EMS | P47: 5318 | AK47: =SUM($F47:AJ47) -> 5318 | AL47: CD
A48: Flete Vitacura- Bellavista -Vitacura | C48: 44683 | D48: =12.9*1050/9+1100+1068+1736 -> 5409 | P48: =12.9*1050/9+1100+1068+1736 -> 5409 | AK48: =SUM($F48:AJ48) -> 5409 | AL48: GAV
A49: Superm Diez muestra | B49: F12617 | C49: 44683 | D49: 5990 | E49: TC EMS | P49: 5990 | AK49: =SUM($F49:AJ49) -> 5990 | AL49: CD
A50: UNIMARC VINO BLANCO 5X2LT | B50: F34857768 | C50: 44685 | D50: 13599 | E50: TC EMS | P50: 13599 | AK50: =SUM($F50:AJ50) -> 13599 | AL50: CD
A51: FRIGO 3 grifos,sellos regulador, cilindro 4Kg | B51: F266 | C51: 44686 | D51: 240000 | I51: 120000 | J51: 120000 | AK51: =SUM($F51:AJ51) -> 240000 | AL51: AF
A52: SODIMAC mesa lateral para base torre clavos | B52: F118254584 | C52: 44686 | D52: 18579 | E52: TC EMS | P52: 18579 | AK52: =SUM($F52:AJ52) -> 18579 | AL52: AF
A53: Supermercado DIEZ 27 bot sin alcohol | B53: F12636 | C53: 44686 | D53: 161730 | E53: TC EMS | P53: 161730 | AK53: =SUM($F53:AJ53) -> 161730 | AL53: CD
A54: LIDER AGUA, AZUCAR | B54: F54392945 | C54: 44687 | D54: 4090 | E54: TC EMS | P54: 4090 | AK54: =SUM($F54:AJ54) -> 4090 | AL54: CD
A55: Supermercado DIEZ 1 bot sin alcohol | B55: F12662 | C55: 44691 | D55: 5990 | E55: TC EMS | P55: 5990 | AK55: =SUM($F55:AJ55) -> 5990 | AL55: CD
A56: F29 Abril | C56: 44692 | D56: 35573 | Q56: 35573 | AK56: =SUM($F56:AJ56) -> 35573 | AL56: GAV
A57: Gastos Mutuo | C57: 44693 | D57: 26000 | Q57: 26000 | AK57: =SUM($F57:AJ57) -> 26000 | AL57: GAV
A58: Freddy Quintana retorno 9 bolsas | C58: 44693 | D58: 9000 | Q58: 9000 | AK58: =SUM($F58:AJ58) -> 9000 | AL58: GAV
A59: Flete Vitacura-Tegualda- Bellavista -Vitacura | C59: 44694 | D59: =(15.3+3.1+14)*1150/9+1100+1068+1736 -> 8044 | P59: =(15.3+3.1+14)*1150/9+1100+1068+1736 -> 8044 | AK59: =SUM($F59:AJ59) -> 8044 | AL59: GAV
A60: UNIMARC AGUA +AZUCAR | B60: F34919005 | C60: 44694 | D60: 10470 | E60: TC EMS | AK60: =SUM($F60:AJ60) -> 0 | AL60: CD
A61: Flete Vitacura- El Mañío-Vitacura | C61: 44694 | D61: =6.9*2*1050/9+2000 -> 3610 | AK61: =SUM($F61:AJ61) -> 0 | AL61: GAV
A62: Flete Vitacura-Ñuñoa -Vitacura | C62: 44694 | D62: =13.9*1150/9+2000 -> 3776.1111 | AK62: =SUM($F62:AJ62) -> 0 | AL62: GAV
A63: Carlos Da silva retorno 4 bolsas | C63: 44697 | D63: 4000 | U63: 4000 | AK63: =SUM($F63:AJ63) -> 4000 | AL63: GAV
A64: UNIMARC AGUA +AZUCAR | B64: F34918205 | C64: 44701 | D64: 17007 | E64: TC EMS | AK64: =SUM($F64:AJ64) -> 0 | AL64: CD
A65: Flete Vitacura- El Mañío-Vitacura | C65: 44701 | D65: =6.9*2*1050/9+2000 -> 3610 | AK65: =SUM($F65:AJ65) -> 0 | AL65: GAV
A66: CLEAN ICE 2 KG | B66: F42796 | C66: 44707 | D66: 7140 | AE66: 7140 | AK66: =SUM($F66:AJ66) -> 7140 | AL66: GAV
A67: FUKAI SpA almuerzo J.Nazal | B67: F10323 | C67: 44707 | D67: =59420+5942 -> 65362 | E67: TC EMS | AK67: =SUM($F67:AJ67) -> 0 | AL67: GAV
A68: Flete Vitacura- Bellavista -Vitacura | C68: 44708 | D68: =12.9*1050/9+1100+1068+1736 -> 5409 | AK68: =SUM($F68:AJ68) -> 0 | AL68: GAV
A69: Previred | C69: 44711 | D69: 100316 | AG69: 100316 | AK69: =SUM($F69:AJ69) -> 100316 | AL69: GAV
AK70: =SUM($F70:AJ70) -> 0 | AM70: V | AN70: =+D32/1.19 -> 832294.96
AK71: =SUM($F71:AJ71) -> 0 | AM71: CV | AN71: =+SUMIF(AL34:AL75,"CD",D34:D75)/1.19 -> 188398.32
A72: Pago Mutuo 3 de 8 CORMORAN UF 95,69 | B72: =95.69/8 -> 11.96125 | C72: 44709 | D72: =+B72*D73 -> 390362.57 | AG72: 390362.57 | AK72: =SUM($F72:AJ72) -> 390362.57 | AL72: GF | AM72: UB | AN72: =+AN70-AN71 -> 643896.64
C73: UF | D73: 32635.6 | AL73: cxp | AM73: MB | AN73: =+AN72/AN70 -> 0.77363996
A74: TOTAL EGRESOS | D74: =SUM(D46:D72) -> 1164289.7 | F74: =SUM(F35:F73) -> 0 | G74: =SUM(G35:G73) -> 0 | H74: =SUM(H35:H73) -> 0 | I74: =SUM(I35:I73) -> 120000 | J74: =SUM(J35:J73) -> 133905 | K74: =SUM(K35:K73) -> 0 | L74: =SUM(L35:L73) -> 0 | M74: =SUM(M35:M73) -> 0 | ... AJ74: =SUM(AJ35:AJ73) -> 0 | AK74: =SUM(AK46:AK72) -> 1055045.6 | AL74: =+D74-AK74 -> 109244.11 | AM74: GAV | AN74: =+SUMIF(AL34:AL75,"GAV",D34:D75)/1.19 -> 232982.45
A75: SALDO FINAL | F75: =+F32+F3-F74 -> 107113.52 | G75: =+G32+G3-G74 -> 278397.52 | H75: =+H32+H3-H74 -> 278397.52 | I75: =+I32+I3-I74 -> 158397.52 | J75: =+J32+J3-J74 -> 24492.516 | K75: =+K32+K3-K74 -> 24492.516 | L75: =+L32+L3-L74 -> 24492.516 | M75: =+M32+M3-M74 -> 24492.516 | ... AI75: =+AI32+AI3-AI74 -> 813995.95 | AJ75: =+AJ3+AJ32-AJ74 -> 813995.95 | AL75: =+AL31-AL74+AJ75 -> -1074691.2 | AM75: EBITDA | AN75: =+AN72-AN74 -> 410914.19
AM76: GF+amort | AN76: =+SUMIF(AL34:AL75,"GF",D34:D75) -> 390362.57
AM77: AF | AN77: =+SUMIF(AL34:AL75,"AF",D34:D75)/1.19 -> 217293.28
AN78: =+AN75-AN76-AN77 -> -196741.66
G79: =5956.57*1.19 -> 7088.3183

Sheet Jun-22
B2: N° doc | C2: Fecha | D2: Monto Bruto | E2: Forma Pago | F2: 44713 | G2: 44714 | H2: 44715 | I2: 44716 | J2: 44717 | K2: 44718 | L2: 44719 | M2: 44720 | N2: 44721 | O2: 44722 | P2: 44723 | Q2: 44724 | R2: 44725 | S2: 44726 | T2: 44727 | U2: 44728 | V2: 44729 | W2: 44730 | X2: 44731 | Y2: 44732 | Z2: 44733 | AA2: 44734 | AB2: 44735 | AC2: 44736 | AD2: 44737 | AE2: 44738 | AF2: 44739 | AG2: 44740 | AH2: 44741 | AI2: 44742 | AK2: TOTAL
A3: SALDO INICIAL | F3: =+'May-22'!AJ75 -> 813995.95 | G3: =+F75 -> 813995.95 | H3: =+G75 -> 810245.95 | I3: =+H75 -> 810245.95 | J3: =+I75 -> 810245.95 | K3: =+J75 -> 810245.95 | L3: =+K75 -> 796340.95 | M3: =+L75 -> 796340.95 | N3: =+M75 -> 1021540.9 | ... AI3: =+AH75 -> 37224.808
A4: INGRESOS
A5: Factura N° 12 Sofía Jottar | B5: F12 | C5: 43882 | D5: 160200 | O5: 160200 | AK5: =SUM($F5:AJ5) -> 160200
A6: Factura N° 13 Sofía Jottar | B6: F13 | C6: 43889 | D6: 160200 | O6: 160200 | AK6: =SUM($F6:AJ6) -> 160200
A7: Factura N° 15 Sofía Jottar | B7: F15 | C7: 43904 | D7: 160200 | O7: 160200 | AK7: =SUM($F7:AJ7) -> 160200
A8: Factura N° 90 Los Laureles | B8: F90 | C8: 44618 | D8: 56708 | AK8: =SUM($F8:AJ8) -> 0
A9: Factura N° 113 Marina | B9: F113 | C9: 44687 | D9: 293399 | AK9: =SUM($F9:AJ9) -> 0
A10: Factura N° 119 Fukai El Mañío | B10: F119 | C10: 44701 | D10: 44308 | E10: F | M10: 44308 | AK10: =SUM($F10:AJ10) -> 44308
A11: Factura N° 120 RositaEl Mañío | B11: F120 | C11: 44701 | D11: 85642 | E11: F | M11: 85642 | AK11: =SUM($F11:AJ11) -> 85642
A12: Factura N° 121 Rosita Bellavista | B12: F121 | C12: 44708 | D12: 85642 | E12: F | M12: 85642 | AK12: =SUM($F12:AJ12) -> 85642
A13: Factura N° 122 Fukai Bellavista | B13: F122 | C13: 44708 | D13: 44308 | E13: F | M13: 44308 | AK13: =SUM($F13:AJ13) -> 44308
A14: Factura N° 123 Rosita Ñuñoa | B14: F123 | C14: 44715 | D14: 85642 | E14: F | Y14: 85642 | AK14: =SUM($F14:AJ14) -> 85642
A15: Factura N° 124 Fukai El Mañío | B15: F124 | C15: 44722 | D15: 85642 | E15: F | Y15: 85642 | AK15: =SUM($F15:AJ15) -> 85642
A16: Factura N° 125 RositaEl Mañío | B16: F125 | C16: 44722 | D16: 85642 | E16: F | Y16: 85642 | AK16: =SUM($F16:AJ16) -> 85642
A17: Factura N° 126 Rosita Bellavista | B17: F126 | C17: 44729 | D17: 85642 | E17: F | AK17: =SUM($F17:AJ17) -> 0
A18: Factura N° 127 Rosita Ñuñoa | B18: F127 | C18: 44735 | D18: 85642 | E18: F | AK18: =SUM($F18:AJ18) -> 0
A19: Factura N° 128 Rosita Bellavista | B19: F128 | C19: 44735 | D19: 85642 | E19: F | AK19: =SUM($F19:AJ19) -> 0
A20: Factura N° 129 RositaEl Mañío | B20: F129 | C20: 44736 | D20: 85642 | E20: F | AK20: =SUM($F20:AJ20) -> 0
A21: Factura N° 130 Fukai Bellavista | B21: F130 | C21: 44742 | D21: 168309 | E21: F | AK21: =SUM($F21:AJ21) -> 0
A22: Factura N° 131 Rosita Bellavista | B22: F131 | C22: 44742 | D22: 44308 | E22: F | AK22: =SUM($F22:AJ22) -> 0
AK23: =SUM($F23:AJ23) -> 0
AK24: =SUM($F24:AJ24) -> 0
AK25: =SUM($F25:AJ25) -> 0
A26: Factura N° XX Sofía Jottar SPRITZ | B26: FXX | D26: 0 | E26: por facturar | AK26: =SUM($F26:AJ26) -> 0
AK28: =SUM(AK5:AK27) -> 997426
A29: TOTAL INGRESOS | D29: =SUM(D14:D22) -> 812111 | F29: =SUM(F5:F28) -> 0 | G29: =SUM(G5:G28) -> 0 | H29: =SUM(H5:H28) -> 0 | I29: =SUM(I5:I28) -> 0 | J29: =SUM(J5:J28) -> 0 | K29: =SUM(K5:K28) -> 0 | L29: =SUM(L5:L28) -> 0 | M29: =SUM(M5:M28) -> 259900 | ... AJ29: =SUM(AJ5:AJ28) -> 0
A31: EGRESOS
A32: Boleta N° xxx EMS Remun Feb2021 | B32: Bxxx | D32: 500000 | AK32: =SUM($F32:AJ32) -> 0
A33: Boleta N° xxx EMS Remun Marzo 2021 | B33: B136 | D33: 250000 | N33: 250000 | AK33: =SUM($F33:AJ33) -> 250000
A34: Boleta N°xxx Remun Var. Gte.Ene a Dic 2021 | B34: Bxxx | D34: =+'MAR-21'!AK19*0.17+('ABR-21'!AJ18+'MAY-21'!AK16+'JUN-21'!AK14+'JUL-21'!AK28+'AGO-21'!AK22+'SEP-21'!AK14+'OCT-21'!AK19)*0.17 -> 309430.03 | AK34: =SUM($F34:AJ34) -> 0
A35: Boleta N°xxx Remun Var. Gte.Ene a Abr 2022 | B35: Bxxx | D35: =+'May-22'!D42 -> 242556.17 | AK35: =SUM($F35:AJ35) -> 0
A36: Boleta N°xxx Remun Var. Gte.May a Jun 2022 | B36: Bxxx | D36: =+'May-22'!D43+'Jun-22'!AK28*0.17 -> 299090.18 | AK36: =SUM($F36:AJ36) -> 0
A37: Remuneración Fija Gte. Sept a Dic 2021 | D37: 2400000 | AK37: =SUM($F37:AJ37) -> 0
A38: Remuneración Fija Gte. Ene- Feb-Mar-Abr-May 2022 | D38: 2400000 | AK38: =SUM($F38:AJ38) -> 0
A39: UNIMARC AGUA +AZUCAR | B39: F34919005 | C39: 44694 | D39: 10470 | E39: TC EMS | Y39: 10470 | AK39: =SUM($F39:AJ39) -> 10470
A40: Flete Vitacura- El Mañío-Vitacura | C40: 44694 | D40: =6.9*2*1050/9+2000 -> 3610 | Y40: =6.9*2*1050/9+2000 -> 3610 | AK40: =SUM($F40:AJ40) -> 3610
A41: Flete Vitacura-Ñuñoa -Vitacura | C41: 44694 | D41: =13.9*1150/9+2000 -> 3776.1111 | Y41: =13.9*1150/9+2000 -> 3776.1111 | AK41: =SUM($F41:AJ41) -> 3776.1111
A42: UNIMARC AGUA +AZUCAR | B42: F34918205 | C42: 44701 | D42: 17007 | E42: TC EMS | Y42: 17007 | AK42: =SUM($F42:AJ42) -> 17007
A43: Flete Vitacura- El Mañío-Vitacura | C43: 44701 | D43: =6.9*2*1050/9+2000 -> 3610 | Y43: =6.9*2*1050/9+2000 -> 3610 | AK43: =SUM($F43:AJ43) -> 3610
A44: FUKAI SpA almuerzo J.Nazal | B44: F10323 | C44: 44707 | D44: =59420+5942 -> 65362 | E44: TC EMS | Y44: =59420+5942 -> 65362 | AK44: =SUM($F44:AJ44) -> 65362
A45: Flete Vitacura- Bellavista -Vitacura | C45: 44708 | D45: =12.9*1050/9+1100+1068+1736 -> 5409 | Y45: =12.9*1050/9+1100+1068+1736 -> 5409 | AK45: =SUM($F45:AJ45) -> 5409
A46: UNIMARC AGUA +AZUCAR | B46: F35155155 | C46: 44711 | D46: 10150 | E46: TC EMS | AK46: =SUM($F46:AJ46) -> 0
A47: Flete muestra Tagler San Bdo-Vitacura | B47: F5132 | C47: 44714 | D47: 3750 | G47: 3750 | AK47: =SUM($F47:AJ47) -> 3750 | AL47: GAV
A48: Flete Vitacura-Ñuñoa -Vitacura | C48: 44715 | D48: =13.9*1150/9+2000 -> 3776.1111 | Y48: =13.9*1150/9+2000 -> 3776.1111 | AK48: =SUM($F48:AJ48) -> 3776.1111 | AL48: GAV
A49: PAC CREDITO CUOTA 6 DE 36 | C49: 44718 | D49: 13905 | K49: 13905 | AK49: =SUM($F49:AJ49) -> 13905 | AL49: GF
A50: CLEAN ICE 2X9 KG | B50: F43184 | C50: 44719 | D50: 34700 | M50: 34700 | AK50: =SUM($F50:AJ50) -> 34700 | AL50: GAV
A51: LANCER Valvula cilindro 9Kg accesorios | B51: F1075297 | C51: 44719 | D51: 40222 | O51: 40222 | AK51: =SUM($F51:AJ51) -> 40222 | AL51: AF
A52: LANCER 10 bib 10lt | B52: F1075347 | C52: 44722 | D52: 16660 | O52: 16660 | AK52: =SUM($F52:AJ52) -> 16660 | AL52: CD
A53: UNIMARC AGUA +AZUCAR | B53: F35049260 | C53: 44722 | D53: 12804 | Y53: 12804 | AK53: =SUM($F53:AJ53) -> 12804 | AL53: CD
A54: Flete Vitacura- El Mañío-Vitacura | C54: 44722 | D54: =6.9*2*1150/9+2000 -> 3763.3333 | Y54: =6.9*2*1150/9+2000 -> 3763.3333 | AK54: =SUM($F54:AJ54) -> 3763.3333 | AL54: GAV
A55: F29 Mayo | C55: 44725 | D55: 420060 | R55: 420060 | AK55: =SUM($F55:AJ55) -> 420060 | AL55: GAV
A56: LIDER AGUA +AZUCAR | B56: F54464485 | C56: 44728 | D56: 11610 | Y56: 11610 | AK56: =SUM($F56:AJ56) -> 11610 | AL56: CD
A57: Qatar Shop SpA Calentador eléctrico | B57: F2899 | C57: 44728 | D57: 30591 | Y57: 30591 | AK57: =SUM($F57:AJ57) -> 30591 | AL57: CD
A58: Flete Vitacura- Bellavista -Vitacura | C58: 44729 | D58: =12.9*1150/9+1100+1068+1736 -> 5552.3333 | Y58: =12.9*1150/9+1100+1068+1736 -> 5552.3333 | AK58: =SUM($F58:AJ58) -> 5552.3333 | AL58: GAV
A59: Danus Conexiones | B59: F260707 | C59: 44732 | D59: 18199 | Z59: 18199 | AK59: =SUM($F59:AJ59) -> 18199 | AL59: AF
A60: Flete Santiago-I de Maipo-Santiago | C60: 44735 | D60: =82*2*1150/9+6000 -> 26955.556 | AK60: =SUM($F60:AJ60) -> 0 | AL60: GAV
A61: LAS PIRCAS 200 lt genérico 20 lt BL | B61: F3102 | C61: 44735 | D61: =220*400*1.19 -> 104720 | AK61: =SUM($F61:AJ61) -> 0 | AL61: CD
A62: Flete Vitacura-Ñuñoa -Vitacura | C62: 44735 | D62: =13.9*1150/9+2000 -> 3776.1111 | AK62: =SUM($F62:AJ62) -> 0 | AL62: GAV
A63: Flete Vitacura- Bellavista -Vitacura | C63: 44735 | D63: =12.9*1150/9+1100+1068+1736 -> 5552.3333 | AK63: =SUM($F63:AJ63) -> 0 | AL63: GAV
A64: UNIMARC AGUA +AZUCAR | B64: F35113400 | C64: 44735 | D64: 14250 | E64: TC EMS | AK64: =SUM($F64:AJ64) -> 0 | AL64: CD
A65: Sabores | B65: F118078 | C65: 44736 | D65: 21322 | AB65: 21322 | AK65: =SUM($F65:AJ65) -> 21322 | AL65: CD
A66: Flete Vitacura- El Mañío-Vitacura | C66: 44736 | D66: =6.9*2*1150/9+2000 -> 3763.3333 | AK66: =SUM($F66:AJ66) -> 0 | AL66: GAV
A67: SODIMAC conctor rápido+macho maguera 1/2" | B67: F119359103 | C67: 44741 | D67: 3382 | E67: TC EMS | AK67: =SUM($F67:AJ67) -> 0 | AL67: AF
A68: Flete Vitacura- Bellavista -Vitacura | C68: 44742 | D68: =12.9*1150/9+1100+1068+1736 -> 5552.3333 | AK68: =SUM($F68:AJ68) -> 0 | AL68: GAV
A69: LANCER TJ.Guest 3/8 + 10 bolsas | B69: F1075446 | C69: 44741 | D69: =+(4300+1400*10)*1.19 -> 21777 | AK69: =SUM($F69:AJ69) -> 0 | AL69: AF
AM70: V | AN70: =+D32/1.19 -> 420168.07
A71: Pago Mutuo 4 de 8 CORMORAN UF 95,69 | B71: =95.69/8 -> 11.96125 | C71: 44740 | D71: =+B71*D73 -> 395445.26 | AG71: =+D71 -> 395445.26 | AK71: =SUM($F71:AJ71) -> 395445.26 | AL71: GF | AM71: CV | AN71: =+SUMIF(AL34:AL75,"CD",D34:D75)/1.19 -> 178115.13
A72: Pago Mutuo 1 de 8 CORMORAN UF 92,58 | B72: =92.58/8 -> 11.5725 | C72: 44740 | D72: =+B72*D73 -> 382592.98 | AG72: =+D72 -> 382592.98 | AK72: =SUM($F72:AJ72) -> 382592.98 | AL72: GF | AM72: UB | AN72: =+AN70-AN71 -> 242052.94
C73: UF | D73: 33060.53 | AM73: MB | AN73: =+AN72/AN70 -> 0.576086
A74: TOTAL EGRESOS | F74: =SUM(F32:F73) -> 0 | G74: =SUM(G32:G73) -> 3750 | H74: =SUM(H32:H73) -> 0 | I74: =SUM(I32:I73) -> 0 | J74: =SUM(J32:J73) -> 0 | K74: =SUM(K32:K73) -> 13905 | L74: =SUM(L32:L73) -> 0 | M74: =SUM(M32:M73) -> 34700 | ... AJ74: =SUM(AJ32:AJ73) -> 0 | AK74: =SUM(AK32:AK72) -> 1774197.1 | AM74: GAV | AN74: =+SUMIF(AL34:AL75,"GAV",D34:D75)/1.19 -> 434623.06
A75: SALDO FINAL | F75: =+F29+F3-F74 -> 813995.95 | G75: =+G29+G3-G74 -> 810245.95 | H75: =+H29+H3-H74 -> 810245.95 | I75: =+I29+I3-I74 -> 810245.95 | J75: =+J29+J3-J74 -> 810245.95 | K75: =+K29+K3-K74 -> 796340.95 | L75: =+L29+L3-L74 -> 796340.95 | M75: =+M29+M3-M74 -> 1021540.9 | ... AI75: =+AI29+AI3-AI74 -> 37224.808 | AJ75: =+AJ3+AJ29-AJ74 -> #VALUE! | AM75: EBITDA | AN75: =+AN72-AN74 -> -192570.12
AM76: GF+amort | AN76: =+SUMIF(AL34:AL75,"GF",D34:D75) -> 791943.25
AM77: AF | AN77: =+SUMIF(AL34:AL75,"AF",D34:D75)/1.19 -> 70235.294
AN78: =+AN75-AN76-AN77 -> -1054748.7

Sheet Jul-22
B2: N° doc | C2: Fecha | D2: Monto Bruto | E2: Forma Pago | F2: 44743 | G2: 44744 | H2: 44745 | I2: 44746 | J2: 44747 | K2: 44748 | L2: 44749 | M2: 44750 | N2: 44751 | O2: 44752 | P2: 44753 | Q2: 44754 | R2: 44755 | S2: 44756 | T2: 44757 | U2: 44758 | V2: 44759 | W2: 44760 | X2: 44761 | Y2: 44762 | Z2: 44763 | AA2: 44764 | AB2: 44765 | AC2: 44766 | AD2: 44767 | AE2: 44768 | AF2: 44769 | AG2: 44770 | AH2: 44771 | AI2: 44772 | AJ2: 44773 | AK2: TOTAL
A3: SALDO INICIAL | F3: =+'Jun-22'!AI75 -> 37224.808 | G3: =+F73 -> 37224.808 | H3: =+G73 -> 37224.808 | I3: =+H73 -> 37224.808 | J3: =+I73 -> 37224.808 | K3: =+J73 -> 23319.808 | L3: =+K73 -> 23319.808 | M3: =+L73 -> 23319.808 | N3: =+M73 -> 23319.808 | ... AJ3: =+AI73 -> 531613.92
A4: INGRESOS
A5: Factura N° 90 Los Laureles | B5: F90 | C5: 44618 | D5: 56708 | AK5: =SUM($F5:AJ5) -> 0
A6: Factura N° 113 Marina | B6: F113 | C6: 44687 | D6: 293399 | AF6: 102690 | AG6: 44010 | AK6: =SUM($F6:AJ6) -> 146700
A7: Factura N° 126 Rosita Bellavista | B7: F126 | C7: 44729 | D7: 85642 | E7: F | Q7: 85642 | AK7: =SUM($F7:AJ7) -> 85642
A8: Factura N° 127 Rosita Ñuñoa | B8: F127 | C8: 44735 | D8: 85642 | E8: F | Q8: 85642 | AK8: =SUM($F8:AJ8) -> 85642
A9: Factura N° 128 Rosita Bellavista | B9: F128 | C9: 44735 | D9: 85642 | E9: F | Q9: 85642 | AK9: =SUM($F9:AJ9) -> 85642
A10: Factura N° 129 RositaEl Mañío | B10: F129 | C10: 44736 | D10: 85642 | E10: F | Q10: 85642 | AK10: =SUM($F10:AJ10) -> 85642
A11: Factura N° 130 Fukai Bellavista | B11: F130 | C11: 44742 | D11: 168309 | E11: F | W11: 168309 | AK11: =SUM($F11:AJ11) -> 168309
A12: Factura N° 131 Rosita Bellavista | B12: F131 | C12: 44742 | D12: 44308 | E12: F | W12: 44308 | AK12: =SUM($F12:AJ12) -> 44308
A13: Factura N° 132 RositaEl Mañío | B13: F132 | C13: 44749 | D13: 85642 | E13: F | AD13: 85642 | AK13: =SUM($F13:AJ13) -> 85642
A14: Factura N° 133 FukaiEl Mañío | B14: F133 | C14: 44749 | D14: 85642 | E14: F | AD14: 85642 | AK14: =SUM($F14:AJ14) -> 85642
A15: Factura N° 135 Rosita Ñuñoa | B15: F135 | C15: 44750 | D15: 85642 | E15: F | AD15: 85642 | AK15: =SUM($F15:AJ15) -> 85642
A16: Factura N° 136 Fukai Bellavista | B16: F136 | C16: 44761 | D16: 85642 | E16: F | AJ16: 85642 | AK16: =SUM($F16:AJ16) -> 85642
A17: Factura N° 137 Rosita Bellavista | B17: F137 | C17: 44761 | D17: 85642 | E17: F | AJ17: 85642 | AK17: =SUM($F17:AJ17) -> 85642
A18: Factura N° 138 Fukai El Mañío | B18: F138 | C18: 44763 | D18: 85642 | E18: F | AJ18: 85642 | AK18: =SUM($F18:AJ18) -> 85642
A19: Factura N° 139 RositaEl Mañío | B19: F139 | C19: 44763 | D19: 85642 | E19: F | AJ19: 85642 | AK19: =SUM($F19:AJ19) -> 85642
A20: Factura N° 140 Rosita Ñuñoa | B20: F140 | C20: 44764 | D20: 85642 | E20: F | AJ20: 85642 | AK20: =SUM($F20:AJ20) -> 85642
A21: Factura N° 141 Rosita Bellavista | B21: F141 | C21: 44770 | D21: 85642 | E21: F | AK21: =SUM($F21:AJ21) -> 0
A22: Factura N° 142 Fukai Bellavista | B22: F142 | C22: 44770 | D22: 44308 | E22: F | AK22: =SUM($F22:AJ22) -> 0
A23: Factura N° 143 RositaEl Mañío | B23: F143 | C23: 44771 | D23: 138542 | E23: F | AK23: =SUM($F23:AJ23) -> 0
A24: Factura N° 144 Fukai El Mañío | B24: F144 | C24: 44771 | D24: 85642 | E24: F | AK24: =SUM($F24:AJ24) -> 0
AK26: =SUM($F26:AJ26) -> 0
AK27: =SUM(AK5:AK26) -> 1387021
A28: TOTAL INGRESOS | D28: =SUM(D13:D27) -> 1039270 | F28: =SUM(F5:F27) -> 0 | G28: =SUM(G5:G27) -> 0 | H28: =SUM(H5:H27) -> 0 | I28: =SUM(I5:I27) -> 0 | J28: =SUM(J5:J27) -> 0 | K28: =SUM(K5:K27) -> 0 | L28: =SUM(L5:L27) -> 0 | M28: =SUM(M5:M27) -> 0 | ... AJ28: =SUM(AJ5:AJ27) -> 428210
A30: EGRESOS
A32: Boleta N°xxx Remun Var. Gte.Ene a Dic 2021 | B32: Bxxx | D32: =+'MAR-21'!AK19*0.17+('ABR-21'!AJ18+'MAY-21'!AK16+'JUN-21'!AK14+'JUL-21'!AK28+'AGO-21'!AK22+'SEP-21'!AK14+'OCT-21'!AK19)*0.17 -> 309430.03 | AK32: =SUM($F32:AJ32) -> 0
A33: Boleta N°xxx Remun Var. Gte.Ene a Abr 2022 | B33: Bxxx | D33: =+'Jun-22'!D35 -> 242556.17 | AK33: =SUM($F33:AJ33) -> 0
A34: Boleta N°xxx Remun Var. Gte.May a Jul 2022 | B34: Bxxx | D34: =+'Jun-22'!D36+AK27*0.17 -> 534883.75 | AK34: =SUM($F34:AJ34) -> 0
A35: Boleta N° xxx EMS Remun Feb2021 | B35: Bxxx | D35: 500000 | AK35: =SUM($F35:AJ35) -> 0
A36: Remuneración Fija Gte. Sept a Dic 2021 | B36: Bxxx | D36: 2400000 | AK36: =SUM($F36:AJ36) -> 0
A37: Remuneración Fija Gte. Ene- Feb-Mar-Abr-May 2022 | B37: Bxxx | D37: 2400000 | AK37: =SUM($F37:AJ37) -> 0
A38: UNIMARC AGUA +AZUCAR | B38: F3496005 | C38: 44708 | D38: 5180 | E38: TC EMS | Q38: 5180 | AK38: =SUM($F38:AJ38) -> 5180
A39: UNIMARC AGUA +AZUCAR | B39: F35155155 | C39: 44711 | D39: 10150 | E39: TC EMS | Q39: 10150 | AK39: =SUM($F39:AJ39) -> 10150
A40: UNIMARC AGUA +AZUCAR | B40: F35032094 | C40: 44715 | D40: 10240 | E40: TC EMS | Q40: 10240 | AK40: =SUM($F40:AJ40) -> 10240
A41: Flete Santiago-I de Maipo-Santiago | C41: 44735 | D41: =82*2*1150/9+6000 -> 26955.556 | Q41: =82*2*1150/9+6000 -> 26955.556 | AK41: =SUM($F41:AJ41) -> 26955.556
A42: Flete Vitacura-Ñuñoa -Vitacura | C42: 44735 | D42: =13.9*1150/9+2000 -> 3776.1111 | Q42: =13.9*1150/9+2000 -> 3776.1111 | AK42: =SUM($F42:AJ42) -> 3776.1111
A43: Flete Vitacura- Bellavista -Vitacura | C43: 44735 | D43: =12.9*1150/9+1100+1068+1736 -> 5552.3333 | Q43: =12.9*1150/9+1100+1068+1736 -> 5552.3333 | AK43: =SUM($F43:AJ43) -> 5552.3333
A44: UNIMARC AGUA +AZUCAR | B44: F35113400 | C44: 44735 | D44: 14250 | E44: TC EMS | Q44: 14250 | AK44: =SUM($F44:AJ44) -> 14250
A45: Flete Vitacura- El Mañío-Vitacura | C45: 44736 | D45: =6.9*2*1150/9+2000 -> 3763.3333 | Q45: =6.9*2*1150/9+2000 -> 3763.3333 | AK45: =SUM($F45:AJ45) -> 3763.3333
A46: SODIMAC conctor rápido+macho maguera 1/2" | B46: F119359103 | C46: 44741 | D46: 3382 | E46: TC EMS | Q46: 3382 | AK46: =SUM($F46:AJ46) -> 3382
A47: Flete Vitacura- Bellavista -Vitacura | C47: 44742 | D47: =12.9*1150/9+1100+1068+1736 -> 5552.3333 | Q47: =12.9*1150/9+1100+1068+1736 -> 5552.3333 | AK47: =SUM($F47:AJ47) -> 5552.3333 | AL47: GAV
A48: PAC CREDITO CUOTA 7 DE 36 | B48: 1 | C48: 44747 | D48: 13905 | J48: 13905 | AK48: =SUM($F48:AJ48) -> 13905 | AL48: GF
A49: Flete Vitacura- El Mañío-Vitacura | C49: 44749 | D49: =6.9*2*1150/9+2000 -> 3763.3333 | Q49: =6.9*2*1150/9+2000 -> 3763.3333 | AK49: =SUM($F49:AJ49) -> 3763.3333 | AL49: GAV
A50: UNIMARC AGUA +AZUCAR | B50: F35169031 | C50: 44749 | D50: 7140 | E50: TC EMS | Q50: 7140 | AK50: =SUM($F50:AJ50) -> 7140 | AL50: CD
A51: Flete Vitacura-Ñuñoa -Vitacura | C51: 44750 | D51: =13.9*1150/9+2000 -> 3776.1111 | Q51: =13.9*1150/9+2000 -> 3776.1111 | AK51: =SUM($F51:AJ51) -> 3776.1111 | AL51: GAV
A52: UNIMARC AGUA +AZUCAR | B52: F35175478 | C52: 44750 | D52: 6116 | E52: TC EMS | Q52: 6116 | AK52: =SUM($F52:AJ52) -> 6116 | AL52: CD
A53: LAS PIRCAS 220 lt genérico 20 lt BL | B53: F3102 | C53: 44754 | D53: =220*400*1.19 -> 104720 | W53: =220*400*1.19 -> 104720 | AK53: =SUM($F53:AJ53) -> 104720 | AL53: CD
A54: Oficina Virtual S&T SpA | B54: F526 | C54: 44755 | D54: 58000 | Q54: 58000 | AK54: =SUM($F54:AJ54) -> 58000 | AL54: GAV
A55: F29 Junio | C55: 44755 | D55: 128854 | R55: 128854 | AK55: =SUM($F55:AJ55) -> 128854 | AL55: GAV
A56: Flete Vitacura- Bellavista -Vitacura | C56: 44761 | D56: =12.9*1150/9+1100+1068+1736 -> 5552.3333 | AD56: =12.9*1150/9+1100+1068+1736 -> 5552.3333 | AK56: =SUM($F56:AJ56) -> 5552.3333 | AL56: GAV
A57: UNIMARC AGUA +AZUCAR | B57: F35243710 | C57: 44761 | D57: 8734 | E57: TC EMS | AD57: 8734 | AK57: =SUM($F57:AJ57) -> 8734 | AL57: CD
A58: Freddy Quintana retorno 10 bolsas | C58: 44762 | D58: 10000 | Y58: 10000 | AK58: =SUM($F58:AJ58) -> 10000 | AL58: GAV
A59: LIDER AGUA+AZUCAR | B59: F54539836 | C59: 44763 | D59: 17520 | E59: TC EMS | AD59: 17520 | AK59: =SUM($F59:AJ59) -> 17520 | AL59: CD
A60: Flete Vitacura- El Mañío-Vitacura | C60: 44763 | D60: =6.9*2*1150/9+2000 -> 3763.3333 | AD60: =6.9*2*1150/9+2000 -> 3763.3333 | AK60: =SUM($F60:AJ60) -> 3763.3333 | AL60: GAV
A61: Flete Vitacura-Ñuñoa -Vitacura | C61: 44764 | D61: =13.9*1150/9+2000 -> 3776.1111 | AD61: =13.9*1150/9+2000 -> 3776.1111 | AK61: =SUM($F61:AJ61) -> 3776.1111 | AL61: GAV
A62: Flete Vitacura- Bellavista -Vitacura | C62: 44761 | D62: =12.9*1150/9+1100+1068+1736 -> 5552.3333 | AK62: =SUM($F62:AJ62) -> 0 | AL62: GAV
A63: Flete Vitacura- El Mañío-Vitacura | C63: 44763 | D63: =6.9*2*1150/9+2000 -> 3763.3333 | AK63: =SUM($F63:AJ63) -> 0 | AL63: GAV
A64: UNIMARC AGUA +AZUCAR | B64: F35290454 | C64: 44770 | D64: 9066 | E64: TC EMS | AK64: =SUM($F64:AJ64) -> 0 | AL64: CD
A65: UNIMARC AGUA +AZUCAR | B65: 84705 | C65: 44771 | D65: 7740 | E65: TC EMS | AK65: =SUM($F65:AJ65) -> 0 | AL65: CD
A66: LANCER 10 bib 10lt | B66: F1075668 | C66: 44771 | D66: 16660 | AK66: =SUM($F66:AJ66) -> 0 | AL66: CD | AM66: V | AN66: =+D28/1.19 -> 873336.13
AK67: =SUM($F67:AJ67) -> 0 | AM67: CV | AN67: =+SUMIF(AL30:AL71,"CD",D30:D71)/1.19 -> 149324.37
AK68: =SUM($F68:AJ68) -> 0 | AM68: UB | AN68: =+AN66-AN67 -> 724011.76
A69: Pago Mutuo 5 de 8 CORMORAN UF 95,69 | B69: =95.69/8 -> 11.96125 | C69: 44770 | D69: =+B69*D71 -> 397178.69 | AK69: =SUM($F69:AJ69) -> 0 | AL69: GF | AM69: MB | AN69: =+AN68/AN66 -> 0.82901845
A70: Pago Mutuo 2 de 8 CORMORAN UF 92,58 | B70: =92.58/8 -> 11.5725 | C70: 44770 | D70: =+B70*D71 -> 384270.07 | AK70: =SUM($F70:AJ70) -> 0 | AL70: GF | AM70: GAV | AN70: =+SUMIF(AL30:AL71,"GAV",D30:D71)/1.19 -> 195254.81
C71: UF | D71: 33205.45 | AM71: EBITDA | AN71: =+AN68-AN70 -> 528756.96
A72: TOTAL EGRESOS | F72: =SUM(F38:F71) -> 0 | G72: =SUM(G38:G71) -> 0 | H72: =SUM(H38:H71) -> 0 | I72: =SUM(I38:I71) -> 0 | J72: =SUM(J38:J71) -> 13905 | K72: =SUM(K38:K71) -> 0 | L72: =SUM(L38:L71) -> 0 | M72: =SUM(M38:M71) -> 0 | ... AJ72: =SUM(AJ38:AJ71) -> 0 | AK72: =SUM(AK33:AK70) -> 464421.89 | AM72: GF+amort | AN72: =+SUMIF(AL30:AL71,"GF",D30:D71) -> 795353.76
A73: SALDO FINAL | F73: =+F28+F3-F72 -> 37224.808 | G73: =+G28+G3-G72 -> 37224.808 | H73: =+H28+H3-H72 -> 37224.808 | I73: =+I28+I3-I72 -> 37224.808 | J73: =+J28+J3-J72 -> 23319.808 | K73: =+K28+K3-K72 -> 23319.808 | L73: =+L28+L3-L72 -> 23319.808 | M73: =+M28+M3-M72 -> 23319.808 | ... AI73: =+AI28+AI3-AI72 -> 531613.92 | AJ73: =+AJ3+AJ28-AJ72 -> 959823.92 | AM73: AF | AN73: =+SUMIF(AL30:AL71,"AF",D30:D71)/1.19 -> 0
AN74: =+AN71-AN72-AN73 -> -266596.8

Sheet Ago-22
B2: N° doc | C2: Fecha | D2: Monto Bruto | E2: Forma Pago | F2: 44774 | G2: 44775 | H2: 44776 | I2: 44777 | J2: 44778 | K2: 44779 | L2: 44780 | M2: 44781 | N2: 44782 | O2: 44783 | P2: 44784 | Q2: 44785 | R2: 44786 | S2: 44787 | T2: 44788 | U2: 44789 | V2: 44790 | W2: 44791 | X2: 44792 | Y2: 44793 | Z2: 44794 | AA2: 44795 | AB2: 44796 | AC2: 44797 | AD2: 44798 | AE2: 44799 | AF2: 44800 | AG2: 44801 | AH2: 44802 | AI2: 44803 | AJ2: 44804 | AK2: TOTAL
A3: SALDO INICIAL | F3: =+'Jul-22'!AJ73 -> 959823.92 | G3: =+F82 -> 959823.92 | H3: =+G82 -> 172935.81 | I3: =+H82 -> 172935.81 | J3: =+I82 -> 172935.81 | K3: =+J82 -> 159031.81 | L3: =+K82 -> 159031.81 | M3: =+L82 -> 159031.81 | N3: =+M82 -> 513165.81 | ... AJ3: =+AI82 -> 96515.818
A4: INGRESOS
A5: Factura N° 90 Los Laureles | B5: F90 | C5: 44618 | D5: 56708 | AK5: =SUM($F5:AJ5) -> 0
A6: Factura N° 113 Marina | B6: F113 | C6: 44687 | D6: =293399-'Jul-22'!AK6 -> 146699 | AK6: =SUM($F6:AJ6) -> 0
A7: Factura N° 141 Rosita Bellavista | B7: F141 | C7: 44770 | D7: 85642 | E7: F | M7: 85642 | AK7: =SUM($F7:AJ7) -> 85642
A8: Factura N° 142 Fukai Bellavista | B8: F142 | C8: 44770 | D8: 44308 | E8: F | M8: 44308 | AK8: =SUM($F8:AJ8) -> 44308
A9: Factura N° 143 RositaEl Mañío | B9: F143 | C9: 44771 | D9: 138542 | E9: F | M9: 138542 | AK9: =SUM($F9:AJ9) -> 138542
A10: Factura N° 144 Fukai El Mañío | B10: F144 | C10: 44771 | D10: 85642 | E10: F | M10: 85642 | AK10: =SUM($F10:AJ10) -> 85642
A11: Factura N° 145 Rosita Bellavista | B11: F145 | C11: 44778 | D11: 85642 | E11: F | AH11: 85642 | AK11: =SUM($F11:AJ11) -> 85642
A12: Factura N° 148 Rosita Ñuñoa | B12: F148 | C12: 44784 | D12: 85642 | E12: F | AH12: 85642 | AK12: =SUM($F12:AJ12) -> 85642
A13: Factura N° 149 Rosita Bellavista | B13: F149 | C13: 44784 | D13: 85642 | E13: F | AH13: 85642 | AK13: =SUM($F13:AJ13) -> 85642
A14: Factura N° 150 Fukai Bellavista | B14: F150 | C14: 44784 | D14: 44308 | E14: F | AH14: 44308 | AK14: =SUM($F14:AJ14) -> 44308
A15: Factura N° 151 Fukai El Mañío | B15: F151 | C15: 44784 | D15: 44308 | E15: F | AH15: 44308 | AK15: =SUM($F15:AJ15) -> 44308
A16: Factura N° 152 RositaEl Mañío | B16: F152 | C16: 44784 | D16: 85642 | E16: F | AH16: 85642 | AK16: =SUM($F16:AJ16) -> 85642
A17: Factura N° 153 Mall Dominicos | B17: F153 | C17: 44785 | D17: 208308 | E17: MD | AK17: =SUM($F17:AJ17) -> 0
A18: Factura N° 154 RositaEl Mañío | B18: F154 | C18: 44791 | D18: 85642 | E18: F | AH18: 85642 | AK18: =SUM($F18:AJ18) -> 85642
A19: Factura N° 155 Fukai El Mañío | B19: F155 | C19: 44791 | D19: 85642 | E19: F | AH19: 85642 | AK19: =SUM($F19:AJ19) -> 85642
A20: Factura N° 156 Rosita Bellavista | B20: F156 | C20: 44791 | D20: 85642 | E20: F | AH20: 85642 | AK20: =SUM($F20:AJ20) -> 85642
A21: Factura N° 157 Fukai Bellavista | B21: F157 | C21: 44791 | D21: 85642 | E21: F | AH21: 85642 | AK21: =SUM($F21:AJ21) -> 85642
A22: Factura N° 158 Rosita Ñuñoa | B22: F158 | C22: 44799 | D22: 85642 | E22: F | AK22: =SUM($F22:AJ22) -> 0
AK24: =SUM(AK5:AK21) -> 1127886
A25: TOTAL VENTAS DEL MES | D25: =SUM(D11:D24) -> 1067702 | F25: =SUM(F5:F24) -> 0 | G25: =SUM(G5:G24) -> 0 | H25: =SUM(H5:H24) -> 0 | I25: =SUM(I5:I24) -> 0 | J25: =SUM(J5:J24) -> 0 | K25: =SUM(K5:K24) -> 0 | L25: =SUM(L5:L24) -> 0 | M25: =SUM(M5:M24) -> 354134 | ... AJ25: =SUM(AJ5:AJ24) -> 0
A26: TOTAL VENTAS DEL MES + CXC apertura | D26: =SUM(D6:D22) -> 1568535
A27: EGRESOS
A29: Boleta N°xxx Remun Var. Gte.Ene a Dic 2021 | B29: B137 | D29: =+'MAR-21'!AK19*0.17+('ABR-21'!AJ18+'MAY-21'!AK16+'JUN-21'!AK14+'JUL-21'!AK28+'AGO-21'!AK22+'SEP-21'!AK14+'OCT-21'!AK19)*0.17 -> 309430.03 | O29: 309430.03 | AK29: =SUM($F29:AJ29) -> 309430.03
A30: Boleta N°xxx Remun Var. Gte.Ene a Abr 2022 | B30: Bxxx | D30: =+'Jun-22'!D35 -> 242556.17 | AK30: =SUM($F30:AJ30) -> 0
A31: Boleta N°xxx Remun Var. Gte.May a Jul 2022 | B31: Bxxx | D31: =+'Jul-22'!D34 -> 534883.75 | AK31: =SUM($F31:AJ31) -> 0
A32: Boleta N°xxx Remun Var. Gte. Ago 2022 | B32: Bxxx | C32: 44803 | D32: =+'Ago-22'!AK24*0.17 -> 191740.62 | AK32: =SUM($F32:AJ32) -> 0 | AL32: REM
A33: Boleta N° xxx EMS Remun Feb2021 | B33: Bxxx | D33: 500000 | AK33: =SUM($F33:AJ33) -> 0
A34: Remuneración Fija Gte. Sept a Dic 2021 | B34: Bxxx | D34: 2400000 | AK34: =SUM($F34:AJ34) -> 0
A35: Remuneración Fija Gte. Ene- Feb-Mar-Abr-May 2022 | B35: Bxxx | D35: 2400000 | AK35: =SUM($F35:AJ35) -> 0
A36: Flete Vitacura- Bellavista -Vitacura | C36: 44761 | D36: =12.9*1150/9+1100+1068+1736 -> 5552.3333 | AJ36: =12.9*1150/9+1100+1068+1736 -> 5552.3333 | AK36: =SUM($F36:AJ36) -> 5552.3333
A37: Flete Vitacura- El Mañío-Vitacura | C37: 44763 | D37: =6.9*2*1150/9+2000 -> 3763.3333 | AJ37: =6.9*2*1150/9+2000 -> 3763.3333 | AK37: =SUM($F37:AJ37) -> 3763.3333
A38: UNIMARC AGUA +AZUCAR | B38: F35290454 | C38: 44770 | D38: 9066 | E38: TC EMS | AJ38: 9066 | AK38: =SUM($F38:AJ38) -> 9066
A39: UNIMARC AGUA +AZUCAR | B39: 84705 | C39: 44771 | D39: 7740 | E39: TC EMS | AJ39: 7740 | AK39: =SUM($F39:AJ39) -> 7740
A40: LANCER 10 bib 10lt | B40: F1075668 | C40: 44771 | D40: 16660
A41: Lancer Bomba mangueras fittings | B41: F1075676 | C41: 44776 | D41: 142860 | AK41: =SUM($F41:AJ41) -> 0
